// class version 50.0 (50)
// access flags 0x20
class kotlin/text/StringsKt__StringsJVMKt extends kotlin/text/StringsKt__StringNumberConversionsKt {

  // compiled from: StringsJVM.kt

  @Lkotlin/Metadata;(mv={1, 7, 1}, k=5, xi=49, d1={"\u0000~\n\u0000\n\u0002\u0018\u0002\n\u0002\u0010\u000e\n\u0002\u0018\u0002\n\u0002\u0018\u0002\n\u0002\u0008\u0004\n\u0002\u0018\u0002\n\u0000\n\u0002\u0018\u0002\n\u0000\n\u0002\u0010\u0012\n\u0000\n\u0002\u0018\u0002\n\u0000\n\u0002\u0010\u0008\n\u0002\u0008\u0002\n\u0002\u0010\u0019\n\u0000\n\u0002\u0010\u0015\n\u0002\u0008\u0002\n\u0002\u0018\u0002\n\u0002\u0008\u0009\n\u0002\u0010\u000b\n\u0002\u0008\u0003\n\u0002\u0010\r\n\u0002\u0008\n\n\u0002\u0010\u0011\n\u0002\u0010\u0000\n\u0002\u0008\n\n\u0002\u0010\u000c\n\u0002\u0008\u0011\n\u0002\u0010 \n\u0000\n\u0002\u0018\u0002\n\u0002\u0008\u000e\u001a\u0011\u0010\u0007\u001a\u00020\u00022\u0006\u0010\u0008\u001a\u00020\u0009H\u0087\u0008\u001a\u0011\u0010\u0007\u001a\u00020\u00022\u0006\u0010\n\u001a\u00020\u000bH\u0087\u0008\u001a\u0011\u0010\u0007\u001a\u00020\u00022\u0006\u0010\u000c\u001a\u00020\rH\u0087\u0008\u001a\u0019\u0010\u0007\u001a\u00020\u00022\u0006\u0010\u000c\u001a\u00020\r2\u0006\u0010\u000e\u001a\u00020\u000fH\u0087\u0008\u001a!\u0010\u0007\u001a\u00020\u00022\u0006\u0010\u000c\u001a\u00020\r2\u0006\u0010\u0010\u001a\u00020\u00112\u0006\u0010\u0012\u001a\u00020\u0011H\u0087\u0008\u001a)\u0010\u0007\u001a\u00020\u00022\u0006\u0010\u000c\u001a\u00020\r2\u0006\u0010\u0010\u001a\u00020\u00112\u0006\u0010\u0012\u001a\u00020\u00112\u0006\u0010\u000e\u001a\u00020\u000fH\u0087\u0008\u001a\u0011\u0010\u0007\u001a\u00020\u00022\u0006\u0010\u0013\u001a\u00020\u0014H\u0087\u0008\u001a!\u0010\u0007\u001a\u00020\u00022\u0006\u0010\u0013\u001a\u00020\u00142\u0006\u0010\u0010\u001a\u00020\u00112\u0006\u0010\u0012\u001a\u00020\u0011H\u0087\u0008\u001a!\u0010\u0007\u001a\u00020\u00022\u0006\u0010\u0015\u001a\u00020\u00162\u0006\u0010\u0010\u001a\u00020\u00112\u0006\u0010\u0012\u001a\u00020\u0011H\u0087\u0008\u001a\u000c\u0010\u0017\u001a\u00020\u0002*\u00020\u0002H\u0007\u001a\u0014\u0010\u0017\u001a\u00020\u0002*\u00020\u00022\u0006\u0010\u0018\u001a\u00020\u0019H\u0007\u001a\u0015\u0010\u001a\u001a\u00020\u0011*\u00020\u00022\u0006\u0010\u001b\u001a\u00020\u0011H\u0087\u0008\u001a\u0015\u0010\u001c\u001a\u00020\u0011*\u00020\u00022\u0006\u0010\u001b\u001a\u00020\u0011H\u0087\u0008\u001a\u001d\u0010\u001d\u001a\u00020\u0011*\u00020\u00022\u0006\u0010\u001e\u001a\u00020\u00112\u0006\u0010\u001f\u001a\u00020\u0011H\u0087\u0008\u001a\u001c\u0010 \u001a\u00020\u0011*\u00020\u00022\u0006\u0010!\u001a\u00020\u00022\u0008\u0008\u0002\u0010\"\u001a\u00020#\u001a\u000c\u0010$\u001a\u00020\u0002*\u00020\u0014H\u0007\u001a \u0010$\u001a\u00020\u0002*\u00020\u00142\u0008\u0008\u0002\u0010%\u001a\u00020\u00112\u0008\u0008\u0002\u0010\u001f\u001a\u00020\u0011H\u0007\u001a\u0019\u0010&\u001a\u00020#*\u0004\u0018\u00010'2\u0008\u0010!\u001a\u0004\u0018\u00010'H\u0087\u0004\u001a \u0010&\u001a\u00020#*\u0004\u0018\u00010'2\u0008\u0010!\u001a\u0004\u0018\u00010'2\u0006\u0010\"\u001a\u00020#H\u0007\u001a\u0015\u0010&\u001a\u00020#*\u00020\u00022\u0006\u0010\n\u001a\u00020\u0009H\u0087\u0008\u001a\u0015\u0010&\u001a\u00020#*\u00020\u00022\u0006\u0010(\u001a\u00020'H\u0087\u0008\u001a\u000c\u0010)\u001a\u00020\u0002*\u00020\u0002H\u0007\u001a\u0014\u0010)\u001a\u00020\u0002*\u00020\u00022\u0006\u0010\u0018\u001a\u00020\u0019H\u0007\u001a\u000c\u0010*\u001a\u00020\u0002*\u00020\rH\u0007\u001a*\u0010*\u001a\u00020\u0002*\u00020\r2\u0008\u0008\u0002\u0010%\u001a\u00020\u00112\u0008\u0008\u0002\u0010\u001f\u001a\u00020\u00112\u0008\u0008\u0002\u0010+\u001a\u00020#H\u0007\u001a\u000c\u0010,\u001a\u00020\r*\u00020\u0002H\u0007\u001a*\u0010,\u001a\u00020\r*\u00020\u00022\u0008\u0008\u0002\u0010%\u001a\u00020\u00112\u0008\u0008\u0002\u0010\u001f\u001a\u00020\u00112\u0008\u0008\u0002\u0010+\u001a\u00020#H\u0007\u001a\u001c\u0010-\u001a\u00020#*\u00020\u00022\u0006\u0010.\u001a\u00020\u00022\u0008\u0008\u0002\u0010\"\u001a\u00020#\u001a \u0010/\u001a\u00020#*\u0004\u0018\u00010\u00022\u0008\u0010!\u001a\u0004\u0018\u00010\u00022\u0008\u0008\u0002\u0010\"\u001a\u00020#\u001a2\u00100\u001a\u00020\u0002*\u00020\u00022\u0006\u0010\u0018\u001a\u00020\u00192\u0016\u00101\u001a\u000c\u0012\u0008\u0008\u0001\u0012\u0004\u0018\u00010302\"\u0004\u0018\u000103H\u0087\u0008\u00a2\u0006\u0002\u00104\u001a6\u00100\u001a\u00020\u0002*\u00020\u00022\u0008\u0010\u0018\u001a\u0004\u0018\u00010\u00192\u0016\u00101\u001a\u000c\u0012\u0008\u0008\u0001\u0012\u0004\u0018\u00010302\"\u0004\u0018\u000103H\u0087\u0008\u00a2\u0006\u0004\u00085\u00104\u001a*\u00100\u001a\u00020\u0002*\u00020\u00022\u0016\u00101\u001a\u000c\u0012\u0008\u0008\u0001\u0012\u0004\u0018\u00010302\"\u0004\u0018\u000103H\u0087\u0008\u00a2\u0006\u0002\u00106\u001a:\u00100\u001a\u00020\u0002*\u00020\u00042\u0006\u0010\u0018\u001a\u00020\u00192\u0006\u00100\u001a\u00020\u00022\u0016\u00101\u001a\u000c\u0012\u0008\u0008\u0001\u0012\u0004\u0018\u00010302\"\u0004\u0018\u000103H\u0087\u0008\u00a2\u0006\u0002\u00107\u001a>\u00100\u001a\u00020\u0002*\u00020\u00042\u0008\u0010\u0018\u001a\u0004\u0018\u00010\u00192\u0006\u00100\u001a\u00020\u00022\u0016\u00101\u001a\u000c\u0012\u0008\u0008\u0001\u0012\u0004\u0018\u00010302\"\u0004\u0018\u000103H\u0087\u0008\u00a2\u0006\u0004\u00085\u00107\u001a2\u00100\u001a\u00020\u0002*\u00020\u00042\u0006\u00100\u001a\u00020\u00022\u0016\u00101\u001a\u000c\u0012\u0008\u0008\u0001\u0012\u0004\u0018\u00010302\"\u0004\u0018\u000103H\u0087\u0008\u00a2\u0006\u0002\u00108\u001a\r\u00109\u001a\u00020\u0002*\u00020\u0002H\u0087\u0008\u001a\n\u0010:\u001a\u00020#*\u00020'\u001a\r\u0010;\u001a\u00020\u0002*\u00020\u0002H\u0087\u0008\u001a\u0015\u0010;\u001a\u00020\u0002*\u00020\u00022\u0006\u0010\u0018\u001a\u00020\u0019H\u0087\u0008\u001a\u001d\u0010<\u001a\u00020\u0011*\u00020\u00022\u0006\u0010=\u001a\u00020>2\u0006\u0010?\u001a\u00020\u0011H\u0081\u0008\u001a\u001d\u0010<\u001a\u00020\u0011*\u00020\u00022\u0006\u0010@\u001a\u00020\u00022\u0006\u0010?\u001a\u00020\u0011H\u0081\u0008\u001a\u001d\u0010A\u001a\u00020\u0011*\u00020\u00022\u0006\u0010=\u001a\u00020>2\u0006\u0010?\u001a\u00020\u0011H\u0081\u0008\u001a\u001d\u0010A\u001a\u00020\u0011*\u00020\u00022\u0006\u0010@\u001a\u00020\u00022\u0006\u0010?\u001a\u00020\u0011H\u0081\u0008\u001a\u001d\u0010B\u001a\u00020\u0011*\u00020\u00022\u0006\u0010\u001b\u001a\u00020\u00112\u0006\u0010C\u001a\u00020\u0011H\u0087\u0008\u001a4\u0010D\u001a\u00020#*\u00020'2\u0006\u0010E\u001a\u00020\u00112\u0006\u0010!\u001a\u00020'2\u0006\u0010F\u001a\u00020\u00112\u0006\u0010\u0012\u001a\u00020\u00112\u0008\u0008\u0002\u0010\"\u001a\u00020#\u001a4\u0010D\u001a\u00020#*\u00020\u00022\u0006\u0010E\u001a\u00020\u00112\u0006\u0010!\u001a\u00020\u00022\u0006\u0010F\u001a\u00020\u00112\u0006\u0010\u0012\u001a\u00020\u00112\u0008\u0008\u0002\u0010\"\u001a\u00020#\u001a\u0012\u0010G\u001a\u00020\u0002*\u00020'2\u0006\u0010H\u001a\u00020\u0011\u001a$\u0010I\u001a\u00020\u0002*\u00020\u00022\u0006\u0010J\u001a\u00020>2\u0006\u0010K\u001a\u00020>2\u0008\u0008\u0002\u0010\"\u001a\u00020#\u001a$\u0010I\u001a\u00020\u0002*\u00020\u00022\u0006\u0010L\u001a\u00020\u00022\u0006\u0010M\u001a\u00020\u00022\u0008\u0008\u0002\u0010\"\u001a\u00020#\u001a$\u0010N\u001a\u00020\u0002*\u00020\u00022\u0006\u0010J\u001a\u00020>2\u0006\u0010K\u001a\u00020>2\u0008\u0008\u0002\u0010\"\u001a\u00020#\u001a$\u0010N\u001a\u00020\u0002*\u00020\u00022\u0006\u0010L\u001a\u00020\u00022\u0006\u0010M\u001a\u00020\u00022\u0008\u0008\u0002\u0010\"\u001a\u00020#\u001a\"\u0010O\u001a\u0008\u0012\u0004\u0012\u00020\u00020P*\u00020'2\u0006\u0010Q\u001a\u00020R2\u0008\u0008\u0002\u0010S\u001a\u00020\u0011\u001a\u001c\u0010T\u001a\u00020#*\u00020\u00022\u0006\u0010U\u001a\u00020\u00022\u0008\u0008\u0002\u0010\"\u001a\u00020#\u001a$\u0010T\u001a\u00020#*\u00020\u00022\u0006\u0010U\u001a\u00020\u00022\u0006\u0010%\u001a\u00020\u00112\u0008\u0008\u0002\u0010\"\u001a\u00020#\u001a\u0015\u0010V\u001a\u00020\u0002*\u00020\u00022\u0006\u0010%\u001a\u00020\u0011H\u0087\u0008\u001a\u001d\u0010V\u001a\u00020\u0002*\u00020\u00022\u0006\u0010%\u001a\u00020\u00112\u0006\u0010\u001f\u001a\u00020\u0011H\u0087\u0008\u001a\u0017\u0010W\u001a\u00020\r*\u00020\u00022\u0008\u0008\u0002\u0010\u000e\u001a\u00020\u000fH\u0087\u0008\u001a\r\u0010X\u001a\u00020\u0014*\u00020\u0002H\u0087\u0008\u001a3\u0010X\u001a\u00020\u0014*\u00020\u00022\u0006\u0010Y\u001a\u00020\u00142\u0008\u0008\u0002\u0010Z\u001a\u00020\u00112\u0008\u0008\u0002\u0010%\u001a\u00020\u00112\u0008\u0008\u0002\u0010\u001f\u001a\u00020\u0011H\u0087\u0008\u001a \u0010X\u001a\u00020\u0014*\u00020\u00022\u0008\u0008\u0002\u0010%\u001a\u00020\u00112\u0008\u0008\u0002\u0010\u001f\u001a\u00020\u0011H\u0007\u001a\r\u0010[\u001a\u00020\u0002*\u00020\u0002H\u0087\u0008\u001a\u0015\u0010[\u001a\u00020\u0002*\u00020\u00022\u0006\u0010\u0018\u001a\u00020\u0019H\u0087\u0008\u001a\u0017\u0010\\\u001a\u00020R*\u00020\u00022\u0008\u0008\u0002\u0010]\u001a\u00020\u0011H\u0087\u0008\u001a\r\u0010^\u001a\u00020\u0002*\u00020\u0002H\u0087\u0008\u001a\u0015\u0010^\u001a\u00020\u0002*\u00020\u00022\u0006\u0010\u0018\u001a\u00020\u0019H\u0087\u0008\u001a\r\u0010_\u001a\u00020\u0002*\u00020\u0002H\u0087\u0008\u001a\u0015\u0010_\u001a\u00020\u0002*\u00020\u00022\u0006\u0010\u0018\u001a\u00020\u0019H\u0087\u0008\"%\u0010\u0000\u001a\u0012\u0012\u0004\u0012\u00020\u00020\u0001j\u0008\u0012\u0004\u0012\u00020\u0002`\u0003*\u00020\u00048F\u00a2\u0006\u0006\u001a\u0004\u0008\u0005\u0010\u0006\u00a8\u0006`"}, d2={"CASE_INSENSITIVE_ORDER", "Ljava/util/Comparator;", "", "Lkotlin/Comparator;", "Lkotlin/String$Companion;", "getCASE_INSENSITIVE_ORDER", "(Lkotlin/jvm/internal/StringCompanionObject;)Ljava/util/Comparator;", "String", "stringBuffer", "Ljava/lang/StringBuffer;", "stringBuilder", "Ljava/lang/StringBuilder;", "bytes", "", "charset", "Ljava/nio/charset/Charset;", "offset", "", "length", "chars", "", "codePoints", "", "capitalize", "locale", "Ljava/util/Locale;", "codePointAt", "index", "codePointBefore", "codePointCount", "beginIndex", "endIndex", "compareTo", "other", "ignoreCase", "", "concatToString", "startIndex", "contentEquals", "", "charSequence", "decapitalize", "decodeToString", "throwOnInvalidSequence", "encodeToByteArray", "endsWith", "suffix", "equals", "format", "args", "", "", "(Ljava/lang/String;Ljava/util/Locale;[Ljava/lang/Object;)Ljava/lang/String;", "formatNullable", "(Ljava/lang/String;[Ljava/lang/Object;)Ljava/lang/String;", "(Lkotlin/jvm/internal/StringCompanionObject;Ljava/util/Locale;Ljava/lang/String;[Ljava/lang/Object;)Ljava/lang/String;", "(Lkotlin/jvm/internal/StringCompanionObject;Ljava/lang/String;[Ljava/lang/Object;)Ljava/lang/String;", "intern", "isBlank", "lowercase", "nativeIndexOf", "ch", "", "fromIndex", "str", "nativeLastIndexOf", "offsetByCodePoints", "codePointOffset", "regionMatches", "thisOffset", "otherOffset", "repeat", "n", "replace", "oldChar", "newChar", "oldValue", "newValue", "replaceFirst", "split", "", "regex", "Ljava/util/regex/Pattern;", "limit", "startsWith", "prefix", "substring", "toByteArray", "toCharArray", "destination", "destinationOffset", "toLowerCase", "toPattern", "flags", "toUpperCase", "uppercase", "kotlin-stdlib"}, xs="kotlin/text/StringsKt")

  // access flags 0x1A
  private final static String([III)Ljava/lang/String;
   L0
    ALOAD 0
    LDC "codePoints"
    INVOKESTATIC kotlin/jvm/internal/Intrinsics.checkNotNullParameter (Ljava/lang/Object;Ljava/lang/String;)V
   L1
    LINENUMBER 509 L1
    NEW java/lang/String
    DUP
    ALOAD 0
    ILOAD 1
    ILOAD 2
    INVOKESPECIAL java/lang/String.<init> ([III)V
    ARETURN
   L2
    LOCALVARIABLE codePoints [I L0 L2 0
    LOCALVARIABLE offset I L0 L2 1
    LOCALVARIABLE length I L0 L2 2
    MAXSTACK = 5
    MAXLOCALS = 3

  // access flags 0x1A
  private final static String([CII)Ljava/lang/String;
   L0
    ALOAD 0
    LDC "chars"
    INVOKESTATIC kotlin/jvm/internal/Intrinsics.checkNotNullParameter (Ljava/lang/Object;Ljava/lang/String;)V
   L1
    LINENUMBER 502 L1
    NEW java/lang/String
    DUP
    ALOAD 0
    ILOAD 1
    ILOAD 2
    INVOKESPECIAL java/lang/String.<init> ([CII)V
    ARETURN
   L2
    LOCALVARIABLE chars [C L0 L2 0
    LOCALVARIABLE offset I L0 L2 1
    LOCALVARIABLE length I L0 L2 2
    MAXSTACK = 5
    MAXLOCALS = 3

  // access flags 0x1A
  private final static String([C)Ljava/lang/String;
   L0
    ALOAD 0
    LDC "chars"
    INVOKESTATIC kotlin/jvm/internal/Intrinsics.checkNotNullParameter (Ljava/lang/Object;Ljava/lang/String;)V
   L1
    LINENUMBER 492 L1
    NEW java/lang/String
    DUP
    ALOAD 0
    INVOKESPECIAL java/lang/String.<init> ([C)V
    ARETURN
   L2
    LOCALVARIABLE chars [C L0 L2 0
    MAXSTACK = 3
    MAXLOCALS = 1

  // access flags 0x1A
  private final static String([B)Ljava/lang/String;
   L0
    ALOAD 0
    LDC "bytes"
    INVOKESTATIC kotlin/jvm/internal/Intrinsics.checkNotNullParameter (Ljava/lang/Object;Ljava/lang/String;)V
   L1
    LINENUMBER 485 L1
    NEW java/lang/String
    DUP
    ALOAD 0
    GETSTATIC kotlin/text/Charsets.UTF_8 : Ljava/nio/charset/Charset;
    INVOKESPECIAL java/lang/String.<init> ([BLjava/nio/charset/Charset;)V
    ARETURN
   L2
    LOCALVARIABLE bytes [B L0 L2 0
    MAXSTACK = 4
    MAXLOCALS = 1

  // access flags 0x1A
  private final static String([BII)Ljava/lang/String;
   L0
    ALOAD 0
    LDC "bytes"
    INVOKESTATIC kotlin/jvm/internal/Intrinsics.checkNotNullParameter (Ljava/lang/Object;Ljava/lang/String;)V
   L1
    LINENUMBER 477 L1
    NEW java/lang/String
    DUP
    ALOAD 0
    ILOAD 1
    ILOAD 2
    GETSTATIC kotlin/text/Charsets.UTF_8 : Ljava/nio/charset/Charset;
    INVOKESPECIAL java/lang/String.<init> ([BIILjava/nio/charset/Charset;)V
    ARETURN
   L2
    LOCALVARIABLE bytes [B L0 L2 0
    LOCALVARIABLE offset I L0 L2 1
    LOCALVARIABLE length I L0 L2 2
    MAXSTACK = 6
    MAXLOCALS = 3

  // access flags 0x1A
  private final static String([BLjava/nio/charset/Charset;)Ljava/lang/String;
   L0
    ALOAD 0
    LDC "bytes"
    INVOKESTATIC kotlin/jvm/internal/Intrinsics.checkNotNullParameter (Ljava/lang/Object;Ljava/lang/String;)V
    ALOAD 1
    LDC "charset"
    INVOKESTATIC kotlin/jvm/internal/Intrinsics.checkNotNullParameter (Ljava/lang/Object;Ljava/lang/String;)V
   L1
    LINENUMBER 465 L1
    NEW java/lang/String
    DUP
    ALOAD 0
    ALOAD 1
    INVOKESPECIAL java/lang/String.<init> ([BLjava/nio/charset/Charset;)V
    ARETURN
   L2
    LOCALVARIABLE bytes [B L0 L2 0
    LOCALVARIABLE charset Ljava/nio/charset/Charset; L0 L2 1
    MAXSTACK = 4
    MAXLOCALS = 2

  // access flags 0x1A
  private final static String([BIILjava/nio/charset/Charset;)Ljava/lang/String;
   L0
    ALOAD 0
    LDC "bytes"
    INVOKESTATIC kotlin/jvm/internal/Intrinsics.checkNotNullParameter (Ljava/lang/Object;Ljava/lang/String;)V
    ALOAD 3
    LDC "charset"
    INVOKESTATIC kotlin/jvm/internal/Intrinsics.checkNotNullParameter (Ljava/lang/Object;Ljava/lang/String;)V
   L1
    LINENUMBER 458 L1
    NEW java/lang/String
    DUP
    ALOAD 0
    ILOAD 1
    ILOAD 2
    ALOAD 3
    INVOKESPECIAL java/lang/String.<init> ([BIILjava/nio/charset/Charset;)V
    ARETURN
   L2
    LOCALVARIABLE bytes [B L0 L2 0
    LOCALVARIABLE offset I L0 L2 1
    LOCALVARIABLE length I L0 L2 2
    LOCALVARIABLE charset Ljava/nio/charset/Charset; L0 L2 3
    MAXSTACK = 6
    MAXLOCALS = 4

  // access flags 0x1A
  private final static String(Ljava/lang/StringBuilder;)Ljava/lang/String;
   L0
    ALOAD 0
    LDC "stringBuilder"
    INVOKESTATIC kotlin/jvm/internal/Intrinsics.checkNotNullParameter (Ljava/lang/Object;Ljava/lang/String;)V
   L1
    LINENUMBER 523 L1
    NEW java/lang/String
    DUP
    ALOAD 0
    INVOKESPECIAL java/lang/String.<init> (Ljava/lang/StringBuilder;)V
    ARETURN
   L2
    LOCALVARIABLE stringBuilder Ljava/lang/StringBuilder; L0 L2 0
    MAXSTACK = 3
    MAXLOCALS = 1

  // access flags 0x1A
  private final static String(Ljava/lang/StringBuffer;)Ljava/lang/String;
   L0
    ALOAD 0
    LDC "stringBuffer"
    INVOKESTATIC kotlin/jvm/internal/Intrinsics.checkNotNullParameter (Ljava/lang/Object;Ljava/lang/String;)V
   L1
    LINENUMBER 516 L1
    NEW java/lang/String
    DUP
    ALOAD 0
    INVOKESPECIAL java/lang/String.<init> (Ljava/lang/StringBuffer;)V
    ARETURN
   L2
    LOCALVARIABLE stringBuffer Ljava/lang/StringBuffer; L0 L2 0
    MAXSTACK = 3
    MAXLOCALS = 1

  // access flags 0x1A
  private final static lowercase(Ljava/lang/String;)Ljava/lang/String;
   L0
    ALOAD 0
    LDC "<this>"
    INVOKESTATIC kotlin/jvm/internal/Intrinsics.checkNotNullParameter (Ljava/lang/Object;Ljava/lang/String;)V
   L1
    LINENUMBER 168 L1
    ALOAD 0
    GETSTATIC java/util/Locale.ROOT : Ljava/util/Locale;
    INVOKEVIRTUAL java/lang/String.toLowerCase (Ljava/util/Locale;)Ljava/lang/String;
    DUP
    LDC "this as java.lang.String).toLowerCase(Locale.ROOT)"
    INVOKESTATIC kotlin/jvm/internal/Intrinsics.checkNotNullExpressionValue (Ljava/lang/Object;Ljava/lang/String;)V
    ARETURN
   L2
    LOCALVARIABLE $this$lowercase Ljava/lang/String; L0 L2 0
    MAXSTACK = 3
    MAXLOCALS = 1

  // access flags 0x1A
  private final static lowercase(Ljava/lang/String;Ljava/util/Locale;)Ljava/lang/String;
   L0
    ALOAD 0
    LDC "<this>"
    INVOKESTATIC kotlin/jvm/internal/Intrinsics.checkNotNullParameter (Ljava/lang/Object;Ljava/lang/String;)V
    ALOAD 1
    LDC "locale"
    INVOKESTATIC kotlin/jvm/internal/Intrinsics.checkNotNullParameter (Ljava/lang/Object;Ljava/lang/String;)V
   L1
    LINENUMBER 677 L1
    ALOAD 0
    ALOAD 1
    INVOKEVIRTUAL java/lang/String.toLowerCase (Ljava/util/Locale;)Ljava/lang/String;
    DUP
    LDC "this as java.lang.String).toLowerCase(locale)"
    INVOKESTATIC kotlin/jvm/internal/Intrinsics.checkNotNullExpressionValue (Ljava/lang/Object;Ljava/lang/String;)V
    ARETURN
   L2
    LOCALVARIABLE $this$lowercase Ljava/lang/String; L0 L2 0
    LOCALVARIABLE locale Ljava/util/Locale; L0 L2 1
    MAXSTACK = 3
    MAXLOCALS = 2

  // access flags 0x1A
  private final static toPattern(Ljava/lang/String;I)Ljava/util/regex/Pattern;
   L0
    ALOAD 0
    LDC "<this>"
    INVOKESTATIC kotlin/jvm/internal/Intrinsics.checkNotNullParameter (Ljava/lang/Object;Ljava/lang/String;)V
   L1
    LINENUMBER 714 L1
    ALOAD 0
    ILOAD 1
    INVOKESTATIC java/util/regex/Pattern.compile (Ljava/lang/String;I)Ljava/util/regex/Pattern;
    DUP
    LDC "compile(this, flags)"
    INVOKESTATIC kotlin/jvm/internal/Intrinsics.checkNotNullExpressionValue (Ljava/lang/Object;Ljava/lang/String;)V
    ARETURN
   L2
    LOCALVARIABLE $this$toPattern Ljava/lang/String; L0 L2 0
    LOCALVARIABLE flags I L0 L2 1
    MAXSTACK = 3
    MAXLOCALS = 2

  // access flags 0x1A
  private final static uppercase(Ljava/lang/String;)Ljava/lang/String;
   L0
    ALOAD 0
    LDC "<this>"
    INVOKESTATIC kotlin/jvm/internal/Intrinsics.checkNotNullParameter (Ljava/lang/Object;Ljava/lang/String;)V
   L1
    LINENUMBER 147 L1
    ALOAD 0
    GETSTATIC java/util/Locale.ROOT : Ljava/util/Locale;
    INVOKEVIRTUAL java/lang/String.toUpperCase (Ljava/util/Locale;)Ljava/lang/String;
    DUP
    LDC "this as java.lang.String).toUpperCase(Locale.ROOT)"
    INVOKESTATIC kotlin/jvm/internal/Intrinsics.checkNotNullExpressionValue (Ljava/lang/Object;Ljava/lang/String;)V
    ARETURN
   L2
    LOCALVARIABLE $this$uppercase Ljava/lang/String; L0 L2 0
    MAXSTACK = 3
    MAXLOCALS = 1

  // access flags 0x1A
  private final static uppercase(Ljava/lang/String;Ljava/util/Locale;)Ljava/lang/String;
   L0
    ALOAD 0
    LDC "<this>"
    INVOKESTATIC kotlin/jvm/internal/Intrinsics.checkNotNullParameter (Ljava/lang/Object;Ljava/lang/String;)V
    ALOAD 1
    LDC "locale"
    INVOKESTATIC kotlin/jvm/internal/Intrinsics.checkNotNullParameter (Ljava/lang/Object;Ljava/lang/String;)V
   L1
    LINENUMBER 698 L1
    ALOAD 0
    ALOAD 1
    INVOKEVIRTUAL java/lang/String.toUpperCase (Ljava/util/Locale;)Ljava/lang/String;
    DUP
    LDC "this as java.lang.String).toUpperCase(locale)"
    INVOKESTATIC kotlin/jvm/internal/Intrinsics.checkNotNullExpressionValue (Ljava/lang/Object;Ljava/lang/String;)V
    ARETURN
   L2
    LOCALVARIABLE $this$uppercase Ljava/lang/String; L0 L2 0
    LOCALVARIABLE locale Ljava/util/Locale; L0 L2 1
    MAXSTACK = 3
    MAXLOCALS = 2

  // access flags 0x1009
  public static synthetic split$default(Ljava/lang/CharSequence;Ljava/util/regex/Pattern;IILjava/lang/Object;)Ljava/util/List;
   L0
    LINENUMBER 392 L0
    ILOAD 3
    ICONST_2
    IAND
    IFEQ L1
    ICONST_0
    ISTORE 2
   L1
   FRAME FULL [java/lang/CharSequence java/util/regex/Pattern I I java/lang/Object] []
    ALOAD 0
    ALOAD 1
    ILOAD 2
    INVOKESTATIC kotlin/text/StringsKt.split (Ljava/lang/CharSequence;Ljava/util/regex/Pattern;I)Ljava/util/List;
    ARETURN
    MAXSTACK = 3
    MAXLOCALS = 5

  // access flags 0x1009
  public static synthetic startsWith$default(Ljava/lang/String;Ljava/lang/String;ZILjava/lang/Object;)Z
   L0
    LINENUMBER 416 L0
    ILOAD 3
    ICONST_2
    IAND
    IFEQ L1
    ICONST_0
    ISTORE 2
   L1
   FRAME FULL [java/lang/String java/lang/String I I java/lang/Object] []
    ALOAD 0
    ALOAD 1
    ILOAD 2
    INVOKESTATIC kotlin/text/StringsKt.startsWith (Ljava/lang/String;Ljava/lang/String;Z)Z
    IRETURN
    MAXSTACK = 3
    MAXLOCALS = 5

  // access flags 0x1009
  public static synthetic startsWith$default(Ljava/lang/String;Ljava/lang/String;IZILjava/lang/Object;)Z
   L0
    LINENUMBER 427 L0
    ILOAD 4
    ICONST_4
    IAND
    IFEQ L1
    ICONST_0
    ISTORE 3
   L1
   FRAME FULL [java/lang/String java/lang/String I I I java/lang/Object] []
    ALOAD 0
    ALOAD 1
    ILOAD 2
    ILOAD 3
    INVOKESTATIC kotlin/text/StringsKt.startsWith (Ljava/lang/String;Ljava/lang/String;IZ)Z
    IRETURN
    MAXSTACK = 4
    MAXLOCALS = 6

  // access flags 0x1009
  public static synthetic endsWith$default(Ljava/lang/String;Ljava/lang/String;ZILjava/lang/Object;)Z
   L0
    LINENUMBER 438 L0
    ILOAD 3
    ICONST_2
    IAND
    IFEQ L1
    ICONST_0
    ISTORE 2
   L1
   FRAME FULL [java/lang/String java/lang/String I I java/lang/Object] []
    ALOAD 0
    ALOAD 1
    ILOAD 2
    INVOKESTATIC kotlin/text/StringsKt.endsWith (Ljava/lang/String;Ljava/lang/String;Z)Z
    IRETURN
    MAXSTACK = 3
    MAXLOCALS = 5

  // access flags 0x1009
  public static synthetic replaceFirst$default(Ljava/lang/String;Ljava/lang/String;Ljava/lang/String;ZILjava/lang/Object;)Ljava/lang/String;
   L0
    LINENUMBER 123 L0
    ILOAD 4
    ICONST_4
    IAND
    IFEQ L1
    ICONST_0
    ISTORE 3
   L1
   FRAME FULL [java/lang/String java/lang/String java/lang/String I I java/lang/Object] []
    ALOAD 0
    ALOAD 1
    ALOAD 2
    ILOAD 3
    INVOKESTATIC kotlin/text/StringsKt.replaceFirst (Ljava/lang/String;Ljava/lang/String;Ljava/lang/String;Z)Ljava/lang/String;
    ARETURN
    MAXSTACK = 4
    MAXLOCALS = 6

  // access flags 0x1009
  public static synthetic replaceFirst$default(Ljava/lang/String;CCZILjava/lang/Object;)Ljava/lang/String;
   L0
    LINENUMBER 113 L0
    ILOAD 4
    ICONST_4
    IAND
    IFEQ L1
    ICONST_0
    ISTORE 3
   L1
   FRAME FULL [java/lang/String I I I I java/lang/Object] []
    ALOAD 0
    ILOAD 1
    ILOAD 2
    ILOAD 3
    INVOKESTATIC kotlin/text/StringsKt.replaceFirst (Ljava/lang/String;CCZ)Ljava/lang/String;
    ARETURN
    MAXSTACK = 4
    MAXLOCALS = 6

  // access flags 0x1009
  public static synthetic replace$default(Ljava/lang/String;CCZILjava/lang/Object;)Ljava/lang/String;
   L0
    LINENUMBER 68 L0
    ILOAD 4
    ICONST_4
    IAND
    IFEQ L1
    ICONST_0
    ISTORE 3
   L1
   FRAME FULL [java/lang/String I I I I java/lang/Object] []
    ALOAD 0
    ILOAD 1
    ILOAD 2
    ILOAD 3
    INVOKESTATIC kotlin/text/StringsKt.replace (Ljava/lang/String;CCZ)Ljava/lang/String;
    ARETURN
    MAXSTACK = 4
    MAXLOCALS = 6

  // access flags 0x1009
  public static synthetic replace$default(Ljava/lang/String;Ljava/lang/String;Ljava/lang/String;ZILjava/lang/Object;)Ljava/lang/String;
   L0
    LINENUMBER 86 L0
    ILOAD 4
    ICONST_4
    IAND
    IFEQ L1
    ICONST_0
    ISTORE 3
   L1
   FRAME FULL [java/lang/String java/lang/String java/lang/String I I java/lang/Object] []
    ALOAD 0
    ALOAD 1
    ALOAD 2
    ILOAD 3
    INVOKESTATIC kotlin/text/StringsKt.replace (Ljava/lang/String;Ljava/lang/String;Ljava/lang/String;Z)Ljava/lang/String;
    ARETURN
    MAXSTACK = 4
    MAXLOCALS = 6

  // access flags 0x1009
  public static synthetic equals$default(Ljava/lang/String;Ljava/lang/String;ZILjava/lang/Object;)Z
   L0
    LINENUMBER 53 L0
    ILOAD 3
    ICONST_2
    IAND
    IFEQ L1
    ICONST_0
    ISTORE 2
   L1
   FRAME FULL [java/lang/String java/lang/String I I java/lang/Object] []
    ALOAD 0
    ALOAD 1
    ILOAD 2
    INVOKESTATIC kotlin/text/StringsKt.equals (Ljava/lang/String;Ljava/lang/String;Z)Z
    IRETURN
    MAXSTACK = 3
    MAXLOCALS = 5

  // access flags 0x1A
  private final static nativeLastIndexOf(Ljava/lang/String;Ljava/lang/String;I)I
   L0
    ALOAD 0
    LDC "<this>"
    INVOKESTATIC kotlin/jvm/internal/Intrinsics.checkNotNullParameter (Ljava/lang/Object;Ljava/lang/String;)V
    ALOAD 1
    LDC "str"
    INVOKESTATIC kotlin/jvm/internal/Intrinsics.checkNotNullParameter (Ljava/lang/Object;Ljava/lang/String;)V
   L1
    LINENUMBER 42 L1
    ALOAD 0
    ALOAD 1
    ILOAD 2
    INVOKEVIRTUAL java/lang/String.lastIndexOf (Ljava/lang/String;I)I
    IRETURN
   L2
    LOCALVARIABLE $this$nativeLastIndexOf Ljava/lang/String; L0 L2 0
    LOCALVARIABLE str Ljava/lang/String; L0 L2 1
    LOCALVARIABLE fromIndex I L0 L2 2
    MAXSTACK = 3
    MAXLOCALS = 3

  // access flags 0x1A
  private final static nativeLastIndexOf(Ljava/lang/String;CI)I
   L0
    ALOAD 0
    LDC "<this>"
    INVOKESTATIC kotlin/jvm/internal/Intrinsics.checkNotNullParameter (Ljava/lang/Object;Ljava/lang/String;)V
   L1
    LINENUMBER 36 L1
    ALOAD 0
    ILOAD 1
   L2
    LINENUMBER 36 L2
    ILOAD 2
    INVOKEVIRTUAL java/lang/String.lastIndexOf (II)I
    IRETURN
   L3
    LOCALVARIABLE $this$nativeLastIndexOf Ljava/lang/String; L0 L3 0
    LOCALVARIABLE ch C L0 L3 1
    LOCALVARIABLE fromIndex I L0 L3 2
    MAXSTACK = 3
    MAXLOCALS = 3

  // access flags 0x19
  public final static decapitalize(Ljava/lang/String;)Ljava/lang/String;
  @Lkotlin/Deprecated;(message="Use replaceFirstChar instead.", replaceWith=@Lkotlin/ReplaceWith;(expression="replaceFirstChar { it.lowercase(Locale.getDefault()) }", imports={"java.util.Locale"}))
  @Lkotlin/DeprecatedSinceKotlin;(warningSince="1.5")
   L0
    ALOAD 0
    LDC "<this>"
    INVOKESTATIC kotlin/jvm/internal/Intrinsics.checkNotNullParameter (Ljava/lang/Object;Ljava/lang/String;)V
   L1
    LINENUMBER 773 L1
    ALOAD 0
    CHECKCAST java/lang/CharSequence
    INVOKEINTERFACE java/lang/CharSequence.length ()I (itf)
    IFLE L2
    ICONST_1
    GOTO L3
   L2
   FRAME FULL [java/lang/String] []
    ICONST_0
   L3
    LINENUMBER 773 L3
   FRAME FULL [java/lang/String] [I]
    IFEQ L4
    ALOAD 0
    ICONST_0
    INVOKEVIRTUAL java/lang/String.charAt (I)C
    INVOKESTATIC java/lang/Character.isLowerCase (C)Z
   L5
    LINENUMBER 773 L5
    IFNE L4
    NEW java/lang/StringBuilder
    DUP
    INVOKESPECIAL java/lang/StringBuilder.<init> ()V
    ALOAD 0
    ASTORE 1
    ICONST_0
    ISTORE 2
    ICONST_1
    ISTORE 3
    ALOAD 1
    ILOAD 2
    ILOAD 3
    INVOKEVIRTUAL java/lang/String.substring (II)Ljava/lang/String;
    DUP
    LDC "this as java.lang.String\u2026ing(startIndex, endIndex)"
    INVOKESTATIC kotlin/jvm/internal/Intrinsics.checkNotNullExpressionValue (Ljava/lang/Object;Ljava/lang/String;)V
    ASTORE 1
   L6
    LINENUMBER 773 L6
    ALOAD 1
    LDC "null cannot be cast to non-null type java.lang.String"
    INVOKESTATIC kotlin/jvm/internal/Intrinsics.checkNotNull (Ljava/lang/Object;Ljava/lang/String;)V
    ALOAD 1
    INVOKEVIRTUAL java/lang/String.toLowerCase ()Ljava/lang/String;
    DUP
    LDC "this as java.lang.String).toLowerCase()"
    INVOKESTATIC kotlin/jvm/internal/Intrinsics.checkNotNullExpressionValue (Ljava/lang/Object;Ljava/lang/String;)V
   L7
    LINENUMBER 773 L7
    INVOKEVIRTUAL java/lang/StringBuilder.append (Ljava/lang/String;)Ljava/lang/StringBuilder;
    ALOAD 0
    ASTORE 1
    ICONST_1
    ISTORE 2
    ALOAD 1
    ILOAD 2
    INVOKEVIRTUAL java/lang/String.substring (I)Ljava/lang/String;
    DUP
    LDC "this as java.lang.String).substring(startIndex)"
    INVOKESTATIC kotlin/jvm/internal/Intrinsics.checkNotNullExpressionValue (Ljava/lang/Object;Ljava/lang/String;)V
   L8
    LINENUMBER 773 L8
    INVOKEVIRTUAL java/lang/StringBuilder.append (Ljava/lang/String;)Ljava/lang/StringBuilder;
    INVOKEVIRTUAL java/lang/StringBuilder.toString ()Ljava/lang/String;
    GOTO L9
   L4
   FRAME FULL [java/lang/String] []
    ALOAD 0
   L9
   FRAME FULL [java/lang/String] [java/lang/String]
    ARETURN
   L10
    LOCALVARIABLE $this$decapitalize Ljava/lang/String; L0 L10 0
    MAXSTACK = 4
    MAXLOCALS = 4

  // access flags 0x19
  public final static decapitalize(Ljava/lang/String;Ljava/util/Locale;)Ljava/lang/String;
  @Lkotlin/Deprecated;(message="Use replaceFirstChar instead.", replaceWith=@Lkotlin/ReplaceWith;(expression="replaceFirstChar { it.lowercase(locale) }", imports={}))
  @Lkotlin/DeprecatedSinceKotlin;(warningSince="1.5")
   L0
    ALOAD 0
    LDC "<this>"
    INVOKESTATIC kotlin/jvm/internal/Intrinsics.checkNotNullParameter (Ljava/lang/Object;Ljava/lang/String;)V
    ALOAD 1
    LDC "locale"
    INVOKESTATIC kotlin/jvm/internal/Intrinsics.checkNotNullParameter (Ljava/lang/Object;Ljava/lang/String;)V
   L1
    LINENUMBER 786 L1
    ALOAD 0
    CHECKCAST java/lang/CharSequence
    INVOKEINTERFACE java/lang/CharSequence.length ()I (itf)
    IFLE L2
    ICONST_1
    GOTO L3
   L2
   FRAME FULL [java/lang/String java/util/Locale] []
    ICONST_0
   L3
    LINENUMBER 786 L3
   FRAME FULL [java/lang/String java/util/Locale] [I]
    IFEQ L4
    ALOAD 0
    ICONST_0
    INVOKEVIRTUAL java/lang/String.charAt (I)C
    INVOKESTATIC java/lang/Character.isLowerCase (C)Z
   L5
    LINENUMBER 786 L5
    IFNE L4
    NEW java/lang/StringBuilder
    DUP
    INVOKESPECIAL java/lang/StringBuilder.<init> ()V
    ALOAD 0
    ASTORE 2
    ICONST_0
    ISTORE 3
    ICONST_1
    ISTORE 4
    ALOAD 2
    ILOAD 3
    ILOAD 4
    INVOKEVIRTUAL java/lang/String.substring (II)Ljava/lang/String;
    DUP
    LDC "this as java.lang.String\u2026ing(startIndex, endIndex)"
    INVOKESTATIC kotlin/jvm/internal/Intrinsics.checkNotNullExpressionValue (Ljava/lang/Object;Ljava/lang/String;)V
    ASTORE 2
   L6
    LINENUMBER 786 L6
    ALOAD 2
    LDC "null cannot be cast to non-null type java.lang.String"
    INVOKESTATIC kotlin/jvm/internal/Intrinsics.checkNotNull (Ljava/lang/Object;Ljava/lang/String;)V
    ALOAD 2
    ALOAD 1
    INVOKEVIRTUAL java/lang/String.toLowerCase (Ljava/util/Locale;)Ljava/lang/String;
    DUP
    LDC "this as java.lang.String).toLowerCase(locale)"
    INVOKESTATIC kotlin/jvm/internal/Intrinsics.checkNotNullExpressionValue (Ljava/lang/Object;Ljava/lang/String;)V
   L7
    LINENUMBER 786 L7
    INVOKEVIRTUAL java/lang/StringBuilder.append (Ljava/lang/String;)Ljava/lang/StringBuilder;
    ALOAD 0
    ASTORE 2
    ICONST_1
    ISTORE 3
    ALOAD 2
    ILOAD 3
    INVOKEVIRTUAL java/lang/String.substring (I)Ljava/lang/String;
    DUP
    LDC "this as java.lang.String).substring(startIndex)"
    INVOKESTATIC kotlin/jvm/internal/Intrinsics.checkNotNullExpressionValue (Ljava/lang/Object;Ljava/lang/String;)V
   L8
    LINENUMBER 786 L8
    INVOKEVIRTUAL java/lang/StringBuilder.append (Ljava/lang/String;)Ljava/lang/StringBuilder;
    INVOKEVIRTUAL java/lang/StringBuilder.toString ()Ljava/lang/String;
    GOTO L9
   L4
   FRAME FULL [java/lang/String java/util/Locale] []
    ALOAD 0
   L9
   FRAME FULL [java/lang/String java/util/Locale] [java/lang/String]
    ARETURN
   L10
    LOCALVARIABLE $this$decapitalize Ljava/lang/String; L0 L10 0
    LOCALVARIABLE locale Ljava/util/Locale; L0 L10 1
    MAXSTACK = 4
    MAXLOCALS = 5

  // access flags 0x9A
  private final static varargs formatNullable(Lkotlin/jvm/internal/StringCompanionObject;Ljava/util/Locale;Ljava/lang/String;[Ljava/lang/Object;)Ljava/lang/String;
   L0
    ALOAD 0
    LDC "<this>"
    INVOKESTATIC kotlin/jvm/internal/Intrinsics.checkNotNullParameter (Ljava/lang/Object;Ljava/lang/String;)V
    ALOAD 2
    LDC "format"
    INVOKESTATIC kotlin/jvm/internal/Intrinsics.checkNotNullParameter (Ljava/lang/Object;Ljava/lang/String;)V
    ALOAD 3
    LDC "args"
    INVOKESTATIC kotlin/jvm/internal/Intrinsics.checkNotNullParameter (Ljava/lang/Object;Ljava/lang/String;)V
   L1
    LINENUMBER 379 L1
    ALOAD 1
    ALOAD 2
    ALOAD 3
    ALOAD 3
    ARRAYLENGTH
    INVOKESTATIC java/util/Arrays.copyOf ([Ljava/lang/Object;I)[Ljava/lang/Object;
    INVOKESTATIC java/lang/String.format (Ljava/util/Locale;Ljava/lang/String;[Ljava/lang/Object;)Ljava/lang/String;
    DUP
    LDC "format(locale, format, *args)"
    INVOKESTATIC kotlin/jvm/internal/Intrinsics.checkNotNullExpressionValue (Ljava/lang/Object;Ljava/lang/String;)V
    ARETURN
   L2
    LOCALVARIABLE $this$format Lkotlin/jvm/internal/StringCompanionObject; L0 L2 0
    LOCALVARIABLE locale Ljava/util/Locale; L0 L2 1
    LOCALVARIABLE format Ljava/lang/String; L0 L2 2
    LOCALVARIABLE args [Ljava/lang/Object; L0 L2 3
    MAXSTACK = 4
    MAXLOCALS = 4

  // access flags 0x9A
  private final static varargs formatNullable(Ljava/lang/String;Ljava/util/Locale;[Ljava/lang/Object;)Ljava/lang/String;
   L0
    ALOAD 0
    LDC "<this>"
    INVOKESTATIC kotlin/jvm/internal/Intrinsics.checkNotNullParameter (Ljava/lang/Object;Ljava/lang/String;)V
    ALOAD 2
    LDC "args"
    INVOKESTATIC kotlin/jvm/internal/Intrinsics.checkNotNullParameter (Ljava/lang/Object;Ljava/lang/String;)V
   L1
    LINENUMBER 359 L1
    ALOAD 1
    ALOAD 0
    ALOAD 2
    ALOAD 2
    ARRAYLENGTH
    INVOKESTATIC java/util/Arrays.copyOf ([Ljava/lang/Object;I)[Ljava/lang/Object;
    INVOKESTATIC java/lang/String.format (Ljava/util/Locale;Ljava/lang/String;[Ljava/lang/Object;)Ljava/lang/String;
    DUP
    LDC "format(locale, this, *args)"
    INVOKESTATIC kotlin/jvm/internal/Intrinsics.checkNotNullExpressionValue (Ljava/lang/Object;Ljava/lang/String;)V
    ARETURN
   L2
    LOCALVARIABLE $this$format Ljava/lang/String; L0 L2 0
    LOCALVARIABLE locale Ljava/util/Locale; L0 L2 1
    LOCALVARIABLE args [Ljava/lang/Object; L0 L2 2
    MAXSTACK = 4
    MAXLOCALS = 3

  // access flags 0x19
  public final static decodeToString([BIIZ)Ljava/lang/String;
   L0
    ALOAD 0
    LDC "<this>"
    INVOKESTATIC kotlin/jvm/internal/Intrinsics.checkNotNullParameter (Ljava/lang/Object;Ljava/lang/String;)V
   L1
    LINENUMBER 243 L1
    GETSTATIC kotlin/collections/AbstractList.Companion : Lkotlin/collections/AbstractList$Companion;
    ILOAD 1
    ILOAD 2
    ALOAD 0
    ARRAYLENGTH
    INVOKEVIRTUAL kotlin/collections/AbstractList$Companion.checkBoundsIndexes$kotlin_stdlib (III)V
   L2
    LINENUMBER 245 L2
    ILOAD 3
    IFNE L3
    NEW java/lang/String
    DUP
    ALOAD 0
    ILOAD 1
   L4
    LINENUMBER 246 L4
    ILOAD 2
    ILOAD 1
    ISUB
    GETSTATIC kotlin/text/Charsets.UTF_8 : Ljava/nio/charset/Charset;
    INVOKESPECIAL java/lang/String.<init> ([BIILjava/nio/charset/Charset;)V
   L5
    LINENUMBER 246 L5
    ARETURN
   L3
    LINENUMBER 249 L3
   FRAME FULL [[B I I I] []
    GETSTATIC kotlin/text/Charsets.UTF_8 : Ljava/nio/charset/Charset;
    INVOKEVIRTUAL java/nio/charset/Charset.newDecoder ()Ljava/nio/charset/CharsetDecoder;
   L6
    LINENUMBER 250 L6
    GETSTATIC java/nio/charset/CodingErrorAction.REPORT : Ljava/nio/charset/CodingErrorAction;
    INVOKEVIRTUAL java/nio/charset/CharsetDecoder.onMalformedInput (Ljava/nio/charset/CodingErrorAction;)Ljava/nio/charset/CharsetDecoder;
   L7
    LINENUMBER 251 L7
    GETSTATIC java/nio/charset/CodingErrorAction.REPORT : Ljava/nio/charset/CodingErrorAction;
    INVOKEVIRTUAL java/nio/charset/CharsetDecoder.onUnmappableCharacter (Ljava/nio/charset/CodingErrorAction;)Ljava/nio/charset/CharsetDecoder;
   L8
    LINENUMBER 249 L8
    ASTORE 4
   L9
    LINENUMBER 253 L9
    ALOAD 4
    ALOAD 0
    ILOAD 1
    ILOAD 2
    ILOAD 1
    ISUB
    INVOKESTATIC java/nio/ByteBuffer.wrap ([BII)Ljava/nio/ByteBuffer;
    INVOKEVIRTUAL java/nio/charset/CharsetDecoder.decode (Ljava/nio/ByteBuffer;)Ljava/nio/CharBuffer;
    INVOKEVIRTUAL java/nio/CharBuffer.toString ()Ljava/lang/String;
    DUP
    LDC "decoder.decode(ByteBuffe\u2026- startIndex)).toString()"
    INVOKESTATIC kotlin/jvm/internal/Intrinsics.checkNotNullExpressionValue (Ljava/lang/Object;Ljava/lang/String;)V
    ARETURN
   L10
    LOCALVARIABLE decoder Ljava/nio/charset/CharsetDecoder; L9 L10 4
    LOCALVARIABLE $this$decodeToString [B L0 L10 0
    LOCALVARIABLE startIndex I L0 L10 1
    LOCALVARIABLE endIndex I L0 L10 2
    LOCALVARIABLE throwOnInvalidSequence Z L0 L10 3
    MAXSTACK = 6
    MAXLOCALS = 5

  // access flags 0x19
  public final static decodeToString([B)Ljava/lang/String;
   L0
    ALOAD 0
    LDC "<this>"
    INVOKESTATIC kotlin/jvm/internal/Intrinsics.checkNotNullParameter (Ljava/lang/Object;Ljava/lang/String;)V
   L1
    LINENUMBER 221 L1
    NEW java/lang/String
    DUP
    ALOAD 0
    GETSTATIC kotlin/text/Charsets.UTF_8 : Ljava/nio/charset/Charset;
    INVOKESPECIAL java/lang/String.<init> ([BLjava/nio/charset/Charset;)V
   L2
    LINENUMBER 221 L2
    ARETURN
   L3
    LOCALVARIABLE $this$decodeToString [B L0 L3 0
    MAXSTACK = 4
    MAXLOCALS = 1

  // access flags 0x19
  // signature (Lkotlin/jvm/internal/StringCompanionObject;)Ljava/util/Comparator<Ljava/lang/String;>;
  // declaration: java.util.Comparator<java.lang.String> getCASE_INSENSITIVE_ORDER(kotlin.jvm.internal.StringCompanionObject)
  public final static getCASE_INSENSITIVE_ORDER(Lkotlin/jvm/internal/StringCompanionObject;)Ljava/util/Comparator;
   L0
    ALOAD 0
    LDC "<this>"
    INVOKESTATIC kotlin/jvm/internal/Intrinsics.checkNotNullParameter (Ljava/lang/Object;Ljava/lang/String;)V
   L1
    LINENUMBER 824 L1
    GETSTATIC java/lang/String.CASE_INSENSITIVE_ORDER : Ljava/util/Comparator;
    DUP
    LDC "CASE_INSENSITIVE_ORDER"
    INVOKESTATIC kotlin/jvm/internal/Intrinsics.checkNotNullExpressionValue (Ljava/lang/Object;Ljava/lang/String;)V
    ARETURN
   L2
    LOCALVARIABLE $this$CASE_INSENSITIVE_ORDER Lkotlin/jvm/internal/StringCompanionObject; L0 L2 0
    MAXSTACK = 3
    MAXLOCALS = 1

  // access flags 0x19
  public final static concatToString([CII)Ljava/lang/String;
   L0
    ALOAD 0
    LDC "<this>"
    INVOKESTATIC kotlin/jvm/internal/Intrinsics.checkNotNullParameter (Ljava/lang/Object;Ljava/lang/String;)V
   L1
    LINENUMBER 192 L1
    GETSTATIC kotlin/collections/AbstractList.Companion : Lkotlin/collections/AbstractList$Companion;
    ILOAD 1
    ILOAD 2
    ALOAD 0
    ARRAYLENGTH
    INVOKEVIRTUAL kotlin/collections/AbstractList$Companion.checkBoundsIndexes$kotlin_stdlib (III)V
    NEW java/lang/String
    DUP
    ALOAD 0
    ILOAD 1
   L2
    LINENUMBER 193 L2
    ILOAD 2
    ILOAD 1
    ISUB
    INVOKESPECIAL java/lang/String.<init> ([CII)V
   L3
    LINENUMBER 193 L3
    ARETURN
   L4
    LOCALVARIABLE $this$concatToString [C L0 L4 0
    LOCALVARIABLE startIndex I L0 L4 1
    LOCALVARIABLE endIndex I L0 L4 2
    MAXSTACK = 6
    MAXLOCALS = 3

  // access flags 0x19
  public final static concatToString([C)Ljava/lang/String;
   L0
    ALOAD 0
    LDC "<this>"
    INVOKESTATIC kotlin/jvm/internal/Intrinsics.checkNotNullParameter (Ljava/lang/Object;Ljava/lang/String;)V
   L1
    LINENUMBER 176 L1
    NEW java/lang/String
    DUP
    ALOAD 0
    INVOKESPECIAL java/lang/String.<init> ([C)V
   L2
    LINENUMBER 176 L2
    ARETURN
   L3
    LOCALVARIABLE $this$concatToString [C L0 L3 0
    MAXSTACK = 3
    MAXLOCALS = 1

  // access flags 0x1A
  private final static nativeIndexOf(Ljava/lang/String;CI)I
   L0
    ALOAD 0
    LDC "<this>"
    INVOKESTATIC kotlin/jvm/internal/Intrinsics.checkNotNullParameter (Ljava/lang/Object;Ljava/lang/String;)V
   L1
    LINENUMBER 24 L1
    ALOAD 0
    ILOAD 1
   L2
    LINENUMBER 24 L2
    ILOAD 2
    INVOKEVIRTUAL java/lang/String.indexOf (II)I
    IRETURN
   L3
    LOCALVARIABLE $this$nativeIndexOf Ljava/lang/String; L0 L3 0
    LOCALVARIABLE ch C L0 L3 1
    LOCALVARIABLE fromIndex I L0 L3 2
    MAXSTACK = 3
    MAXLOCALS = 3

  // access flags 0x1A
  private final static nativeIndexOf(Ljava/lang/String;Ljava/lang/String;I)I
   L0
    ALOAD 0
    LDC "<this>"
    INVOKESTATIC kotlin/jvm/internal/Intrinsics.checkNotNullParameter (Ljava/lang/Object;Ljava/lang/String;)V
    ALOAD 1
    LDC "str"
    INVOKESTATIC kotlin/jvm/internal/Intrinsics.checkNotNullParameter (Ljava/lang/Object;Ljava/lang/String;)V
   L1
    LINENUMBER 30 L1
    ALOAD 0
    ALOAD 1
    ILOAD 2
    INVOKEVIRTUAL java/lang/String.indexOf (Ljava/lang/String;I)I
    IRETURN
   L2
    LOCALVARIABLE $this$nativeIndexOf Ljava/lang/String; L0 L2 0
    LOCALVARIABLE str Ljava/lang/String; L0 L2 1
    LOCALVARIABLE fromIndex I L0 L2 2
    MAXSTACK = 3
    MAXLOCALS = 3

  // access flags 0x19
  public final static encodeToByteArray(Ljava/lang/String;)[B
   L0
    ALOAD 0
    LDC "<this>"
    INVOKESTATIC kotlin/jvm/internal/Intrinsics.checkNotNullParameter (Ljava/lang/Object;Ljava/lang/String;)V
   L1
    LINENUMBER 264 L1
    ALOAD 0
    ASTORE 1
    GETSTATIC kotlin/text/Charsets.UTF_8 : Ljava/nio/charset/Charset;
    ALOAD 1
    SWAP
    INVOKEVIRTUAL java/lang/String.getBytes (Ljava/nio/charset/Charset;)[B
    DUP
    LDC "this as java.lang.String).getBytes(charset)"
    INVOKESTATIC kotlin/jvm/internal/Intrinsics.checkNotNullExpressionValue (Ljava/lang/Object;Ljava/lang/String;)V
   L2
    LINENUMBER 264 L2
    ARETURN
   L3
    LOCALVARIABLE $this$encodeToByteArray Ljava/lang/String; L0 L3 0
    MAXSTACK = 3
    MAXLOCALS = 2

  // access flags 0x19
  public final static encodeToByteArray(Ljava/lang/String;IIZ)[B
   L0
    ALOAD 0
    LDC "<this>"
    INVOKESTATIC kotlin/jvm/internal/Intrinsics.checkNotNullParameter (Ljava/lang/Object;Ljava/lang/String;)V
   L1
    LINENUMBER 286 L1
    GETSTATIC kotlin/collections/AbstractList.Companion : Lkotlin/collections/AbstractList$Companion;
    ILOAD 1
    ILOAD 2
    ALOAD 0
    INVOKEVIRTUAL java/lang/String.length ()I
    INVOKEVIRTUAL kotlin/collections/AbstractList$Companion.checkBoundsIndexes$kotlin_stdlib (III)V
   L2
    LINENUMBER 288 L2
    ILOAD 3
    IFNE L3
   L4
    LINENUMBER 289 L4
    ALOAD 0
    ILOAD 1
    ILOAD 2
    INVOKEVIRTUAL java/lang/String.substring (II)Ljava/lang/String;
    DUP
    LDC "this as java.lang.String\u2026ing(startIndex, endIndex)"
    INVOKESTATIC kotlin/jvm/internal/Intrinsics.checkNotNullExpressionValue (Ljava/lang/Object;Ljava/lang/String;)V
    ASTORE 4
   L5
    LINENUMBER 289 L5
    GETSTATIC kotlin/text/Charsets.UTF_8 : Ljava/nio/charset/Charset;
    ASTORE 5
    ALOAD 4
    LDC "null cannot be cast to non-null type java.lang.String"
    INVOKESTATIC kotlin/jvm/internal/Intrinsics.checkNotNull (Ljava/lang/Object;Ljava/lang/String;)V
    ALOAD 4
    ALOAD 5
    INVOKEVIRTUAL java/lang/String.getBytes (Ljava/nio/charset/Charset;)[B
    DUP
    LDC "this as java.lang.String).getBytes(charset)"
    INVOKESTATIC kotlin/jvm/internal/Intrinsics.checkNotNullExpressionValue (Ljava/lang/Object;Ljava/lang/String;)V
   L6
    LINENUMBER 289 L6
    ARETURN
   L3
    LINENUMBER 292 L3
   FRAME FULL [java/lang/String I I I] []
    GETSTATIC kotlin/text/Charsets.UTF_8 : Ljava/nio/charset/Charset;
    INVOKEVIRTUAL java/nio/charset/Charset.newEncoder ()Ljava/nio/charset/CharsetEncoder;
   L7
    LINENUMBER 293 L7
    GETSTATIC java/nio/charset/CodingErrorAction.REPORT : Ljava/nio/charset/CodingErrorAction;
    INVOKEVIRTUAL java/nio/charset/CharsetEncoder.onMalformedInput (Ljava/nio/charset/CodingErrorAction;)Ljava/nio/charset/CharsetEncoder;
   L8
    LINENUMBER 294 L8
    GETSTATIC java/nio/charset/CodingErrorAction.REPORT : Ljava/nio/charset/CodingErrorAction;
    INVOKEVIRTUAL java/nio/charset/CharsetEncoder.onUnmappableCharacter (Ljava/nio/charset/CodingErrorAction;)Ljava/nio/charset/CharsetEncoder;
   L9
    LINENUMBER 292 L9
    ASTORE 4
   L10
    LINENUMBER 296 L10
    ALOAD 4
    ALOAD 0
    CHECKCAST java/lang/CharSequence
    ILOAD 1
    ILOAD 2
    INVOKESTATIC java/nio/CharBuffer.wrap (Ljava/lang/CharSequence;II)Ljava/nio/CharBuffer;
    INVOKEVIRTUAL java/nio/charset/CharsetEncoder.encode (Ljava/nio/CharBuffer;)Ljava/nio/ByteBuffer;
    ASTORE 5
   L11
    LINENUMBER 297 L11
    ALOAD 5
    INVOKEVIRTUAL java/nio/ByteBuffer.hasArray ()Z
    IFEQ L12
    ALOAD 5
    INVOKEVIRTUAL java/nio/ByteBuffer.arrayOffset ()I
    IFNE L12
    ALOAD 5
    INVOKEVIRTUAL java/nio/ByteBuffer.remaining ()I
    ALOAD 5
    INVOKEVIRTUAL java/nio/ByteBuffer.array ()[B
    DUP
    INVOKESTATIC kotlin/jvm/internal/Intrinsics.checkNotNull (Ljava/lang/Object;)V
    ARRAYLENGTH
    IF_ICMPNE L12
   L13
    LINENUMBER 298 L13
    ALOAD 5
    INVOKEVIRTUAL java/nio/ByteBuffer.array ()[B
   L14
    LINENUMBER 297 L14
    DUP
    LDC "{\n        byteBuffer.array()\n    }"
    INVOKESTATIC kotlin/jvm/internal/Intrinsics.checkNotNullExpressionValue (Ljava/lang/Object;Ljava/lang/String;)V
    GOTO L15
   L12
    LINENUMBER 300 L12
   FRAME FULL [java/lang/String I I I java/nio/charset/CharsetEncoder java/nio/ByteBuffer] []
    ALOAD 5
    INVOKEVIRTUAL java/nio/ByteBuffer.remaining ()I
    NEWARRAY T_BYTE
    ASTORE 6
    ALOAD 6
    ASTORE 7
   L16
    LINENUMBER 828 L16
    ICONST_0
    ISTORE 8
   L17
    LINENUMBER 300 L17
    ALOAD 5
    ALOAD 7
    INVOKEVIRTUAL java/nio/ByteBuffer.get ([B)Ljava/nio/ByteBuffer;
    POP
   L18
    LINENUMBER 300 L18
    ALOAD 6
   L15
    LINENUMBER 297 L15
   FRAME FULL [java/lang/String I I I java/nio/charset/CharsetEncoder java/nio/ByteBuffer] [[B]
    ARETURN
   L19
    LOCALVARIABLE $i$a$-also-StringsKt__StringsJVMKt$encodeToByteArray$1 I L17 L18 8
    LOCALVARIABLE it [B L16 L18 7
    LOCALVARIABLE encoder Ljava/nio/charset/CharsetEncoder; L10 L19 4
    LOCALVARIABLE byteBuffer Ljava/nio/ByteBuffer; L11 L19 5
    LOCALVARIABLE $this$encodeToByteArray Ljava/lang/String; L0 L19 0
    LOCALVARIABLE startIndex I L0 L19 1
    LOCALVARIABLE endIndex I L0 L19 2
    LOCALVARIABLE throwOnInvalidSequence Z L0 L19 3
    MAXSTACK = 4
    MAXLOCALS = 9

  // access flags 0x1009
  public static synthetic concatToString$default([CIIILjava/lang/Object;)Ljava/lang/String;
   L0
    LINENUMBER 191 L0
    ILOAD 3
    ICONST_1
    IAND
    IFEQ L1
    ICONST_0
    ISTORE 1
   L1
   FRAME FULL [[C I I I java/lang/Object] []
    ILOAD 3
    ICONST_2
    IAND
    IFEQ L2
    ALOAD 0
    ARRAYLENGTH
    ISTORE 2
   L2
   FRAME FULL [[C I I I java/lang/Object] []
    ALOAD 0
    ILOAD 1
    ILOAD 2
    INVOKESTATIC kotlin/text/StringsKt.concatToString ([CII)Ljava/lang/String;
    ARETURN
    MAXSTACK = 3
    MAXLOCALS = 5

  // access flags 0x1009
  public static synthetic toCharArray$default(Ljava/lang/String;IIILjava/lang/Object;)[C
   L0
    LINENUMBER 208 L0
    ILOAD 3
    ICONST_1
    IAND
    IFEQ L1
    ICONST_0
    ISTORE 1
   L1
   FRAME FULL [java/lang/String I I I java/lang/Object] []
    ILOAD 3
    ICONST_2
    IAND
    IFEQ L2
    ALOAD 0
    INVOKEVIRTUAL java/lang/String.length ()I
    ISTORE 2
   L2
   FRAME FULL [java/lang/String I I I java/lang/Object] []
    ALOAD 0
    ILOAD 1
    ILOAD 2
    INVOKESTATIC kotlin/text/StringsKt.toCharArray (Ljava/lang/String;II)[C
    ARETURN
    MAXSTACK = 3
    MAXLOCALS = 5

  // access flags 0x1008
  static synthetic toCharArray$default(Ljava/lang/String;[CIIIILjava/lang/Object;)[C
   L0
    LINENUMBER 319 L0
    ILOAD 5
    ICONST_2
    IAND
    IFEQ L1
   L2
    LINENUMBER 321 L2
    ICONST_0
    ISTORE 2
   L1
    LINENUMBER 319 L1
   FRAME FULL [java/lang/String [C I I I I java/lang/Object] []
    ILOAD 5
    ICONST_4
    IAND
    IFEQ L3
   L4
    LINENUMBER 322 L4
    ICONST_0
    ISTORE 3
   L3
    LINENUMBER 319 L3
   FRAME FULL [java/lang/String [C I I I I java/lang/Object] []
    ILOAD 5
    BIPUSH 8
    IAND
    IFEQ L5
   L6
    LINENUMBER 323 L6
    ALOAD 0
    INVOKEVIRTUAL java/lang/String.length ()I
    ISTORE 4
   L5
    LINENUMBER 319 L5
   FRAME FULL [java/lang/String [C I I I I java/lang/Object] []
    ALOAD 0
    LDC "<this>"
    INVOKESTATIC kotlin/jvm/internal/Intrinsics.checkNotNullParameter (Ljava/lang/Object;Ljava/lang/String;)V
    ALOAD 1
    LDC "destination"
    INVOKESTATIC kotlin/jvm/internal/Intrinsics.checkNotNullParameter (Ljava/lang/Object;Ljava/lang/String;)V
   L7
    LINENUMBER 325 L7
    ALOAD 0
    ILOAD 3
    ILOAD 4
    ALOAD 1
    ILOAD 2
    INVOKEVIRTUAL java/lang/String.getChars (II[CI)V
   L8
    LINENUMBER 326 L8
    ALOAD 1
    ARETURN
   L9
    LOCALVARIABLE $this$toCharArray_u24default Ljava/lang/String; L0 L9 0
    LOCALVARIABLE destination [C L0 L9 1
    LOCALVARIABLE destinationOffset I L0 L9 2
    LOCALVARIABLE startIndex I L0 L9 3
    LOCALVARIABLE endIndex I L0 L9 4
    MAXSTACK = 5
    MAXLOCALS = 7

  // access flags 0x1009
  public static synthetic decodeToString$default([BIIZILjava/lang/Object;)Ljava/lang/String;
   L0
    LINENUMBER 238 L0
    ILOAD 4
    ICONST_1
    IAND
    IFEQ L1
   L2
    LINENUMBER 239 L2
    ICONST_0
    ISTORE 1
   L1
    LINENUMBER 238 L1
   FRAME FULL [[B I I I I java/lang/Object] []
    ILOAD 4
    ICONST_2
    IAND
    IFEQ L3
   L4
    LINENUMBER 240 L4
    ALOAD 0
    ARRAYLENGTH
    ISTORE 2
   L3
    LINENUMBER 238 L3
   FRAME FULL [[B I I I I java/lang/Object] []
    ILOAD 4
    ICONST_4
    IAND
    IFEQ L5
   L6
    LINENUMBER 241 L6
    ICONST_0
    ISTORE 3
   L5
    LINENUMBER 238 L5
   FRAME FULL [[B I I I I java/lang/Object] []
    ALOAD 0
    ILOAD 1
    ILOAD 2
    ILOAD 3
    INVOKESTATIC kotlin/text/StringsKt.decodeToString ([BIIZ)Ljava/lang/String;
    ARETURN
    MAXSTACK = 4
    MAXLOCALS = 6

  // access flags 0x1009
  public static synthetic encodeToByteArray$default(Ljava/lang/String;IIZILjava/lang/Object;)[B
   L0
    LINENUMBER 281 L0
    ILOAD 4
    ICONST_1
    IAND
    IFEQ L1
   L2
    LINENUMBER 282 L2
    ICONST_0
    ISTORE 1
   L1
    LINENUMBER 281 L1
   FRAME FULL [java/lang/String I I I I java/lang/Object] []
    ILOAD 4
    ICONST_2
    IAND
    IFEQ L3
   L4
    LINENUMBER 283 L4
    ALOAD 0
    INVOKEVIRTUAL java/lang/String.length ()I
    ISTORE 2
   L3
    LINENUMBER 281 L3
   FRAME FULL [java/lang/String I I I I java/lang/Object] []
    ILOAD 4
    ICONST_4
    IAND
    IFEQ L5
   L6
    LINENUMBER 284 L6
    ICONST_0
    ISTORE 3
   L5
    LINENUMBER 281 L5
   FRAME FULL [java/lang/String I I I I java/lang/Object] []
    ALOAD 0
    ILOAD 1
    ILOAD 2
    ILOAD 3
    INVOKESTATIC kotlin/text/StringsKt.encodeToByteArray (Ljava/lang/String;IIZ)[B
    ARETURN
    MAXSTACK = 4
    MAXLOCALS = 6

  // access flags 0x1009
  public static synthetic compareTo$default(Ljava/lang/String;Ljava/lang/String;ZILjava/lang/Object;)I
   L0
    LINENUMBER 550 L0
    ILOAD 3
    ICONST_2
    IAND
    IFEQ L1
    ICONST_0
    ISTORE 2
   L1
   FRAME FULL [java/lang/String java/lang/String I I java/lang/Object] []
    ALOAD 0
    ALOAD 1
    ILOAD 2
    INVOKESTATIC kotlin/text/StringsKt.compareTo (Ljava/lang/String;Ljava/lang/String;Z)I
    IRETURN
    MAXSTACK = 3
    MAXLOCALS = 5

  // access flags 0x1009
  public static synthetic regionMatches$default(Ljava/lang/CharSequence;ILjava/lang/CharSequence;IIZILjava/lang/Object;)Z
   L0
    LINENUMBER 638 L0
    ILOAD 6
    BIPUSH 16
    IAND
    IFEQ L1
    ICONST_0
    ISTORE 5
   L1
   FRAME FULL [java/lang/CharSequence I java/lang/CharSequence I I I I java/lang/Object] []
    ALOAD 0
    ILOAD 1
    ALOAD 2
    ILOAD 3
    ILOAD 4
    ILOAD 5
    INVOKESTATIC kotlin/text/StringsKt.regionMatches (Ljava/lang/CharSequence;ILjava/lang/CharSequence;IIZ)Z
    IRETURN
    MAXSTACK = 6
    MAXLOCALS = 8

  // access flags 0x1009
  public static synthetic regionMatches$default(Ljava/lang/String;ILjava/lang/String;IIZILjava/lang/Object;)Z
   L0
    LINENUMBER 652 L0
    ILOAD 6
    BIPUSH 16
    IAND
    IFEQ L1
    ICONST_0
    ISTORE 5
   L1
   FRAME FULL [java/lang/String I java/lang/String I I I I java/lang/Object] []
    ALOAD 0
    ILOAD 1
    ALOAD 2
    ILOAD 3
    ILOAD 4
    ILOAD 5
    INVOKESTATIC kotlin/text/StringsKt.regionMatches (Ljava/lang/String;ILjava/lang/String;IIZ)Z
    IRETURN
    MAXSTACK = 6
    MAXLOCALS = 8

  // access flags 0x1008
  static synthetic toByteArray$default(Ljava/lang/String;Ljava/nio/charset/Charset;ILjava/lang/Object;)[B
   L0
    LINENUMBER 705 L0
    ILOAD 2
    ICONST_1
    IAND
    IFEQ L1
    GETSTATIC kotlin/text/Charsets.UTF_8 : Ljava/nio/charset/Charset;
    ASTORE 1
   L1
   FRAME FULL [java/lang/String java/nio/charset/Charset I java/lang/Object] []
    ALOAD 0
    LDC "<this>"
    INVOKESTATIC kotlin/jvm/internal/Intrinsics.checkNotNullParameter (Ljava/lang/Object;Ljava/lang/String;)V
    ALOAD 1
    LDC "charset"
    INVOKESTATIC kotlin/jvm/internal/Intrinsics.checkNotNullParameter (Ljava/lang/Object;Ljava/lang/String;)V
   L2
    LINENUMBER 705 L2
    ALOAD 0
    ALOAD 1
    INVOKEVIRTUAL java/lang/String.getBytes (Ljava/nio/charset/Charset;)[B
    DUP
    LDC "this as java.lang.String).getBytes(charset)"
    INVOKESTATIC kotlin/jvm/internal/Intrinsics.checkNotNullExpressionValue (Ljava/lang/Object;Ljava/lang/String;)V
    ARETURN
   L3
    LOCALVARIABLE $this$toByteArray_u24default Ljava/lang/String; L0 L3 0
    LOCALVARIABLE charset Ljava/nio/charset/Charset; L0 L3 1
    MAXSTACK = 3
    MAXLOCALS = 4

  // access flags 0x1008
  static synthetic toPattern$default(Ljava/lang/String;IILjava/lang/Object;)Ljava/util/regex/Pattern;
   L0
    LINENUMBER 713 L0
    ILOAD 2
    ICONST_1
    IAND
    IFEQ L1
    ICONST_0
    ISTORE 1
   L1
   FRAME FULL [java/lang/String I I java/lang/Object] []
    ALOAD 0
    LDC "<this>"
    INVOKESTATIC kotlin/jvm/internal/Intrinsics.checkNotNullParameter (Ljava/lang/Object;Ljava/lang/String;)V
   L2
    LINENUMBER 714 L2
    ALOAD 0
    ILOAD 1
    INVOKESTATIC java/util/regex/Pattern.compile (Ljava/lang/String;I)Ljava/util/regex/Pattern;
    DUP
    LDC "compile(this, flags)"
    INVOKESTATIC kotlin/jvm/internal/Intrinsics.checkNotNullExpressionValue (Ljava/lang/Object;Ljava/lang/String;)V
    ARETURN
   L3
    LOCALVARIABLE $this$toPattern_u24default Ljava/lang/String; L0 L3 0
    LOCALVARIABLE flags I L0 L3 1
    MAXSTACK = 3
    MAXLOCALS = 4

  // access flags 0x19
  public final static capitalize(Ljava/lang/String;)Ljava/lang/String;
  @Lkotlin/Deprecated;(message="Use replaceFirstChar instead.", replaceWith=@Lkotlin/ReplaceWith;(expression="replaceFirstChar { if (it.isLowerCase()) it.titlecase(Locale.getDefault()) else it.toString() }", imports={"java.util.Locale"}))
  @Lkotlin/DeprecatedSinceKotlin;(warningSince="1.5")
   L0
    ALOAD 0
    LDC "<this>"
    INVOKESTATIC kotlin/jvm/internal/Intrinsics.checkNotNullParameter (Ljava/lang/Object;Ljava/lang/String;)V
   L1
    LINENUMBER 730 L1
    ALOAD 0
    INVOKESTATIC java/util/Locale.getDefault ()Ljava/util/Locale;
    DUP
    LDC "getDefault()"
    INVOKESTATIC kotlin/jvm/internal/Intrinsics.checkNotNullExpressionValue (Ljava/lang/Object;Ljava/lang/String;)V
    INVOKESTATIC kotlin/text/StringsKt.capitalize (Ljava/lang/String;Ljava/util/Locale;)Ljava/lang/String;
    ARETURN
   L2
    LOCALVARIABLE $this$capitalize Ljava/lang/String; L0 L2 0
    MAXSTACK = 4
    MAXLOCALS = 1

  // access flags 0x19
  public final static capitalize(Ljava/lang/String;Ljava/util/Locale;)Ljava/lang/String;
  @Lkotlin/Deprecated;(message="Use replaceFirstChar instead.", replaceWith=@Lkotlin/ReplaceWith;(expression="replaceFirstChar { if (it.isLowerCase()) it.titlecase(locale) else it.toString() }", imports={}))
  @Lkotlin/DeprecatedSinceKotlin;(warningSince="1.5")
   L0
    ALOAD 0
    LDC "<this>"
    INVOKESTATIC kotlin/jvm/internal/Intrinsics.checkNotNullParameter (Ljava/lang/Object;Ljava/lang/String;)V
    ALOAD 1
    LDC "locale"
    INVOKESTATIC kotlin/jvm/internal/Intrinsics.checkNotNullParameter (Ljava/lang/Object;Ljava/lang/String;)V
   L1
    LINENUMBER 746 L1
    ALOAD 0
    CHECKCAST java/lang/CharSequence
    INVOKEINTERFACE java/lang/CharSequence.length ()I (itf)
    IFLE L2
    ICONST_1
    GOTO L3
   L2
   FRAME FULL [java/lang/String java/util/Locale] []
    ICONST_0
   L3
    LINENUMBER 746 L3
   FRAME FULL [java/lang/String java/util/Locale] [I]
    IFEQ L4
   L5
    LINENUMBER 747 L5
    ALOAD 0
    ICONST_0
    INVOKEVIRTUAL java/lang/String.charAt (I)C
    ISTORE 2
   L6
    LINENUMBER 748 L6
    ILOAD 2
    INVOKESTATIC java/lang/Character.isLowerCase (C)Z
   L7
    LINENUMBER 748 L7
    IFEQ L4
   L8
    LINENUMBER 749 L8
    NEW java/lang/StringBuilder
    DUP
    INVOKESPECIAL java/lang/StringBuilder.<init> ()V
    ASTORE 3
    ALOAD 3
    ASTORE 4
   L9
    ICONST_0
    ISTORE 5
   L10
    LINENUMBER 750 L10
    ILOAD 2
    INVOKESTATIC java/lang/Character.toTitleCase (C)C
   L11
    LINENUMBER 750 L11
    ISTORE 6
   L12
    LINENUMBER 751 L12
    ILOAD 6
    ILOAD 2
    INVOKESTATIC java/lang/Character.toUpperCase (C)C
   L13
    LINENUMBER 751 L13
    IF_ICMPEQ L14
   L15
    LINENUMBER 752 L15
    ALOAD 4
    ILOAD 6
    INVOKEVIRTUAL java/lang/StringBuilder.append (C)Ljava/lang/StringBuilder;
    POP
    GOTO L16
   L14
    LINENUMBER 754 L14
   FRAME FULL [java/lang/String java/util/Locale I java/lang/StringBuilder java/lang/StringBuilder I I] []
    ALOAD 4
    ALOAD 0
    ASTORE 7
    ICONST_0
    ISTORE 8
    ICONST_1
    ISTORE 9
    ALOAD 7
    ILOAD 8
    ILOAD 9
    INVOKEVIRTUAL java/lang/String.substring (II)Ljava/lang/String;
    DUP
    LDC "this as java.lang.String\u2026ing(startIndex, endIndex)"
    INVOKESTATIC kotlin/jvm/internal/Intrinsics.checkNotNullExpressionValue (Ljava/lang/Object;Ljava/lang/String;)V
    ASTORE 7
   L17
    LINENUMBER 754 L17
    ALOAD 7
    LDC "null cannot be cast to non-null type java.lang.String"
    INVOKESTATIC kotlin/jvm/internal/Intrinsics.checkNotNull (Ljava/lang/Object;Ljava/lang/String;)V
    ALOAD 7
    ALOAD 1
    INVOKEVIRTUAL java/lang/String.toUpperCase (Ljava/util/Locale;)Ljava/lang/String;
    DUP
    LDC "this as java.lang.String).toUpperCase(locale)"
    INVOKESTATIC kotlin/jvm/internal/Intrinsics.checkNotNullExpressionValue (Ljava/lang/Object;Ljava/lang/String;)V
   L18
    LINENUMBER 754 L18
    INVOKEVIRTUAL java/lang/StringBuilder.append (Ljava/lang/String;)Ljava/lang/StringBuilder;
    POP
   L16
    LINENUMBER 756 L16
   FRAME FULL [java/lang/String java/util/Locale I java/lang/StringBuilder java/lang/StringBuilder I I] []
    ALOAD 4
    ALOAD 0
    ASTORE 7
    ICONST_1
    ISTORE 8
    ALOAD 7
    ILOAD 8
    INVOKEVIRTUAL java/lang/String.substring (I)Ljava/lang/String;
    DUP
    LDC "this as java.lang.String).substring(startIndex)"
    INVOKESTATIC kotlin/jvm/internal/Intrinsics.checkNotNullExpressionValue (Ljava/lang/Object;Ljava/lang/String;)V
   L19
    LINENUMBER 756 L19
    INVOKEVIRTUAL java/lang/StringBuilder.append (Ljava/lang/String;)Ljava/lang/StringBuilder;
    POP
   L20
    LINENUMBER 757 L20
    NOP
   L21
    LINENUMBER 749 L21
    ALOAD 3
    INVOKEVIRTUAL java/lang/StringBuilder.toString ()Ljava/lang/String;
    DUP
    LDC "StringBuilder().apply(builderAction).toString()"
    INVOKESTATIC kotlin/jvm/internal/Intrinsics.checkNotNullExpressionValue (Ljava/lang/Object;Ljava/lang/String;)V
   L22
    LINENUMBER 749 L22
    ARETURN
   L4
    LINENUMBER 760 L4
   FRAME FULL [java/lang/String java/util/Locale] []
    ALOAD 0
    ARETURN
   L23
    LOCALVARIABLE $i$a$-buildString-StringsKt__StringsJVMKt$capitalize$1 I L10 L21 5
    LOCALVARIABLE titleChar C L12 L21 6
    LOCALVARIABLE $this$capitalize_u24lambda_u2d5 Ljava/lang/StringBuilder; L9 L21 4
    LOCALVARIABLE firstChar C L6 L4 2
    LOCALVARIABLE $this$capitalize Ljava/lang/String; L0 L23 0
    LOCALVARIABLE locale Ljava/util/Locale; L0 L23 1
    MAXSTACK = 4
    MAXLOCALS = 10

  // access flags 0x1
  public <init>()V
   L0
    ALOAD 0
    INVOKESPECIAL kotlin/text/StringsKt__StringNumberConversionsKt.<init> ()V
    RETURN
   L1
    LOCALVARIABLE this Lkotlin/text/StringsKt__StringsJVMKt; L0 L1 0
    MAXSTACK = 1
    MAXLOCALS = 1

  // access flags 0x19
  public final static equals(Ljava/lang/String;Ljava/lang/String;Z)Z
   L0
    LINENUMBER 54 L0
    ALOAD 0
    IFNONNULL L1
   L2
    LINENUMBER 55 L2
    ALOAD 1
    IFNONNULL L3
    ICONST_1
    GOTO L4
   L3
   FRAME FULL [java/lang/String java/lang/String I] []
    ICONST_0
   L4
   FRAME FULL [java/lang/String java/lang/String I] [I]
    IRETURN
   L1
    LINENUMBER 56 L1
   FRAME FULL [java/lang/String java/lang/String I] []
    ILOAD 2
    IFNE L5
   L6
    LINENUMBER 57 L6
    ALOAD 0
    ALOAD 1
    INVOKEVIRTUAL java/lang/String.equals (Ljava/lang/Object;)Z
    GOTO L7
   L5
    LINENUMBER 59 L5
   FRAME FULL [java/lang/String java/lang/String I] []
    ALOAD 0
    ALOAD 1
    INVOKEVIRTUAL java/lang/String.equalsIgnoreCase (Ljava/lang/String;)Z
   L7
    LINENUMBER 56 L7
   FRAME FULL [java/lang/String java/lang/String I] [I]
    IRETURN
   L8
    LOCALVARIABLE $this$equals Ljava/lang/String; L0 L8 0
    LOCALVARIABLE other Ljava/lang/String; L0 L8 1
    LOCALVARIABLE ignoreCase Z L0 L8 2
    MAXSTACK = 2
    MAXLOCALS = 3

  // access flags 0x19
  public final static compareTo(Ljava/lang/String;Ljava/lang/String;Z)I
   L0
    ALOAD 0
    LDC "<this>"
    INVOKESTATIC kotlin/jvm/internal/Intrinsics.checkNotNullParameter (Ljava/lang/Object;Ljava/lang/String;)V
    ALOAD 1
    LDC "other"
    INVOKESTATIC kotlin/jvm/internal/Intrinsics.checkNotNullParameter (Ljava/lang/Object;Ljava/lang/String;)V
   L1
    LINENUMBER 551 L1
    ILOAD 2
    IFEQ L2
   L3
    LINENUMBER 552 L3
    ALOAD 0
    ALOAD 1
    INVOKEVIRTUAL java/lang/String.compareToIgnoreCase (Ljava/lang/String;)I
    IRETURN
   L2
    LINENUMBER 554 L2
   FRAME FULL [java/lang/String java/lang/String I] []
    ALOAD 0
    ALOAD 1
    INVOKEVIRTUAL java/lang/String.compareTo (Ljava/lang/String;)I
    IRETURN
   L4
    LOCALVARIABLE $this$compareTo Ljava/lang/String; L0 L4 0
    LOCALVARIABLE other Ljava/lang/String; L0 L4 1
    LOCALVARIABLE ignoreCase Z L0 L4 2
    MAXSTACK = 2
    MAXLOCALS = 3

  // access flags 0x1A
  private final static codePointAt(Ljava/lang/String;I)I
   L0
    ALOAD 0
    LDC "<this>"
    INVOKESTATIC kotlin/jvm/internal/Intrinsics.checkNotNullParameter (Ljava/lang/Object;Ljava/lang/String;)V
   L1
    LINENUMBER 529 L1
    ALOAD 0
    ILOAD 1
    INVOKEVIRTUAL java/lang/String.codePointAt (I)I
    IRETURN
   L2
    LOCALVARIABLE $this$codePointAt Ljava/lang/String; L0 L2 0
    LOCALVARIABLE index I L0 L2 1
    MAXSTACK = 2
    MAXLOCALS = 2

  // access flags 0x1A
  private final static codePointBefore(Ljava/lang/String;I)I
   L0
    ALOAD 0
    LDC "<this>"
    INVOKESTATIC kotlin/jvm/internal/Intrinsics.checkNotNullParameter (Ljava/lang/Object;Ljava/lang/String;)V
   L1
    LINENUMBER 535 L1
    ALOAD 0
    ILOAD 1
    INVOKEVIRTUAL java/lang/String.codePointBefore (I)I
    IRETURN
   L2
    LOCALVARIABLE $this$codePointBefore Ljava/lang/String; L0 L2 0
    LOCALVARIABLE index I L0 L2 1
    MAXSTACK = 2
    MAXLOCALS = 2

  // access flags 0x1A
  private final static codePointCount(Ljava/lang/String;II)I
   L0
    ALOAD 0
    LDC "<this>"
    INVOKESTATIC kotlin/jvm/internal/Intrinsics.checkNotNullParameter (Ljava/lang/Object;Ljava/lang/String;)V
   L1
    LINENUMBER 542 L1
    ALOAD 0
    ILOAD 1
    ILOAD 2
    INVOKEVIRTUAL java/lang/String.codePointCount (II)I
    IRETURN
   L2
    LOCALVARIABLE $this$codePointCount Ljava/lang/String; L0 L2 0
    LOCALVARIABLE beginIndex I L0 L2 1
    LOCALVARIABLE endIndex I L0 L2 2
    MAXSTACK = 3
    MAXLOCALS = 3

  // access flags 0x1A
  private final static offsetByCodePoints(Ljava/lang/String;II)I
   L0
    ALOAD 0
    LDC "<this>"
    INVOKESTATIC kotlin/jvm/internal/Intrinsics.checkNotNullParameter (Ljava/lang/Object;Ljava/lang/String;)V
   L1
    LINENUMBER 628 L1
    ALOAD 0
    ILOAD 1
    ILOAD 2
    INVOKEVIRTUAL java/lang/String.offsetByCodePoints (II)I
    IRETURN
   L2
    LOCALVARIABLE $this$offsetByCodePoints Ljava/lang/String; L0 L2 0
    LOCALVARIABLE index I L0 L2 1
    LOCALVARIABLE codePointOffset I L0 L2 2
    MAXSTACK = 3
    MAXLOCALS = 3

  // access flags 0x1A
  private final static contentEquals(Ljava/lang/String;Ljava/lang/CharSequence;)Z
   L0
    ALOAD 0
    LDC "<this>"
    INVOKESTATIC kotlin/jvm/internal/Intrinsics.checkNotNullParameter (Ljava/lang/Object;Ljava/lang/String;)V
    ALOAD 1
    LDC "charSequence"
    INVOKESTATIC kotlin/jvm/internal/Intrinsics.checkNotNullParameter (Ljava/lang/Object;Ljava/lang/String;)V
   L1
    LINENUMBER 564 L1
    ALOAD 0
    ALOAD 1
    INVOKEVIRTUAL java/lang/String.contentEquals (Ljava/lang/CharSequence;)Z
    IRETURN
   L2
    LOCALVARIABLE $this$contentEquals Ljava/lang/String; L0 L2 0
    LOCALVARIABLE charSequence Ljava/lang/CharSequence; L0 L2 1
    MAXSTACK = 2
    MAXLOCALS = 2

  // access flags 0x19
  public final static contentEquals(Ljava/lang/CharSequence;Ljava/lang/CharSequence;)Z
   L0
    LINENUMBER 586 L0
    ALOAD 0
    INSTANCEOF java/lang/String
    IFEQ L1
    ALOAD 1
    IFNULL L1
   L2
    LINENUMBER 587 L2
    ALOAD 0
    CHECKCAST java/lang/String
    ALOAD 1
    INVOKEVIRTUAL java/lang/String.contentEquals (Ljava/lang/CharSequence;)Z
    GOTO L3
   L1
    LINENUMBER 589 L1
   FRAME FULL [java/lang/CharSequence java/lang/CharSequence] []
    ALOAD 0
    ALOAD 1
    INVOKESTATIC kotlin/text/StringsKt.contentEqualsImpl (Ljava/lang/CharSequence;Ljava/lang/CharSequence;)Z
   L3
    LINENUMBER 586 L3
   FRAME FULL [java/lang/CharSequence java/lang/CharSequence] [I]
    IRETURN
   L4
    LOCALVARIABLE $this$contentEquals Ljava/lang/CharSequence; L0 L4 0
    LOCALVARIABLE other Ljava/lang/CharSequence; L0 L4 1
    MAXSTACK = 2
    MAXLOCALS = 2

  // access flags 0x1A
  private final static contentEquals(Ljava/lang/String;Ljava/lang/StringBuffer;)Z
   L0
    ALOAD 0
    LDC "<this>"
    INVOKESTATIC kotlin/jvm/internal/Intrinsics.checkNotNullParameter (Ljava/lang/Object;Ljava/lang/String;)V
    ALOAD 1
    LDC "stringBuilder"
    INVOKESTATIC kotlin/jvm/internal/Intrinsics.checkNotNullParameter (Ljava/lang/Object;Ljava/lang/String;)V
   L1
    LINENUMBER 573 L1
    ALOAD 0
    ALOAD 1
    INVOKEVIRTUAL java/lang/String.contentEquals (Ljava/lang/StringBuffer;)Z
    IRETURN
   L2
    LOCALVARIABLE $this$contentEquals Ljava/lang/String; L0 L2 0
    LOCALVARIABLE stringBuilder Ljava/lang/StringBuffer; L0 L2 1
    MAXSTACK = 2
    MAXLOCALS = 2

  // access flags 0x19
  public final static contentEquals(Ljava/lang/CharSequence;Ljava/lang/CharSequence;Z)Z
   L0
    LINENUMBER 604 L0
    ILOAD 2
    IFEQ L1
   L2
    LINENUMBER 605 L2
    ALOAD 0
    ALOAD 1
    INVOKESTATIC kotlin/text/StringsKt.contentEqualsIgnoreCaseImpl (Ljava/lang/CharSequence;Ljava/lang/CharSequence;)Z
    GOTO L3
   L1
    LINENUMBER 607 L1
   FRAME FULL [java/lang/CharSequence java/lang/CharSequence I] []
    ALOAD 0
    ALOAD 1
    INVOKESTATIC kotlin/text/StringsKt.contentEquals (Ljava/lang/CharSequence;Ljava/lang/CharSequence;)Z
   L3
    LINENUMBER 604 L3
   FRAME FULL [java/lang/CharSequence java/lang/CharSequence I] [I]
    IRETURN
   L4
    LOCALVARIABLE $this$contentEquals Ljava/lang/CharSequence; L0 L4 0
    LOCALVARIABLE other Ljava/lang/CharSequence; L0 L4 1
    LOCALVARIABLE ignoreCase Z L0 L4 2
    MAXSTACK = 2
    MAXLOCALS = 3

  // access flags 0x19
  public final static regionMatches(Ljava/lang/String;ILjava/lang/String;IIZ)Z
   L0
    ALOAD 0
    LDC "<this>"
    INVOKESTATIC kotlin/jvm/internal/Intrinsics.checkNotNullParameter (Ljava/lang/Object;Ljava/lang/String;)V
    ALOAD 2
    LDC "other"
    INVOKESTATIC kotlin/jvm/internal/Intrinsics.checkNotNullParameter (Ljava/lang/Object;Ljava/lang/String;)V
   L1
    LINENUMBER 653 L1
    ILOAD 5
    IFNE L2
   L3
    LINENUMBER 654 L3
    ALOAD 0
    ILOAD 1
    ALOAD 2
    ILOAD 3
    ILOAD 4
    INVOKEVIRTUAL java/lang/String.regionMatches (ILjava/lang/String;II)Z
    GOTO L4
   L2
    LINENUMBER 656 L2
   FRAME FULL [java/lang/String I java/lang/String I I I] []
    ALOAD 0
    ILOAD 5
    ILOAD 1
    ALOAD 2
    ILOAD 3
    ILOAD 4
    INVOKEVIRTUAL java/lang/String.regionMatches (ZILjava/lang/String;II)Z
   L4
   FRAME FULL [java/lang/String I java/lang/String I I I] [I]
    IRETURN
   L5
    LOCALVARIABLE $this$regionMatches Ljava/lang/String; L0 L5 0
    LOCALVARIABLE thisOffset I L0 L5 1
    LOCALVARIABLE other Ljava/lang/String; L0 L5 2
    LOCALVARIABLE otherOffset I L0 L5 3
    LOCALVARIABLE length I L0 L5 4
    LOCALVARIABLE ignoreCase Z L0 L5 5
    MAXSTACK = 6
    MAXLOCALS = 6

  // access flags 0x19
  public final static regionMatches(Ljava/lang/CharSequence;ILjava/lang/CharSequence;IIZ)Z
   L0
    ALOAD 0
    LDC "<this>"
    INVOKESTATIC kotlin/jvm/internal/Intrinsics.checkNotNullParameter (Ljava/lang/Object;Ljava/lang/String;)V
    ALOAD 2
    LDC "other"
    INVOKESTATIC kotlin/jvm/internal/Intrinsics.checkNotNullParameter (Ljava/lang/Object;Ljava/lang/String;)V
   L1
    LINENUMBER 639 L1
    ALOAD 0
    INSTANCEOF java/lang/String
    IFEQ L2
    ALOAD 2
    INSTANCEOF java/lang/String
    IFEQ L2
   L3
    LINENUMBER 640 L3
    ALOAD 0
    CHECKCAST java/lang/String
    ILOAD 1
    ALOAD 2
    CHECKCAST java/lang/String
    ILOAD 3
    ILOAD 4
    ILOAD 5
    INVOKESTATIC kotlin/text/StringsKt.regionMatches (Ljava/lang/String;ILjava/lang/String;IIZ)Z
    IRETURN
   L2
    LINENUMBER 642 L2
   FRAME FULL [java/lang/CharSequence I java/lang/CharSequence I I I] []
    ALOAD 0
    ILOAD 1
    ALOAD 2
    ILOAD 3
    ILOAD 4
    ILOAD 5
    INVOKESTATIC kotlin/text/StringsKt.regionMatchesImpl (Ljava/lang/CharSequence;ILjava/lang/CharSequence;IIZ)Z
    IRETURN
   L4
    LOCALVARIABLE $this$regionMatches Ljava/lang/CharSequence; L0 L4 0
    LOCALVARIABLE thisOffset I L0 L4 1
    LOCALVARIABLE other Ljava/lang/CharSequence; L0 L4 2
    LOCALVARIABLE otherOffset I L0 L4 3
    LOCALVARIABLE length I L0 L4 4
    LOCALVARIABLE ignoreCase Z L0 L4 5
    MAXSTACK = 6
    MAXLOCALS = 6

  // access flags 0x19
  public final static startsWith(Ljava/lang/String;Ljava/lang/String;IZ)Z
   L0
    ALOAD 0
    LDC "<this>"
    INVOKESTATIC kotlin/jvm/internal/Intrinsics.checkNotNullParameter (Ljava/lang/Object;Ljava/lang/String;)V
    ALOAD 1
    LDC "prefix"
    INVOKESTATIC kotlin/jvm/internal/Intrinsics.checkNotNullParameter (Ljava/lang/Object;Ljava/lang/String;)V
   L1
    LINENUMBER 428 L1
    ILOAD 3
    IFNE L2
   L3
    LINENUMBER 429 L3
    ALOAD 0
    ALOAD 1
    ILOAD 2
    INVOKEVIRTUAL java/lang/String.startsWith (Ljava/lang/String;I)Z
    IRETURN
   L2
    LINENUMBER 431 L2
   FRAME FULL [java/lang/String java/lang/String I I] []
    ALOAD 0
    ILOAD 2
    ALOAD 1
    ICONST_0
    ALOAD 1
    INVOKEVIRTUAL java/lang/String.length ()I
    ILOAD 3
    INVOKESTATIC kotlin/text/StringsKt.regionMatches (Ljava/lang/String;ILjava/lang/String;IIZ)Z
    IRETURN
   L4
    LOCALVARIABLE $this$startsWith Ljava/lang/String; L0 L4 0
    LOCALVARIABLE prefix Ljava/lang/String; L0 L4 1
    LOCALVARIABLE startIndex I L0 L4 2
    LOCALVARIABLE ignoreCase Z L0 L4 3
    MAXSTACK = 6
    MAXLOCALS = 4

  // access flags 0x19
  public final static startsWith(Ljava/lang/String;Ljava/lang/String;Z)Z
   L0
    ALOAD 0
    LDC "<this>"
    INVOKESTATIC kotlin/jvm/internal/Intrinsics.checkNotNullParameter (Ljava/lang/Object;Ljava/lang/String;)V
    ALOAD 1
    LDC "prefix"
    INVOKESTATIC kotlin/jvm/internal/Intrinsics.checkNotNullParameter (Ljava/lang/Object;Ljava/lang/String;)V
   L1
    LINENUMBER 417 L1
    ILOAD 2
    IFNE L2
   L3
    LINENUMBER 418 L3
    ALOAD 0
    ALOAD 1
    INVOKEVIRTUAL java/lang/String.startsWith (Ljava/lang/String;)Z
    IRETURN
   L2
    LINENUMBER 420 L2
   FRAME FULL [java/lang/String java/lang/String I] []
    ALOAD 0
    ICONST_0
    ALOAD 1
    ICONST_0
    ALOAD 1
    INVOKEVIRTUAL java/lang/String.length ()I
    ILOAD 2
    INVOKESTATIC kotlin/text/StringsKt.regionMatches (Ljava/lang/String;ILjava/lang/String;IIZ)Z
    IRETURN
   L4
    LOCALVARIABLE $this$startsWith Ljava/lang/String; L0 L4 0
    LOCALVARIABLE prefix Ljava/lang/String; L0 L4 1
    LOCALVARIABLE ignoreCase Z L0 L4 2
    MAXSTACK = 6
    MAXLOCALS = 3

  // access flags 0x19
  public final static endsWith(Ljava/lang/String;Ljava/lang/String;Z)Z
   L0
    ALOAD 0
    LDC "<this>"
    INVOKESTATIC kotlin/jvm/internal/Intrinsics.checkNotNullParameter (Ljava/lang/Object;Ljava/lang/String;)V
    ALOAD 1
    LDC "suffix"
    INVOKESTATIC kotlin/jvm/internal/Intrinsics.checkNotNullParameter (Ljava/lang/Object;Ljava/lang/String;)V
   L1
    LINENUMBER 439 L1
    ILOAD 2
    IFNE L2
   L3
    LINENUMBER 440 L3
    ALOAD 0
    ALOAD 1
    INVOKEVIRTUAL java/lang/String.endsWith (Ljava/lang/String;)Z
    IRETURN
   L2
    LINENUMBER 442 L2
   FRAME FULL [java/lang/String java/lang/String I] []
    ALOAD 0
    ALOAD 0
    INVOKEVIRTUAL java/lang/String.length ()I
    ALOAD 1
    INVOKEVIRTUAL java/lang/String.length ()I
    ISUB
    ALOAD 1
    ICONST_0
    ALOAD 1
    INVOKEVIRTUAL java/lang/String.length ()I
    ICONST_1
    INVOKESTATIC kotlin/text/StringsKt.regionMatches (Ljava/lang/String;ILjava/lang/String;IIZ)Z
    IRETURN
   L4
    LOCALVARIABLE $this$endsWith Ljava/lang/String; L0 L4 0
    LOCALVARIABLE suffix Ljava/lang/String; L0 L4 1
    LOCALVARIABLE ignoreCase Z L0 L4 2
    MAXSTACK = 6
    MAXLOCALS = 3

  // access flags 0x1A
  private final static substring(Ljava/lang/String;I)Ljava/lang/String;
   L0
    ALOAD 0
    LDC "<this>"
    INVOKESTATIC kotlin/jvm/internal/Intrinsics.checkNotNullParameter (Ljava/lang/Object;Ljava/lang/String;)V
   L1
    LINENUMBER 401 L1
    ALOAD 0
    ILOAD 1
    INVOKEVIRTUAL java/lang/String.substring (I)Ljava/lang/String;
    DUP
    LDC "this as java.lang.String).substring(startIndex)"
    INVOKESTATIC kotlin/jvm/internal/Intrinsics.checkNotNullExpressionValue (Ljava/lang/Object;Ljava/lang/String;)V
    ARETURN
   L2
    LOCALVARIABLE $this$substring Ljava/lang/String; L0 L2 0
    LOCALVARIABLE startIndex I L0 L2 1
    MAXSTACK = 3
    MAXLOCALS = 2

  // access flags 0x1A
  private final static substring(Ljava/lang/String;II)Ljava/lang/String;
   L0
    ALOAD 0
    LDC "<this>"
    INVOKESTATIC kotlin/jvm/internal/Intrinsics.checkNotNullParameter (Ljava/lang/Object;Ljava/lang/String;)V
   L1
    LINENUMBER 410 L1
    ALOAD 0
    ILOAD 1
    ILOAD 2
    INVOKEVIRTUAL java/lang/String.substring (II)Ljava/lang/String;
    DUP
    LDC "this as java.lang.String\u2026ing(startIndex, endIndex)"
    INVOKESTATIC kotlin/jvm/internal/Intrinsics.checkNotNullExpressionValue (Ljava/lang/Object;Ljava/lang/String;)V
    ARETURN
   L2
    LOCALVARIABLE $this$substring Ljava/lang/String; L0 L2 0
    LOCALVARIABLE startIndex I L0 L2 1
    LOCALVARIABLE endIndex I L0 L2 2
    MAXSTACK = 3
    MAXLOCALS = 3

  // access flags 0x19
  public final static replace(Ljava/lang/String;Ljava/lang/String;Ljava/lang/String;Z)Ljava/lang/String;
   L0
    ALOAD 0
    LDC "<this>"
    INVOKESTATIC kotlin/jvm/internal/Intrinsics.checkNotNullParameter (Ljava/lang/Object;Ljava/lang/String;)V
    ALOAD 1
    LDC "oldValue"
    INVOKESTATIC kotlin/jvm/internal/Intrinsics.checkNotNullParameter (Ljava/lang/Object;Ljava/lang/String;)V
    ALOAD 2
    LDC "newValue"
    INVOKESTATIC kotlin/jvm/internal/Intrinsics.checkNotNullParameter (Ljava/lang/Object;Ljava/lang/String;)V
   L1
    LINENUMBER 87 L1
    ALOAD 0
    ASTORE 4
    ALOAD 4
    ASTORE 5
   L2
    ICONST_0
    ISTORE 6
   L3
    LINENUMBER 88 L3
    ALOAD 5
    CHECKCAST java/lang/CharSequence
    ALOAD 1
    ICONST_0
    ILOAD 3
    INVOKESTATIC kotlin/text/StringsKt.indexOf (Ljava/lang/CharSequence;Ljava/lang/String;IZ)I
    ISTORE 7
   L4
    LINENUMBER 90 L4
    ILOAD 7
    IFGE L5
    ALOAD 5
    ARETURN
   L5
    LINENUMBER 92 L5
   FRAME FULL [java/lang/String java/lang/String java/lang/String I java/lang/String java/lang/String I I] []
    ALOAD 1
    INVOKEVIRTUAL java/lang/String.length ()I
    ISTORE 8
   L6
    LINENUMBER 93 L6
    ILOAD 8
    ICONST_1
    INVOKESTATIC kotlin/ranges/RangesKt.coerceAtLeast (II)I
    ISTORE 9
   L7
    LINENUMBER 94 L7
    ALOAD 5
    INVOKEVIRTUAL java/lang/String.length ()I
    ILOAD 8
    ISUB
    ALOAD 2
    INVOKEVIRTUAL java/lang/String.length ()I
    IADD
    ISTORE 10
   L8
    LINENUMBER 95 L8
    ILOAD 10
    IFGE L9
    NEW java/lang/OutOfMemoryError
    DUP
    INVOKESPECIAL java/lang/OutOfMemoryError.<init> ()V
    ATHROW
   L9
    LINENUMBER 96 L9
   FRAME FULL [java/lang/String java/lang/String java/lang/String I java/lang/String java/lang/String I I I I I] []
    NEW java/lang/StringBuilder
    DUP
    ILOAD 10
    INVOKESPECIAL java/lang/StringBuilder.<init> (I)V
    ASTORE 11
   L10
    LINENUMBER 98 L10
    ICONST_0
    ISTORE 12
   L11
    LINENUMBER 100 L11
   FRAME FULL [java/lang/String java/lang/String java/lang/String I java/lang/String java/lang/String I I I I I java/lang/StringBuilder I] []
    ALOAD 11
    ALOAD 5
    CHECKCAST java/lang/CharSequence
    ILOAD 12
    ILOAD 7
    INVOKEVIRTUAL java/lang/StringBuilder.append (Ljava/lang/CharSequence;II)Ljava/lang/StringBuilder;
    ALOAD 2
    INVOKEVIRTUAL java/lang/StringBuilder.append (Ljava/lang/String;)Ljava/lang/StringBuilder;
    POP
   L12
    LINENUMBER 101 L12
    ILOAD 7
    ILOAD 8
    IADD
    ISTORE 12
   L13
    LINENUMBER 102 L13
    ILOAD 7
    ALOAD 5
    INVOKEVIRTUAL java/lang/String.length ()I
    IF_ICMPGE L14
   L15
    LINENUMBER 103 L15
    ALOAD 5
    CHECKCAST java/lang/CharSequence
    ALOAD 1
    ILOAD 7
    ILOAD 9
    IADD
    ILOAD 3
    INVOKESTATIC kotlin/text/StringsKt.indexOf (Ljava/lang/CharSequence;Ljava/lang/String;IZ)I
    ISTORE 7
   L16
    LINENUMBER 104 L16
    ILOAD 7
    IFGT L11
   L14
    LINENUMBER 105 L14
   FRAME FULL [java/lang/String java/lang/String java/lang/String I java/lang/String java/lang/String I I I I I java/lang/StringBuilder I] []
    ALOAD 11
    ALOAD 5
    CHECKCAST java/lang/CharSequence
    ILOAD 12
    ALOAD 5
    INVOKEVIRTUAL java/lang/String.length ()I
    INVOKEVIRTUAL java/lang/StringBuilder.append (Ljava/lang/CharSequence;II)Ljava/lang/StringBuilder;
    INVOKEVIRTUAL java/lang/StringBuilder.toString ()Ljava/lang/String;
    DUP
    LDC "stringBuilder.append(this, i, length).toString()"
    INVOKESTATIC kotlin/jvm/internal/Intrinsics.checkNotNullExpressionValue (Ljava/lang/Object;Ljava/lang/String;)V
    ARETURN
   L17
    LOCALVARIABLE $i$a$-run-StringsKt__StringsJVMKt$replace$2 I L3 L17 6
    LOCALVARIABLE occurrenceIndex I L4 L17 7
    LOCALVARIABLE oldValueLength I L6 L17 8
    LOCALVARIABLE searchStep I L7 L17 9
    LOCALVARIABLE newLengthHint I L8 L17 10
    LOCALVARIABLE stringBuilder Ljava/lang/StringBuilder; L10 L17 11
    LOCALVARIABLE i I L11 L17 12
    LOCALVARIABLE $this$replace_u24lambda_u2d2 Ljava/lang/String; L2 L17 5
    LOCALVARIABLE $this$replace Ljava/lang/String; L0 L17 0
    LOCALVARIABLE oldValue Ljava/lang/String; L0 L17 1
    LOCALVARIABLE newValue Ljava/lang/String; L0 L17 2
    LOCALVARIABLE ignoreCase Z L0 L17 3
    MAXSTACK = 4
    MAXLOCALS = 13

  // access flags 0x19
  public final static replace(Ljava/lang/String;CCZ)Ljava/lang/String;
   L0
    ALOAD 0
    LDC "<this>"
    INVOKESTATIC kotlin/jvm/internal/Intrinsics.checkNotNullParameter (Ljava/lang/Object;Ljava/lang/String;)V
   L1
    LINENUMBER 70 L1
    ILOAD 3
    IFNE L2
    ALOAD 0
    ILOAD 1
    ILOAD 2
    INVOKEVIRTUAL java/lang/String.replace (CC)Ljava/lang/String;
    DUP
    LDC "this as java.lang.String\u2026replace(oldChar, newChar)"
    INVOKESTATIC kotlin/jvm/internal/Intrinsics.checkNotNullExpressionValue (Ljava/lang/Object;Ljava/lang/String;)V
    ARETURN
   L2
    LINENUMBER 72 L2
   FRAME FULL [java/lang/String I I I] []
    ALOAD 0
    INVOKEVIRTUAL java/lang/String.length ()I
    ISTORE 4
    NEW java/lang/StringBuilder
    DUP
    ILOAD 4
    INVOKESPECIAL java/lang/StringBuilder.<init> (I)V
    ASTORE 5
    ALOAD 5
    ASTORE 6
   L3
    ICONST_0
    ISTORE 7
   L4
    LINENUMBER 73 L4
    ALOAD 0
    CHECKCAST java/lang/CharSequence
    ASTORE 8
   L5
    ICONST_0
    ISTORE 9
   L6
    LINENUMBER 826 L6
    ICONST_0
    ISTORE 10
   L7
   FRAME FULL [java/lang/String I I I I java/lang/StringBuilder java/lang/StringBuilder I java/lang/CharSequence I I] []
    ILOAD 10
    ALOAD 8
    INVOKEINTERFACE java/lang/CharSequence.length ()I (itf)
    IF_ICMPGE L8
    ALOAD 8
    ILOAD 10
    INVOKEINTERFACE java/lang/CharSequence.charAt (I)C (itf)
    ISTORE 11
   L9
    ILOAD 11
    ISTORE 12
   L10
    ICONST_0
    ISTORE 13
   L11
    LINENUMBER 74 L11
    ALOAD 6
    ILOAD 12
    ILOAD 1
    ILOAD 3
    INVOKESTATIC kotlin/text/CharsKt.equals (CCZ)Z
    IFEQ L12
    ILOAD 2
    GOTO L13
   L12
   FRAME FULL [java/lang/String I I I I java/lang/StringBuilder java/lang/StringBuilder I java/lang/CharSequence I I I I I] [java/lang/StringBuilder]
    ILOAD 12
   L13
   FRAME FULL [java/lang/String I I I I java/lang/StringBuilder java/lang/StringBuilder I java/lang/CharSequence I I I I I] [java/lang/StringBuilder I]
    INVOKEVIRTUAL java/lang/StringBuilder.append (C)Ljava/lang/StringBuilder;
    POP
   L14
    LINENUMBER 75 L14
    NOP
   L15
    IINC 10 1
    GOTO L7
   L8
    LINENUMBER 827 L8
   FRAME FULL [java/lang/String I I I I java/lang/StringBuilder java/lang/StringBuilder I java/lang/CharSequence I I] []
    NOP
   L16
    LINENUMBER 76 L16
    NOP
   L17
    LINENUMBER 72 L17
    ALOAD 5
    INVOKEVIRTUAL java/lang/StringBuilder.toString ()Ljava/lang/String;
    DUP
    LDC "StringBuilder(capacity).\u2026builderAction).toString()"
    INVOKESTATIC kotlin/jvm/internal/Intrinsics.checkNotNullExpressionValue (Ljava/lang/Object;Ljava/lang/String;)V
   L18
    LINENUMBER 72 L18
    ARETURN
   L19
    LOCALVARIABLE $i$a$-forEach-StringsKt__StringsJVMKt$replace$1$1 I L11 L15 13
    LOCALVARIABLE c C L10 L15 12
    LOCALVARIABLE element$iv C L9 L8 11
    LOCALVARIABLE $i$f$forEach I L6 L16 9
    LOCALVARIABLE $this$forEach$iv Ljava/lang/CharSequence; L5 L16 8
    LOCALVARIABLE $i$a$-buildString-StringsKt__StringsJVMKt$replace$1 I L4 L17 7
    LOCALVARIABLE $this$replace_u24lambda_u2d1 Ljava/lang/StringBuilder; L3 L17 6
    LOCALVARIABLE $this$replace Ljava/lang/String; L0 L19 0
    LOCALVARIABLE oldChar C L0 L19 1
    LOCALVARIABLE newChar C L0 L19 2
    LOCALVARIABLE ignoreCase Z L0 L19 3
    MAXSTACK = 4
    MAXLOCALS = 14

  // access flags 0x19
  public final static replaceFirst(Ljava/lang/String;CCZ)Ljava/lang/String;
   L0
    ALOAD 0
    LDC "<this>"
    INVOKESTATIC kotlin/jvm/internal/Intrinsics.checkNotNullParameter (Ljava/lang/Object;Ljava/lang/String;)V
   L1
    LINENUMBER 114 L1
    ALOAD 0
    CHECKCAST java/lang/CharSequence
    ILOAD 1
    ICONST_0
    ILOAD 3
    ICONST_2
    ACONST_NULL
    INVOKESTATIC kotlin/text/StringsKt.indexOf$default (Ljava/lang/CharSequence;CIZILjava/lang/Object;)I
    ISTORE 4
   L2
    LINENUMBER 115 L2
    ILOAD 4
    IFGE L3
    ALOAD 0
    GOTO L4
   L3
   FRAME FULL [java/lang/String I I I I] []
    ALOAD 0
    ASTORE 5
    ILOAD 4
    ICONST_1
    IADD
    ISTORE 6
    ILOAD 2
    INVOKESTATIC java/lang/String.valueOf (C)Ljava/lang/String;
    CHECKCAST java/lang/CharSequence
    ASTORE 7
    ALOAD 5
    CHECKCAST java/lang/CharSequence
    ILOAD 4
    ILOAD 6
    ALOAD 7
    INVOKESTATIC kotlin/text/StringsKt.replaceRange (Ljava/lang/CharSequence;IILjava/lang/CharSequence;)Ljava/lang/CharSequence;
    INVOKEVIRTUAL java/lang/Object.toString ()Ljava/lang/String;
   L4
    LINENUMBER 115 L4
   FRAME FULL [java/lang/String I I I I] [java/lang/String]
    ARETURN
   L5
    LOCALVARIABLE index I L2 L5 4
    LOCALVARIABLE $this$replaceFirst Ljava/lang/String; L0 L5 0
    LOCALVARIABLE oldChar C L0 L5 1
    LOCALVARIABLE newChar C L0 L5 2
    LOCALVARIABLE ignoreCase Z L0 L5 3
    MAXSTACK = 6
    MAXLOCALS = 8

  // access flags 0x19
  public final static replaceFirst(Ljava/lang/String;Ljava/lang/String;Ljava/lang/String;Z)Ljava/lang/String;
   L0
    ALOAD 0
    LDC "<this>"
    INVOKESTATIC kotlin/jvm/internal/Intrinsics.checkNotNullParameter (Ljava/lang/Object;Ljava/lang/String;)V
    ALOAD 1
    LDC "oldValue"
    INVOKESTATIC kotlin/jvm/internal/Intrinsics.checkNotNullParameter (Ljava/lang/Object;Ljava/lang/String;)V
    ALOAD 2
    LDC "newValue"
    INVOKESTATIC kotlin/jvm/internal/Intrinsics.checkNotNullParameter (Ljava/lang/Object;Ljava/lang/String;)V
   L1
    LINENUMBER 124 L1
    ALOAD 0
    CHECKCAST java/lang/CharSequence
    ALOAD 1
    ICONST_0
    ILOAD 3
    ICONST_2
    ACONST_NULL
    INVOKESTATIC kotlin/text/StringsKt.indexOf$default (Ljava/lang/CharSequence;Ljava/lang/String;IZILjava/lang/Object;)I
    ISTORE 4
   L2
    LINENUMBER 125 L2
    ILOAD 4
    IFGE L3
    ALOAD 0
    GOTO L4
   L3
   FRAME FULL [java/lang/String java/lang/String java/lang/String I I] []
    ALOAD 0
    ASTORE 5
    ILOAD 4
    ALOAD 1
    INVOKEVIRTUAL java/lang/String.length ()I
    IADD
    ISTORE 6
    ALOAD 5
    CHECKCAST java/lang/CharSequence
    ILOAD 4
    ILOAD 6
    ALOAD 2
    CHECKCAST java/lang/CharSequence
    INVOKESTATIC kotlin/text/StringsKt.replaceRange (Ljava/lang/CharSequence;IILjava/lang/CharSequence;)Ljava/lang/CharSequence;
    INVOKEVIRTUAL java/lang/Object.toString ()Ljava/lang/String;
   L4
    LINENUMBER 125 L4
   FRAME FULL [java/lang/String java/lang/String java/lang/String I I] [java/lang/String]
    ARETURN
   L5
    LOCALVARIABLE index I L2 L5 4
    LOCALVARIABLE $this$replaceFirst Ljava/lang/String; L0 L5 0
    LOCALVARIABLE oldValue Ljava/lang/String; L0 L5 1
    LOCALVARIABLE newValue Ljava/lang/String; L0 L5 2
    LOCALVARIABLE ignoreCase Z L0 L5 3
    MAXSTACK = 6
    MAXLOCALS = 7

  // access flags 0x19
  // signature (Ljava/lang/CharSequence;Ljava/util/regex/Pattern;I)Ljava/util/List<Ljava/lang/String;>;
  // declaration: java.util.List<java.lang.String> split(java.lang.CharSequence, java.util.regex.Pattern, int)
  public final static split(Ljava/lang/CharSequence;Ljava/util/regex/Pattern;I)Ljava/util/List;
   L0
    ALOAD 0
    LDC "<this>"
    INVOKESTATIC kotlin/jvm/internal/Intrinsics.checkNotNullParameter (Ljava/lang/Object;Ljava/lang/String;)V
    ALOAD 1
    LDC "regex"
    INVOKESTATIC kotlin/jvm/internal/Intrinsics.checkNotNullParameter (Ljava/lang/Object;Ljava/lang/String;)V
   L1
    LINENUMBER 393 L1
    ILOAD 2
    INVOKESTATIC kotlin/text/StringsKt.requireNonNegativeLimit (I)V
   L2
    LINENUMBER 394 L2
    ALOAD 1
    ALOAD 0
    ILOAD 2
    IFNE L3
    ICONST_M1
    GOTO L4
   L3
   FRAME FULL [java/lang/CharSequence java/util/regex/Pattern I] [java/util/regex/Pattern java/lang/CharSequence]
    ILOAD 2
   L4
   FRAME FULL [java/lang/CharSequence java/util/regex/Pattern I] [java/util/regex/Pattern java/lang/CharSequence I]
    INVOKEVIRTUAL java/util/regex/Pattern.split (Ljava/lang/CharSequence;I)[Ljava/lang/String;
    DUP
    LDC "regex.split(this, if (limit == 0) -1 else limit)"
    INVOKESTATIC kotlin/jvm/internal/Intrinsics.checkNotNullExpressionValue (Ljava/lang/Object;Ljava/lang/String;)V
    CHECKCAST [Ljava/lang/Object;
    INVOKESTATIC kotlin/collections/ArraysKt.asList ([Ljava/lang/Object;)Ljava/util/List;
    ARETURN
   L5
    LOCALVARIABLE $this$split Ljava/lang/CharSequence; L0 L5 0
    LOCALVARIABLE regex Ljava/util/regex/Pattern; L0 L5 1
    LOCALVARIABLE limit I L0 L5 2
    MAXSTACK = 3
    MAXLOCALS = 3

  // access flags 0x1A
  private final static toLowerCase(Ljava/lang/String;)Ljava/lang/String;
  @Lkotlin/Deprecated;(message="Use lowercase() instead.", replaceWith=@Lkotlin/ReplaceWith;(expression="lowercase(Locale.getDefault())", imports={"java.util.Locale"}))
  @Lkotlin/DeprecatedSinceKotlin;(warningSince="1.5")
   L0
    ALOAD 0
    LDC "<this>"
    INVOKESTATIC kotlin/jvm/internal/Intrinsics.checkNotNullParameter (Ljava/lang/Object;Ljava/lang/String;)V
   L1
    LINENUMBER 155 L1
    ALOAD 0
    INVOKEVIRTUAL java/lang/String.toLowerCase ()Ljava/lang/String;
    DUP
    LDC "this as java.lang.String).toLowerCase()"
    INVOKESTATIC kotlin/jvm/internal/Intrinsics.checkNotNullExpressionValue (Ljava/lang/Object;Ljava/lang/String;)V
    ARETURN
   L2
    LOCALVARIABLE $this$toLowerCase Ljava/lang/String; L0 L2 0
    MAXSTACK = 3
    MAXLOCALS = 1

  // access flags 0x1A
  private final static toLowerCase(Ljava/lang/String;Ljava/util/Locale;)Ljava/lang/String;
  @Lkotlin/Deprecated;(message="Use lowercase() instead.", replaceWith=@Lkotlin/ReplaceWith;(expression="lowercase(locale)", imports={}))
  @Lkotlin/DeprecatedSinceKotlin;(warningSince="1.5")
   L0
    ALOAD 0
    LDC "<this>"
    INVOKESTATIC kotlin/jvm/internal/Intrinsics.checkNotNullParameter (Ljava/lang/Object;Ljava/lang/String;)V
    ALOAD 1
    LDC "locale"
    INVOKESTATIC kotlin/jvm/internal/Intrinsics.checkNotNullParameter (Ljava/lang/Object;Ljava/lang/String;)V
   L1
    LINENUMBER 664 L1
    ALOAD 0
    ALOAD 1
    INVOKEVIRTUAL java/lang/String.toLowerCase (Ljava/util/Locale;)Ljava/lang/String;
    DUP
    LDC "this as java.lang.String).toLowerCase(locale)"
    INVOKESTATIC kotlin/jvm/internal/Intrinsics.checkNotNullExpressionValue (Ljava/lang/Object;Ljava/lang/String;)V
   L2
    LINENUMBER 664 L2
    ARETURN
   L3
    LOCALVARIABLE $this$toLowerCase Ljava/lang/String; L0 L3 0
    LOCALVARIABLE locale Ljava/util/Locale; L0 L3 1
    MAXSTACK = 3
    MAXLOCALS = 2

  // access flags 0x1A
  private final static toUpperCase(Ljava/lang/String;Ljava/util/Locale;)Ljava/lang/String;
  @Lkotlin/Deprecated;(message="Use uppercase() instead.", replaceWith=@Lkotlin/ReplaceWith;(expression="uppercase(locale)", imports={}))
  @Lkotlin/DeprecatedSinceKotlin;(warningSince="1.5")
   L0
    ALOAD 0
    LDC "<this>"
    INVOKESTATIC kotlin/jvm/internal/Intrinsics.checkNotNullParameter (Ljava/lang/Object;Ljava/lang/String;)V
    ALOAD 1
    LDC "locale"
    INVOKESTATIC kotlin/jvm/internal/Intrinsics.checkNotNullParameter (Ljava/lang/Object;Ljava/lang/String;)V
   L1
    LINENUMBER 685 L1
    ALOAD 0
    ALOAD 1
    INVOKEVIRTUAL java/lang/String.toUpperCase (Ljava/util/Locale;)Ljava/lang/String;
    DUP
    LDC "this as java.lang.String).toUpperCase(locale)"
    INVOKESTATIC kotlin/jvm/internal/Intrinsics.checkNotNullExpressionValue (Ljava/lang/Object;Ljava/lang/String;)V
   L2
    LINENUMBER 685 L2
    ARETURN
   L3
    LOCALVARIABLE $this$toUpperCase Ljava/lang/String; L0 L3 0
    LOCALVARIABLE locale Ljava/util/Locale; L0 L3 1
    MAXSTACK = 3
    MAXLOCALS = 2

  // access flags 0x1A
  private final static toUpperCase(Ljava/lang/String;)Ljava/lang/String;
  @Lkotlin/Deprecated;(message="Use uppercase() instead.", replaceWith=@Lkotlin/ReplaceWith;(expression="uppercase(Locale.getDefault())", imports={"java.util.Locale"}))
  @Lkotlin/DeprecatedSinceKotlin;(warningSince="1.5")
   L0
    ALOAD 0
    LDC "<this>"
    INVOKESTATIC kotlin/jvm/internal/Intrinsics.checkNotNullParameter (Ljava/lang/Object;Ljava/lang/String;)V
   L1
    LINENUMBER 134 L1
    ALOAD 0
    INVOKEVIRTUAL java/lang/String.toUpperCase ()Ljava/lang/String;
    DUP
    LDC "this as java.lang.String).toUpperCase()"
    INVOKESTATIC kotlin/jvm/internal/Intrinsics.checkNotNullExpressionValue (Ljava/lang/Object;Ljava/lang/String;)V
    ARETURN
   L2
    LOCALVARIABLE $this$toUpperCase Ljava/lang/String; L0 L2 0
    MAXSTACK = 3
    MAXLOCALS = 1

  // access flags 0x19
  public final static isBlank(Ljava/lang/CharSequence;)Z
   L0
    ALOAD 0
    LDC "<this>"
    INVOKESTATIC kotlin/jvm/internal/Intrinsics.checkNotNullParameter (Ljava/lang/Object;Ljava/lang/String;)V
   L1
    LINENUMBER 621 L1
    ALOAD 0
    INVOKEINTERFACE java/lang/CharSequence.length ()I (itf)
    IFEQ L2
    ALOAD 0
    INVOKESTATIC kotlin/text/StringsKt.getIndices (Ljava/lang/CharSequence;)Lkotlin/ranges/IntRange;
    CHECKCAST java/lang/Iterable
    ASTORE 1
   L3
    ICONST_0
    ISTORE 2
   L4
    LINENUMBER 829 L4
    ALOAD 1
    INSTANCEOF java/util/Collection
    IFEQ L5
    ALOAD 1
    CHECKCAST java/util/Collection
    INVOKEINTERFACE java/util/Collection.isEmpty ()Z (itf)
    IFEQ L5
    ICONST_1
    GOTO L6
   L5
    LINENUMBER 830 L5
   FRAME FULL [java/lang/CharSequence java/lang/Iterable I] []
    ALOAD 1
    INVOKEINTERFACE java/lang/Iterable.iterator ()Ljava/util/Iterator; (itf)
    ASTORE 3
   L7
   FRAME FULL [java/lang/CharSequence java/lang/Iterable I java/util/Iterator] []
    ALOAD 3
    INVOKEINTERFACE java/util/Iterator.hasNext ()Z (itf)
    IFEQ L8
    ALOAD 3
    CHECKCAST kotlin/collections/IntIterator
    INVOKEVIRTUAL kotlin/collections/IntIterator.nextInt ()I
    ISTORE 4
   L9
    ILOAD 4
    ISTORE 5
   L10
    ICONST_0
    ISTORE 6
   L11
    LINENUMBER 621 L11
    ALOAD 0
    ILOAD 5
    INVOKEINTERFACE java/lang/CharSequence.charAt (I)C (itf)
    INVOKESTATIC kotlin/text/CharsKt.isWhitespace (C)Z
   L12
    IFNE L7
    ICONST_0
    GOTO L6
   L8
    LINENUMBER 831 L8
   FRAME FULL [java/lang/CharSequence java/lang/Iterable I java/util/Iterator] []
    ICONST_1
   L6
   FRAME FULL [java/lang/CharSequence java/lang/Iterable I] [I]
    IFEQ L13
   L2
   FRAME FULL [java/lang/CharSequence] []
    ICONST_1
    GOTO L14
   L13
   FRAME FULL [java/lang/CharSequence java/lang/Iterable I] []
    ICONST_0
   L14
    LINENUMBER 621 L14
   FRAME FULL [java/lang/CharSequence] [I]
    IRETURN
   L15
    LOCALVARIABLE $i$a$-all-StringsKt__StringsJVMKt$isBlank$1 I L11 L12 6
    LOCALVARIABLE it I L10 L12 5
    LOCALVARIABLE element$iv I L9 L8 4
    LOCALVARIABLE $i$f$all I L4 L6 2
    LOCALVARIABLE $this$all$iv Ljava/lang/Iterable; L3 L6 1
    LOCALVARIABLE $this$isBlank Ljava/lang/CharSequence; L0 L15 0
    MAXSTACK = 2
    MAXLOCALS = 7

  // access flags 0x19
  public final static repeat(Ljava/lang/CharSequence;I)Ljava/lang/String;
   L0
    ALOAD 0
    LDC "<this>"
    INVOKESTATIC kotlin/jvm/internal/Intrinsics.checkNotNullParameter (Ljava/lang/Object;Ljava/lang/String;)V
   L1
    LINENUMBER 795 L1
    ILOAD 1
    IFLT L2
    ICONST_1
    GOTO L3
   L2
   FRAME FULL [java/lang/CharSequence I] []
    ICONST_0
   L3
   FRAME FULL [java/lang/CharSequence I] [I]
    ISTORE 2
    ILOAD 2
    IFNE L4
   L5
    LINENUMBER 828 L5
    ICONST_0
    ISTORE 3
   L6
    LINENUMBER 795 L6
    NEW java/lang/StringBuilder
    DUP
    INVOKESPECIAL java/lang/StringBuilder.<init> ()V
    LDC "Count 'n' must be non-negative, but was "
    INVOKEVIRTUAL java/lang/StringBuilder.append (Ljava/lang/String;)Ljava/lang/StringBuilder;
    ILOAD 1
    INVOKEVIRTUAL java/lang/StringBuilder.append (I)Ljava/lang/StringBuilder;
    BIPUSH 46
    INVOKEVIRTUAL java/lang/StringBuilder.append (C)Ljava/lang/StringBuilder;
    INVOKEVIRTUAL java/lang/StringBuilder.toString ()Ljava/lang/String;
   L7
    LINENUMBER 795 L7
    ASTORE 3
    NEW java/lang/IllegalArgumentException
    DUP
    ALOAD 3
    INVOKEVIRTUAL java/lang/Object.toString ()Ljava/lang/String;
    INVOKESPECIAL java/lang/IllegalArgumentException.<init> (Ljava/lang/String;)V
    ATHROW
   L4
    LINENUMBER 797 L4
   FRAME FULL [java/lang/CharSequence I I] []
    ILOAD 1
    TABLESWITCH
      0: L8
      1: L9
      default: L10
   L8
    LINENUMBER 798 L8
   FRAME FULL [java/lang/CharSequence I I] []
    LDC ""
    GOTO L11
   L9
    LINENUMBER 799 L9
   FRAME FULL [java/lang/CharSequence I I] []
    ALOAD 0
    INVOKEVIRTUAL java/lang/Object.toString ()Ljava/lang/String;
    GOTO L11
   L10
    LINENUMBER 801 L10
   FRAME FULL [java/lang/CharSequence I I] []
    ALOAD 0
    INVOKEINTERFACE java/lang/CharSequence.length ()I (itf)
    TABLESWITCH
      0: L12
      1: L13
      default: L14
   L12
    LINENUMBER 802 L12
   FRAME FULL [java/lang/CharSequence I I] []
    LDC ""
    GOTO L11
   L13
    LINENUMBER 803 L13
   FRAME FULL [java/lang/CharSequence I I] []
    ALOAD 0
    ICONST_0
    INVOKEINTERFACE java/lang/CharSequence.charAt (I)C (itf)
    ISTORE 4
    ILOAD 4
    ISTORE 5
   L15
    LINENUMBER 828 L15
    ICONST_0
    ISTORE 6
   L16
    LINENUMBER 803 L16
    ICONST_0
    ISTORE 7
    ILOAD 1
    NEWARRAY T_CHAR
    ASTORE 8
   L17
   FRAME FULL [java/lang/CharSequence I I T I I I I [C] []
    ILOAD 7
    ILOAD 1
    IF_ICMPGE L18
    ILOAD 7
    ISTORE 9
    ALOAD 8
    ILOAD 9
    ILOAD 5
    CASTORE
    IINC 7 1
    GOTO L17
   L18
   FRAME FULL [java/lang/CharSequence I I T I I I I [C] []
    ALOAD 8
    ASTORE 7
    NEW java/lang/String
    DUP
    ALOAD 7
    INVOKESPECIAL java/lang/String.<init> ([C)V
   L19
    LINENUMBER 803 L19
    NOP
   L20
    LINENUMBER 803 L20
    GOTO L11
   L14
    LINENUMBER 805 L14
   FRAME FULL [java/lang/CharSequence I I] []
    NEW java/lang/StringBuilder
    DUP
    ILOAD 1
    ALOAD 0
    INVOKEINTERFACE java/lang/CharSequence.length ()I (itf)
    IMUL
    INVOKESPECIAL java/lang/StringBuilder.<init> (I)V
    ASTORE 5
   L21
    LINENUMBER 806 L21
    NEW kotlin/ranges/IntRange
    DUP
    ICONST_1
    ILOAD 1
    INVOKESPECIAL kotlin/ranges/IntRange.<init> (II)V
    INVOKEVIRTUAL kotlin/ranges/IntRange.iterator ()Lkotlin/collections/IntIterator;
    ASTORE 6
   L22
   FRAME FULL [java/lang/CharSequence I I T T java/lang/StringBuilder kotlin/collections/IntIterator] []
    ALOAD 6
    INVOKEVIRTUAL kotlin/collections/IntIterator.hasNext ()Z
    IFEQ L23
    ALOAD 6
    INVOKEVIRTUAL kotlin/collections/IntIterator.nextInt ()I
    ISTORE 7
   L24
    LINENUMBER 807 L24
    ALOAD 5
    ALOAD 0
    INVOKEVIRTUAL java/lang/StringBuilder.append (Ljava/lang/CharSequence;)Ljava/lang/StringBuilder;
    POP
   L25
    GOTO L22
   L23
    LINENUMBER 809 L23
   FRAME FULL [java/lang/CharSequence I I T T java/lang/StringBuilder kotlin/collections/IntIterator] []
    ALOAD 5
    INVOKEVIRTUAL java/lang/StringBuilder.toString ()Ljava/lang/String;
   L26
    LINENUMBER 804 L26
    ASTORE 4
   L27
    LINENUMBER 807 L27
    ALOAD 4
    LDC "{\n                    va\u2026tring()\n                }"
    INVOKESTATIC kotlin/jvm/internal/Intrinsics.checkNotNullExpressionValue (Ljava/lang/Object;Ljava/lang/String;)V
    ALOAD 4
   L11
    LINENUMBER 797 L11
   FRAME FULL [java/lang/CharSequence I I] [java/lang/String]
    ARETURN
   L28
    LOCALVARIABLE $i$a$-require-StringsKt__StringsJVMKt$repeat$1 I L6 L7 3
    LOCALVARIABLE $i$a$-let-StringsKt__StringsJVMKt$repeat$2 I L16 L20 6
    LOCALVARIABLE char C L15 L20 5
    LOCALVARIABLE i I L24 L25 7
    LOCALVARIABLE sb Ljava/lang/StringBuilder; L21 L26 5
    LOCALVARIABLE $this$repeat Ljava/lang/CharSequence; L0 L28 0
    LOCALVARIABLE n I L0 L28 1
    MAXSTACK = 4
    MAXLOCALS = 10

  // access flags 0x1A
  private final static toCharArray(Ljava/lang/String;[CIII)[C
   L0
    ALOAD 0
    LDC "<this>"
    INVOKESTATIC kotlin/jvm/internal/Intrinsics.checkNotNullParameter (Ljava/lang/Object;Ljava/lang/String;)V
    ALOAD 1
    LDC "destination"
    INVOKESTATIC kotlin/jvm/internal/Intrinsics.checkNotNullParameter (Ljava/lang/Object;Ljava/lang/String;)V
   L1
    LINENUMBER 325 L1
    ALOAD 0
    ILOAD 3
    ILOAD 4
    ALOAD 1
    ILOAD 2
    INVOKEVIRTUAL java/lang/String.getChars (II[CI)V
   L2
    LINENUMBER 326 L2
    ALOAD 1
    ARETURN
   L3
    LOCALVARIABLE $this$toCharArray Ljava/lang/String; L0 L3 0
    LOCALVARIABLE destination [C L0 L3 1
    LOCALVARIABLE destinationOffset I L0 L3 2
    LOCALVARIABLE startIndex I L0 L3 3
    LOCALVARIABLE endIndex I L0 L3 4
    MAXSTACK = 5
    MAXLOCALS = 5

  // access flags 0x1A
  private final static toCharArray(Ljava/lang/String;)[C
   L0
    ALOAD 0
    LDC "<this>"
    INVOKESTATIC kotlin/jvm/internal/Intrinsics.checkNotNullParameter (Ljava/lang/Object;Ljava/lang/String;)V
   L1
    LINENUMBER 308 L1
    ALOAD 0
    INVOKEVIRTUAL java/lang/String.toCharArray ()[C
    DUP
    LDC "this as java.lang.String).toCharArray()"
    INVOKESTATIC kotlin/jvm/internal/Intrinsics.checkNotNullExpressionValue (Ljava/lang/Object;Ljava/lang/String;)V
    ARETURN
   L2
    LOCALVARIABLE $this$toCharArray Ljava/lang/String; L0 L2 0
    MAXSTACK = 3
    MAXLOCALS = 1

  // access flags 0x19
  public final static toCharArray(Ljava/lang/String;II)[C
   L0
    ALOAD 0
    LDC "<this>"
    INVOKESTATIC kotlin/jvm/internal/Intrinsics.checkNotNullParameter (Ljava/lang/Object;Ljava/lang/String;)V
   L1
    LINENUMBER 209 L1
    GETSTATIC kotlin/collections/AbstractList.Companion : Lkotlin/collections/AbstractList$Companion;
    ILOAD 1
    ILOAD 2
    ALOAD 0
    INVOKEVIRTUAL java/lang/String.length ()I
    INVOKEVIRTUAL kotlin/collections/AbstractList$Companion.checkBoundsIndexes$kotlin_stdlib (III)V
   L2
    LINENUMBER 210 L2
    ALOAD 0
    ASTORE 3
    ILOAD 2
    ILOAD 1
    ISUB
    NEWARRAY T_CHAR
    ASTORE 4
    ICONST_0
    ISTORE 5
    ALOAD 3
    ILOAD 1
    ILOAD 2
    ALOAD 4
    ILOAD 5
    INVOKEVIRTUAL java/lang/String.getChars (II[CI)V
    ALOAD 4
   L3
    LINENUMBER 210 L3
    ARETURN
   L4
    LOCALVARIABLE $this$toCharArray Ljava/lang/String; L0 L4 0
    LOCALVARIABLE startIndex I L0 L4 1
    LOCALVARIABLE endIndex I L0 L4 2
    MAXSTACK = 5
    MAXLOCALS = 6

  // access flags 0x9A
  private final static varargs format(Lkotlin/jvm/internal/StringCompanionObject;Ljava/lang/String;[Ljava/lang/Object;)Ljava/lang/String;
   L0
    ALOAD 0
    LDC "<this>"
    INVOKESTATIC kotlin/jvm/internal/Intrinsics.checkNotNullParameter (Ljava/lang/Object;Ljava/lang/String;)V
    ALOAD 1
    LDC "format"
    INVOKESTATIC kotlin/jvm/internal/Intrinsics.checkNotNullParameter (Ljava/lang/Object;Ljava/lang/String;)V
    ALOAD 2
    LDC "args"
    INVOKESTATIC kotlin/jvm/internal/Intrinsics.checkNotNullParameter (Ljava/lang/Object;Ljava/lang/String;)V
   L1
    LINENUMBER 341 L1
    ALOAD 1
    ALOAD 2
    ALOAD 2
    ARRAYLENGTH
    INVOKESTATIC java/util/Arrays.copyOf ([Ljava/lang/Object;I)[Ljava/lang/Object;
    INVOKESTATIC java/lang/String.format (Ljava/lang/String;[Ljava/lang/Object;)Ljava/lang/String;
    DUP
    LDC "format(format, *args)"
    INVOKESTATIC kotlin/jvm/internal/Intrinsics.checkNotNullExpressionValue (Ljava/lang/Object;Ljava/lang/String;)V
    ARETURN
   L2
    LOCALVARIABLE $this$format Lkotlin/jvm/internal/StringCompanionObject; L0 L2 0
    LOCALVARIABLE format Ljava/lang/String; L0 L2 1
    LOCALVARIABLE args [Ljava/lang/Object; L0 L2 2
    MAXSTACK = 3
    MAXLOCALS = 3

  // access flags 0x109A
  private final static synthetic varargs format(Lkotlin/jvm/internal/StringCompanionObject;Ljava/util/Locale;Ljava/lang/String;[Ljava/lang/Object;)Ljava/lang/String;
  @Lkotlin/Deprecated;(message="Use Kotlin compiler 1.4 to avoid deprecation warning.")
  @Lkotlin/DeprecatedSinceKotlin;(hiddenSince="1.4")
   L0
    ALOAD 0
    LDC "<this>"
    INVOKESTATIC kotlin/jvm/internal/Intrinsics.checkNotNullParameter (Ljava/lang/Object;Ljava/lang/String;)V
    ALOAD 1
    LDC "locale"
    INVOKESTATIC kotlin/jvm/internal/Intrinsics.checkNotNullParameter (Ljava/lang/Object;Ljava/lang/String;)V
    ALOAD 2
    LDC "format"
    INVOKESTATIC kotlin/jvm/internal/Intrinsics.checkNotNullParameter (Ljava/lang/Object;Ljava/lang/String;)V
    ALOAD 3
    LDC "args"
    INVOKESTATIC kotlin/jvm/internal/Intrinsics.checkNotNullParameter (Ljava/lang/Object;Ljava/lang/String;)V
   L1
    LINENUMBER 369 L1
    ALOAD 1
    ALOAD 2
    ALOAD 3
    ALOAD 3
    ARRAYLENGTH
    INVOKESTATIC java/util/Arrays.copyOf ([Ljava/lang/Object;I)[Ljava/lang/Object;
    INVOKESTATIC java/lang/String.format (Ljava/util/Locale;Ljava/lang/String;[Ljava/lang/Object;)Ljava/lang/String;
    DUP
    LDC "format(locale, format, *args)"
    INVOKESTATIC kotlin/jvm/internal/Intrinsics.checkNotNullExpressionValue (Ljava/lang/Object;Ljava/lang/String;)V
    ARETURN
   L2
    LOCALVARIABLE $this$format Lkotlin/jvm/internal/StringCompanionObject; L0 L2 0
    LOCALVARIABLE locale Ljava/util/Locale; L0 L2 1
    LOCALVARIABLE format Ljava/lang/String; L0 L2 2
    LOCALVARIABLE args [Ljava/lang/Object; L0 L2 3
    MAXSTACK = 4
    MAXLOCALS = 4

  // access flags 0x109A
  private final static synthetic varargs format(Ljava/lang/String;Ljava/util/Locale;[Ljava/lang/Object;)Ljava/lang/String;
  @Lkotlin/Deprecated;(message="Use Kotlin compiler 1.4 to avoid deprecation warning.")
  @Lkotlin/DeprecatedSinceKotlin;(hiddenSince="1.4")
   L0
    ALOAD 0
    LDC "<this>"
    INVOKESTATIC kotlin/jvm/internal/Intrinsics.checkNotNullParameter (Ljava/lang/Object;Ljava/lang/String;)V
    ALOAD 1
    LDC "locale"
    INVOKESTATIC kotlin/jvm/internal/Intrinsics.checkNotNullParameter (Ljava/lang/Object;Ljava/lang/String;)V
    ALOAD 2
    LDC "args"
    INVOKESTATIC kotlin/jvm/internal/Intrinsics.checkNotNullParameter (Ljava/lang/Object;Ljava/lang/String;)V
   L1
    LINENUMBER 350 L1
    ALOAD 1
    ALOAD 0
    ALOAD 2
    ALOAD 2
    ARRAYLENGTH
    INVOKESTATIC java/util/Arrays.copyOf ([Ljava/lang/Object;I)[Ljava/lang/Object;
    INVOKESTATIC java/lang/String.format (Ljava/util/Locale;Ljava/lang/String;[Ljava/lang/Object;)Ljava/lang/String;
    DUP
    LDC "format(locale, this, *args)"
    INVOKESTATIC kotlin/jvm/internal/Intrinsics.checkNotNullExpressionValue (Ljava/lang/Object;Ljava/lang/String;)V
    ARETURN
   L2
    LOCALVARIABLE $this$format Ljava/lang/String; L0 L2 0
    LOCALVARIABLE locale Ljava/util/Locale; L0 L2 1
    LOCALVARIABLE args [Ljava/lang/Object; L0 L2 2
    MAXSTACK = 4
    MAXLOCALS = 3

  // access flags 0x9A
  private final static varargs format(Ljava/lang/String;[Ljava/lang/Object;)Ljava/lang/String;
   L0
    ALOAD 0
    LDC "<this>"
    INVOKESTATIC kotlin/jvm/internal/Intrinsics.checkNotNullParameter (Ljava/lang/Object;Ljava/lang/String;)V
    ALOAD 1
    LDC "args"
    INVOKESTATIC kotlin/jvm/internal/Intrinsics.checkNotNullParameter (Ljava/lang/Object;Ljava/lang/String;)V
   L1
    LINENUMBER 334 L1
    ALOAD 0
    ALOAD 1
    ALOAD 1
    ARRAYLENGTH
    INVOKESTATIC java/util/Arrays.copyOf ([Ljava/lang/Object;I)[Ljava/lang/Object;
    INVOKESTATIC java/lang/String.format (Ljava/lang/String;[Ljava/lang/Object;)Ljava/lang/String;
    DUP
    LDC "format(this, *args)"
    INVOKESTATIC kotlin/jvm/internal/Intrinsics.checkNotNullExpressionValue (Ljava/lang/Object;Ljava/lang/String;)V
    ARETURN
   L2
    LOCALVARIABLE $this$format Ljava/lang/String; L0 L2 0
    LOCALVARIABLE args [Ljava/lang/Object; L0 L2 1
    MAXSTACK = 3
    MAXLOCALS = 2

  // access flags 0x1A
  private final static intern(Ljava/lang/String;)Ljava/lang/String;
   L0
    ALOAD 0
    LDC "<this>"
    INVOKESTATIC kotlin/jvm/internal/Intrinsics.checkNotNullParameter (Ljava/lang/Object;Ljava/lang/String;)V
   L1
    LINENUMBER 614 L1
    ALOAD 0
    INVOKEVIRTUAL java/lang/String.intern ()Ljava/lang/String;
    DUP
    LDC "this as java.lang.String).intern()"
    INVOKESTATIC kotlin/jvm/internal/Intrinsics.checkNotNullExpressionValue (Ljava/lang/Object;Ljava/lang/String;)V
    ARETURN
   L2
    LOCALVARIABLE $this$intern Ljava/lang/String; L0 L2 0
    MAXSTACK = 3
    MAXLOCALS = 1

  // access flags 0x1A
  private final static toByteArray(Ljava/lang/String;Ljava/nio/charset/Charset;)[B
   L0
    ALOAD 0
    LDC "<this>"
    INVOKESTATIC kotlin/jvm/internal/Intrinsics.checkNotNullParameter (Ljava/lang/Object;Ljava/lang/String;)V
    ALOAD 1
    LDC "charset"
    INVOKESTATIC kotlin/jvm/internal/Intrinsics.checkNotNullParameter (Ljava/lang/Object;Ljava/lang/String;)V
   L1
    LINENUMBER 705 L1
    ALOAD 0
    ALOAD 1
    INVOKEVIRTUAL java/lang/String.getBytes (Ljava/nio/charset/Charset;)[B
    DUP
    LDC "this as java.lang.String).getBytes(charset)"
    INVOKESTATIC kotlin/jvm/internal/Intrinsics.checkNotNullExpressionValue (Ljava/lang/Object;Ljava/lang/String;)V
    ARETURN
   L2
    LOCALVARIABLE $this$toByteArray Ljava/lang/String; L0 L2 0
    LOCALVARIABLE charset Ljava/nio/charset/Charset; L0 L2 1
    MAXSTACK = 3
    MAXLOCALS = 2
}
// class version 50.0 (50)
// access flags 0x20
class kotlin/text/StringsKt__StringsJVMKt extends kotlin/text/StringsKt__StringNumberConversionsKt {

  // compiled from: StringsJVM.kt

  @Lkotlin/Metadata;(mv={1, 7, 1}, k=5, xi=49, d1={"\u0000~\n\u0000\n\u0002\u0018\u0002\n\u0002\u0010\u000e\n\u0002\u0018\u0002\n\u0002\u0018\u0002\n\u0002\u0008\u0004\n\u0002\u0018\u0002\n\u0000\n\u0002\u0018\u0002\n\u0000\n\u0002\u0010\u0012\n\u0000\n\u0002\u0018\u0002\n\u0000\n\u0002\u0010\u0008\n\u0002\u0008\u0002\n\u0002\u0010\u0019\n\u0000\n\u0002\u0010\u0015\n\u0002\u0008\u0002\n\u0002\u0018\u0002\n\u0002\u0008\u0009\n\u0002\u0010\u000b\n\u0002\u0008\u0003\n\u0002\u0010\r\n\u0002\u0008\n\n\u0002\u0010\u0011\n\u0002\u0010\u0000\n\u0002\u0008\n\n\u0002\u0010\u000c\n\u0002\u0008\u0011\n\u0002\u0010 \n\u0000\n\u0002\u0018\u0002\n\u0002\u0008\u000e\u001a\u0011\u0010\u0007\u001a\u00020\u00022\u0006\u0010\u0008\u001a\u00020\u0009H\u0087\u0008\u001a\u0011\u0010\u0007\u001a\u00020\u00022\u0006\u0010\n\u001a\u00020\u000bH\u0087\u0008\u001a\u0011\u0010\u0007\u001a\u00020\u00022\u0006\u0010\u000c\u001a\u00020\rH\u0087\u0008\u001a\u0019\u0010\u0007\u001a\u00020\u00022\u0006\u0010\u000c\u001a\u00020\r2\u0006\u0010\u000e\u001a\u00020\u000fH\u0087\u0008\u001a!\u0010\u0007\u001a\u00020\u00022\u0006\u0010\u000c\u001a\u00020\r2\u0006\u0010\u0010\u001a\u00020\u00112\u0006\u0010\u0012\u001a\u00020\u0011H\u0087\u0008\u001a)\u0010\u0007\u001a\u00020\u00022\u0006\u0010\u000c\u001a\u00020\r2\u0006\u0010\u0010\u001a\u00020\u00112\u0006\u0010\u0012\u001a\u00020\u00112\u0006\u0010\u000e\u001a\u00020\u000fH\u0087\u0008\u001a\u0011\u0010\u0007\u001a\u00020\u00022\u0006\u0010\u0013\u001a\u00020\u0014H\u0087\u0008\u001a!\u0010\u0007\u001a\u00020\u00022\u0006\u0010\u0013\u001a\u00020\u00142\u0006\u0010\u0010\u001a\u00020\u00112\u0006\u0010\u0012\u001a\u00020\u0011H\u0087\u0008\u001a!\u0010\u0007\u001a\u00020\u00022\u0006\u0010\u0015\u001a\u00020\u00162\u0006\u0010\u0010\u001a\u00020\u00112\u0006\u0010\u0012\u001a\u00020\u0011H\u0087\u0008\u001a\u000c\u0010\u0017\u001a\u00020\u0002*\u00020\u0002H\u0007\u001a\u0014\u0010\u0017\u001a\u00020\u0002*\u00020\u00022\u0006\u0010\u0018\u001a\u00020\u0019H\u0007\u001a\u0015\u0010\u001a\u001a\u00020\u0011*\u00020\u00022\u0006\u0010\u001b\u001a\u00020\u0011H\u0087\u0008\u001a\u0015\u0010\u001c\u001a\u00020\u0011*\u00020\u00022\u0006\u0010\u001b\u001a\u00020\u0011H\u0087\u0008\u001a\u001d\u0010\u001d\u001a\u00020\u0011*\u00020\u00022\u0006\u0010\u001e\u001a\u00020\u00112\u0006\u0010\u001f\u001a\u00020\u0011H\u0087\u0008\u001a\u001c\u0010 \u001a\u00020\u0011*\u00020\u00022\u0006\u0010!\u001a\u00020\u00022\u0008\u0008\u0002\u0010\"\u001a\u00020#\u001a\u000c\u0010$\u001a\u00020\u0002*\u00020\u0014H\u0007\u001a \u0010$\u001a\u00020\u0002*\u00020\u00142\u0008\u0008\u0002\u0010%\u001a\u00020\u00112\u0008\u0008\u0002\u0010\u001f\u001a\u00020\u0011H\u0007\u001a\u0019\u0010&\u001a\u00020#*\u0004\u0018\u00010'2\u0008\u0010!\u001a\u0004\u0018\u00010'H\u0087\u0004\u001a \u0010&\u001a\u00020#*\u0004\u0018\u00010'2\u0008\u0010!\u001a\u0004\u0018\u00010'2\u0006\u0010\"\u001a\u00020#H\u0007\u001a\u0015\u0010&\u001a\u00020#*\u00020\u00022\u0006\u0010\n\u001a\u00020\u0009H\u0087\u0008\u001a\u0015\u0010&\u001a\u00020#*\u00020\u00022\u0006\u0010(\u001a\u00020'H\u0087\u0008\u001a\u000c\u0010)\u001a\u00020\u0002*\u00020\u0002H\u0007\u001a\u0014\u0010)\u001a\u00020\u0002*\u00020\u00022\u0006\u0010\u0018\u001a\u00020\u0019H\u0007\u001a\u000c\u0010*\u001a\u00020\u0002*\u00020\rH\u0007\u001a*\u0010*\u001a\u00020\u0002*\u00020\r2\u0008\u0008\u0002\u0010%\u001a\u00020\u00112\u0008\u0008\u0002\u0010\u001f\u001a\u00020\u00112\u0008\u0008\u0002\u0010+\u001a\u00020#H\u0007\u001a\u000c\u0010,\u001a\u00020\r*\u00020\u0002H\u0007\u001a*\u0010,\u001a\u00020\r*\u00020\u00022\u0008\u0008\u0002\u0010%\u001a\u00020\u00112\u0008\u0008\u0002\u0010\u001f\u001a\u00020\u00112\u0008\u0008\u0002\u0010+\u001a\u00020#H\u0007\u001a\u001c\u0010-\u001a\u00020#*\u00020\u00022\u0006\u0010.\u001a\u00020\u00022\u0008\u0008\u0002\u0010\"\u001a\u00020#\u001a \u0010/\u001a\u00020#*\u0004\u0018\u00010\u00022\u0008\u0010!\u001a\u0004\u0018\u00010\u00022\u0008\u0008\u0002\u0010\"\u001a\u00020#\u001a2\u00100\u001a\u00020\u0002*\u00020\u00022\u0006\u0010\u0018\u001a\u00020\u00192\u0016\u00101\u001a\u000c\u0012\u0008\u0008\u0001\u0012\u0004\u0018\u00010302\"\u0004\u0018\u000103H\u0087\u0008\u00a2\u0006\u0002\u00104\u001a6\u00100\u001a\u00020\u0002*\u00020\u00022\u0008\u0010\u0018\u001a\u0004\u0018\u00010\u00192\u0016\u00101\u001a\u000c\u0012\u0008\u0008\u0001\u0012\u0004\u0018\u00010302\"\u0004\u0018\u000103H\u0087\u0008\u00a2\u0006\u0004\u00085\u00104\u001a*\u00100\u001a\u00020\u0002*\u00020\u00022\u0016\u00101\u001a\u000c\u0012\u0008\u0008\u0001\u0012\u0004\u0018\u00010302\"\u0004\u0018\u000103H\u0087\u0008\u00a2\u0006\u0002\u00106\u001a:\u00100\u001a\u00020\u0002*\u00020\u00042\u0006\u0010\u0018\u001a\u00020\u00192\u0006\u00100\u001a\u00020\u00022\u0016\u00101\u001a\u000c\u0012\u0008\u0008\u0001\u0012\u0004\u0018\u00010302\"\u0004\u0018\u000103H\u0087\u0008\u00a2\u0006\u0002\u00107\u001a>\u00100\u001a\u00020\u0002*\u00020\u00042\u0008\u0010\u0018\u001a\u0004\u0018\u00010\u00192\u0006\u00100\u001a\u00020\u00022\u0016\u00101\u001a\u000c\u0012\u0008\u0008\u0001\u0012\u0004\u0018\u00010302\"\u0004\u0018\u000103H\u0087\u0008\u00a2\u0006\u0004\u00085\u00107\u001a2\u00100\u001a\u00020\u0002*\u00020\u00042\u0006\u00100\u001a\u00020\u00022\u0016\u00101\u001a\u000c\u0012\u0008\u0008\u0001\u0012\u0004\u0018\u00010302\"\u0004\u0018\u000103H\u0087\u0008\u00a2\u0006\u0002\u00108\u001a\r\u00109\u001a\u00020\u0002*\u00020\u0002H\u0087\u0008\u001a\n\u0010:\u001a\u00020#*\u00020'\u001a\r\u0010;\u001a\u00020\u0002*\u00020\u0002H\u0087\u0008\u001a\u0015\u0010;\u001a\u00020\u0002*\u00020\u00022\u0006\u0010\u0018\u001a\u00020\u0019H\u0087\u0008\u001a\u001d\u0010<\u001a\u00020\u0011*\u00020\u00022\u0006\u0010=\u001a\u00020>2\u0006\u0010?\u001a\u00020\u0011H\u0081\u0008\u001a\u001d\u0010<\u001a\u00020\u0011*\u00020\u00022\u0006\u0010@\u001a\u00020\u00022\u0006\u0010?\u001a\u00020\u0011H\u0081\u0008\u001a\u001d\u0010A\u001a\u00020\u0011*\u00020\u00022\u0006\u0010=\u001a\u00020>2\u0006\u0010?\u001a\u00020\u0011H\u0081\u0008\u001a\u001d\u0010A\u001a\u00020\u0011*\u00020\u00022\u0006\u0010@\u001a\u00020\u00022\u0006\u0010?\u001a\u00020\u0011H\u0081\u0008\u001a\u001d\u0010B\u001a\u00020\u0011*\u00020\u00022\u0006\u0010\u001b\u001a\u00020\u00112\u0006\u0010C\u001a\u00020\u0011H\u0087\u0008\u001a4\u0010D\u001a\u00020#*\u00020'2\u0006\u0010E\u001a\u00020\u00112\u0006\u0010!\u001a\u00020'2\u0006\u0010F\u001a\u00020\u00112\u0006\u0010\u0012\u001a\u00020\u00112\u0008\u0008\u0002\u0010\"\u001a\u00020#\u001a4\u0010D\u001a\u00020#*\u00020\u00022\u0006\u0010E\u001a\u00020\u00112\u0006\u0010!\u001a\u00020\u00022\u0006\u0010F\u001a\u00020\u00112\u0006\u0010\u0012\u001a\u00020\u00112\u0008\u0008\u0002\u0010\"\u001a\u00020#\u001a\u0012\u0010G\u001a\u00020\u0002*\u00020'2\u0006\u0010H\u001a\u00020\u0011\u001a$\u0010I\u001a\u00020\u0002*\u00020\u00022\u0006\u0010J\u001a\u00020>2\u0006\u0010K\u001a\u00020>2\u0008\u0008\u0002\u0010\"\u001a\u00020#\u001a$\u0010I\u001a\u00020\u0002*\u00020\u00022\u0006\u0010L\u001a\u00020\u00022\u0006\u0010M\u001a\u00020\u00022\u0008\u0008\u0002\u0010\"\u001a\u00020#\u001a$\u0010N\u001a\u00020\u0002*\u00020\u00022\u0006\u0010J\u001a\u00020>2\u0006\u0010K\u001a\u00020>2\u0008\u0008\u0002\u0010\"\u001a\u00020#\u001a$\u0010N\u001a\u00020\u0002*\u00020\u00022\u0006\u0010L\u001a\u00020\u00022\u0006\u0010M\u001a\u00020\u00022\u0008\u0008\u0002\u0010\"\u001a\u00020#\u001a\"\u0010O\u001a\u0008\u0012\u0004\u0012\u00020\u00020P*\u00020'2\u0006\u0010Q\u001a\u00020R2\u0008\u0008\u0002\u0010S\u001a\u00020\u0011\u001a\u001c\u0010T\u001a\u00020#*\u00020\u00022\u0006\u0010U\u001a\u00020\u00022\u0008\u0008\u0002\u0010\"\u001a\u00020#\u001a$\u0010T\u001a\u00020#*\u00020\u00022\u0006\u0010U\u001a\u00020\u00022\u0006\u0010%\u001a\u00020\u00112\u0008\u0008\u0002\u0010\"\u001a\u00020#\u001a\u0015\u0010V\u001a\u00020\u0002*\u00020\u00022\u0006\u0010%\u001a\u00020\u0011H\u0087\u0008\u001a\u001d\u0010V\u001a\u00020\u0002*\u00020\u00022\u0006\u0010%\u001a\u00020\u00112\u0006\u0010\u001f\u001a\u00020\u0011H\u0087\u0008\u001a\u0017\u0010W\u001a\u00020\r*\u00020\u00022\u0008\u0008\u0002\u0010\u000e\u001a\u00020\u000fH\u0087\u0008\u001a\r\u0010X\u001a\u00020\u0014*\u00020\u0002H\u0087\u0008\u001a3\u0010X\u001a\u00020\u0014*\u00020\u00022\u0006\u0010Y\u001a\u00020\u00142\u0008\u0008\u0002\u0010Z\u001a\u00020\u00112\u0008\u0008\u0002\u0010%\u001a\u00020\u00112\u0008\u0008\u0002\u0010\u001f\u001a\u00020\u0011H\u0087\u0008\u001a \u0010X\u001a\u00020\u0014*\u00020\u00022\u0008\u0008\u0002\u0010%\u001a\u00020\u00112\u0008\u0008\u0002\u0010\u001f\u001a\u00020\u0011H\u0007\u001a\r\u0010[\u001a\u00020\u0002*\u00020\u0002H\u0087\u0008\u001a\u0015\u0010[\u001a\u00020\u0002*\u00020\u00022\u0006\u0010\u0018\u001a\u00020\u0019H\u0087\u0008\u001a\u0017\u0010\\\u001a\u00020R*\u00020\u00022\u0008\u0008\u0002\u0010]\u001a\u00020\u0011H\u0087\u0008\u001a\r\u0010^\u001a\u00020\u0002*\u00020\u0002H\u0087\u0008\u001a\u0015\u0010^\u001a\u00020\u0002*\u00020\u00022\u0006\u0010\u0018\u001a\u00020\u0019H\u0087\u0008\u001a\r\u0010_\u001a\u00020\u0002*\u00020\u0002H\u0087\u0008\u001a\u0015\u0010_\u001a\u00020\u0002*\u00020\u00022\u0006\u0010\u0018\u001a\u00020\u0019H\u0087\u0008\"%\u0010\u0000\u001a\u0012\u0012\u0004\u0012\u00020\u00020\u0001j\u0008\u0012\u0004\u0012\u00020\u0002`\u0003*\u00020\u00048F\u00a2\u0006\u0006\u001a\u0004\u0008\u0005\u0010\u0006\u00a8\u0006`"}, d2={"CASE_INSENSITIVE_ORDER", "Ljava/util/Comparator;", "", "Lkotlin/Comparator;", "Lkotlin/String$Companion;", "getCASE_INSENSITIVE_ORDER", "(Lkotlin/jvm/internal/StringCompanionObject;)Ljava/util/Comparator;", "String", "stringBuffer", "Ljava/lang/StringBuffer;", "stringBuilder", "Ljava/lang/StringBuilder;", "bytes", "", "charset", "Ljava/nio/charset/Charset;", "offset", "", "length", "chars", "", "codePoints", "", "capitalize", "locale", "Ljava/util/Locale;", "codePointAt", "index", "codePointBefore", "codePointCount", "beginIndex", "endIndex", "compareTo", "other", "ignoreCase", "", "concatToString", "startIndex", "contentEquals", "", "charSequence", "decapitalize", "decodeToString", "throwOnInvalidSequence", "encodeToByteArray", "endsWith", "suffix", "equals", "format", "args", "", "", "(Ljava/lang/String;Ljava/util/Locale;[Ljava/lang/Object;)Ljava/lang/String;", "formatNullable", "(Ljava/lang/String;[Ljava/lang/Object;)Ljava/lang/String;", "(Lkotlin/jvm/internal/StringCompanionObject;Ljava/util/Locale;Ljava/lang/String;[Ljava/lang/Object;)Ljava/lang/String;", "(Lkotlin/jvm/internal/StringCompanionObject;Ljava/lang/String;[Ljava/lang/Object;)Ljava/lang/String;", "intern", "isBlank", "lowercase", "nativeIndexOf", "ch", "", "fromIndex", "str", "nativeLastIndexOf", "offsetByCodePoints", "codePointOffset", "regionMatches", "thisOffset", "otherOffset", "repeat", "n", "replace", "oldChar", "newChar", "oldValue", "newValue", "replaceFirst", "split", "", "regex", "Ljava/util/regex/Pattern;", "limit", "startsWith", "prefix", "substring", "toByteArray", "toCharArray", "destination", "destinationOffset", "toLowerCase", "toPattern", "flags", "toUpperCase", "uppercase", "kotlin-stdlib"}, xs="kotlin/text/StringsKt")

  // access flags 0x1A
  private final static String([III)Ljava/lang/String;
   L0
    ALOAD 0
    LDC "codePoints"
    INVOKESTATIC kotlin/jvm/internal/Intrinsics.checkNotNullParameter (Ljava/lang/Object;Ljava/lang/String;)V
   L1
    LINENUMBER 509 L1
    NEW java/lang/String
    DUP
    ALOAD 0
    ILOAD 1
    ILOAD 2
    INVOKESPECIAL java/lang/String.<init> ([III)V
    ARETURN
   L2
    LOCALVARIABLE codePoints [I L0 L2 0
    LOCALVARIABLE offset I L0 L2 1
    LOCALVARIABLE length I L0 L2 2
    MAXSTACK = 5
    MAXLOCALS = 3

  // access flags 0x1A
  private final static String([CII)Ljava/lang/String;
   L0
    ALOAD 0
    LDC "chars"
    INVOKESTATIC kotlin/jvm/internal/Intrinsics.checkNotNullParameter (Ljava/lang/Object;Ljava/lang/String;)V
   L1
    LINENUMBER 502 L1
    NEW java/lang/String
    DUP
    ALOAD 0
    ILOAD 1
    ILOAD 2
    INVOKESPECIAL java/lang/String.<init> ([CII)V
    ARETURN
   L2
    LOCALVARIABLE chars [C L0 L2 0
    LOCALVARIABLE offset I L0 L2 1
    LOCALVARIABLE length I L0 L2 2
    MAXSTACK = 5
    MAXLOCALS = 3

  // access flags 0x1A
  private final static String([C)Ljava/lang/String;
   L0
    ALOAD 0
    LDC "chars"
    INVOKESTATIC kotlin/jvm/internal/Intrinsics.checkNotNullParameter (Ljava/lang/Object;Ljava/lang/String;)V
   L1
    LINENUMBER 492 L1
    NEW java/lang/String
    DUP
    ALOAD 0
    INVOKESPECIAL java/lang/String.<init> ([C)V
    ARETURN
   L2
    LOCALVARIABLE chars [C L0 L2 0
    MAXSTACK = 3
    MAXLOCALS = 1

  // access flags 0x1A
  private final static String([B)Ljava/lang/String;
   L0
    ALOAD 0
    LDC "bytes"
    INVOKESTATIC kotlin/jvm/internal/Intrinsics.checkNotNullParameter (Ljava/lang/Object;Ljava/lang/String;)V
   L1
    LINENUMBER 485 L1
    NEW java/lang/String
    DUP
    ALOAD 0
    GETSTATIC kotlin/text/Charsets.UTF_8 : Ljava/nio/charset/Charset;
    INVOKESPECIAL java/lang/String.<init> ([BLjava/nio/charset/Charset;)V
    ARETURN
   L2
    LOCALVARIABLE bytes [B L0 L2 0
    MAXSTACK = 4
    MAXLOCALS = 1

  // access flags 0x1A
  private final static String([BII)Ljava/lang/String;
   L0
    ALOAD 0
    LDC "bytes"
    INVOKESTATIC kotlin/jvm/internal/Intrinsics.checkNotNullParameter (Ljava/lang/Object;Ljava/lang/String;)V
   L1
    LINENUMBER 477 L1
    NEW java/lang/String
    DUP
    ALOAD 0
    ILOAD 1
    ILOAD 2
    GETSTATIC kotlin/text/Charsets.UTF_8 : Ljava/nio/charset/Charset;
    INVOKESPECIAL java/lang/String.<init> ([BIILjava/nio/charset/Charset;)V
    ARETURN
   L2
    LOCALVARIABLE bytes [B L0 L2 0
    LOCALVARIABLE offset I L0 L2 1
    LOCALVARIABLE length I L0 L2 2
    MAXSTACK = 6
    MAXLOCALS = 3

  // access flags 0x1A
  private final static String([BLjava/nio/charset/Charset;)Ljava/lang/String;
   L0
    ALOAD 0
    LDC "bytes"
    INVOKESTATIC kotlin/jvm/internal/Intrinsics.checkNotNullParameter (Ljava/lang/Object;Ljava/lang/String;)V
    ALOAD 1
    LDC "charset"
    INVOKESTATIC kotlin/jvm/internal/Intrinsics.checkNotNullParameter (Ljava/lang/Object;Ljava/lang/String;)V
   L1
    LINENUMBER 465 L1
    NEW java/lang/String
    DUP
    ALOAD 0
    ALOAD 1
    INVOKESPECIAL java/lang/String.<init> ([BLjava/nio/charset/Charset;)V
    ARETURN
   L2
    LOCALVARIABLE bytes [B L0 L2 0
    LOCALVARIABLE charset Ljava/nio/charset/Charset; L0 L2 1
    MAXSTACK = 4
    MAXLOCALS = 2

  // access flags 0x1A
  private final static String([BIILjava/nio/charset/Charset;)Ljava/lang/String;
   L0
    ALOAD 0
    LDC "bytes"
    INVOKESTATIC kotlin/jvm/internal/Intrinsics.checkNotNullParameter (Ljava/lang/Object;Ljava/lang/String;)V
    ALOAD 3
    LDC "charset"
    INVOKESTATIC kotlin/jvm/internal/Intrinsics.checkNotNullParameter (Ljava/lang/Object;Ljava/lang/String;)V
   L1
    LINENUMBER 458 L1
    NEW java/lang/String
    DUP
    ALOAD 0
    ILOAD 1
    ILOAD 2
    ALOAD 3
    INVOKESPECIAL java/lang/String.<init> ([BIILjava/nio/charset/Charset;)V
    ARETURN
   L2
    LOCALVARIABLE bytes [B L0 L2 0
    LOCALVARIABLE offset I L0 L2 1
    LOCALVARIABLE length I L0 L2 2
    LOCALVARIABLE charset Ljava/nio/charset/Charset; L0 L2 3
    MAXSTACK = 6
    MAXLOCALS = 4

  // access flags 0x1A
  private final static String(Ljava/lang/StringBuilder;)Ljava/lang/String;
   L0
    ALOAD 0
    LDC "stringBuilder"
    INVOKESTATIC kotlin/jvm/internal/Intrinsics.checkNotNullParameter (Ljava/lang/Object;Ljava/lang/String;)V
   L1
    LINENUMBER 523 L1
    NEW java/lang/String
    DUP
    ALOAD 0
    INVOKESPECIAL java/lang/String.<init> (Ljava/lang/StringBuilder;)V
    ARETURN
   L2
    LOCALVARIABLE stringBuilder Ljava/lang/StringBuilder; L0 L2 0
    MAXSTACK = 3
    MAXLOCALS = 1

  // access flags 0x1A
  private final static String(Ljava/lang/StringBuffer;)Ljava/lang/String;
   L0
    ALOAD 0
    LDC "stringBuffer"
    INVOKESTATIC kotlin/jvm/internal/Intrinsics.checkNotNullParameter (Ljava/lang/Object;Ljava/lang/String;)V
   L1
    LINENUMBER 516 L1
    NEW java/lang/String
    DUP
    ALOAD 0
    INVOKESPECIAL java/lang/String.<init> (Ljava/lang/StringBuffer;)V
    ARETURN
   L2
    LOCALVARIABLE stringBuffer Ljava/lang/StringBuffer; L0 L2 0
    MAXSTACK = 3
    MAXLOCALS = 1

  // access flags 0x1A
  private final static lowercase(Ljava/lang/String;)Ljava/lang/String;
   L0
    ALOAD 0
    LDC "<this>"
    INVOKESTATIC kotlin/jvm/internal/Intrinsics.checkNotNullParameter (Ljava/lang/Object;Ljava/lang/String;)V
   L1
    LINENUMBER 168 L1
    ALOAD 0
    GETSTATIC java/util/Locale.ROOT : Ljava/util/Locale;
    INVOKEVIRTUAL java/lang/String.toLowerCase (Ljava/util/Locale;)Ljava/lang/String;
    DUP
    LDC "this as java.lang.String).toLowerCase(Locale.ROOT)"
    INVOKESTATIC kotlin/jvm/internal/Intrinsics.checkNotNullExpressionValue (Ljava/lang/Object;Ljava/lang/String;)V
    ARETURN
   L2
    LOCALVARIABLE $this$lowercase Ljava/lang/String; L0 L2 0
    MAXSTACK = 3
    MAXLOCALS = 1

  // access flags 0x1A
  private final static lowercase(Ljava/lang/String;Ljava/util/Locale;)Ljava/lang/String;
   L0
    ALOAD 0
    LDC "<this>"
    INVOKESTATIC kotlin/jvm/internal/Intrinsics.checkNotNullParameter (Ljava/lang/Object;Ljava/lang/String;)V
    ALOAD 1
    LDC "locale"
    INVOKESTATIC kotlin/jvm/internal/Intrinsics.checkNotNullParameter (Ljava/lang/Object;Ljava/lang/String;)V
   L1
    LINENUMBER 677 L1
    ALOAD 0
    ALOAD 1
    INVOKEVIRTUAL java/lang/String.toLowerCase (Ljava/util/Locale;)Ljava/lang/String;
    DUP
    LDC "this as java.lang.String).toLowerCase(locale)"
    INVOKESTATIC kotlin/jvm/internal/Intrinsics.checkNotNullExpressionValue (Ljava/lang/Object;Ljava/lang/String;)V
    ARETURN
   L2
    LOCALVARIABLE $this$lowercase Ljava/lang/String; L0 L2 0
    LOCALVARIABLE locale Ljava/util/Locale; L0 L2 1
    MAXSTACK = 3
    MAXLOCALS = 2

  // access flags 0x1A
  private final static toPattern(Ljava/lang/String;I)Ljava/util/regex/Pattern;
   L0
    ALOAD 0
    LDC "<this>"
    INVOKESTATIC kotlin/jvm/internal/Intrinsics.checkNotNullParameter (Ljava/lang/Object;Ljava/lang/String;)V
   L1
    LINENUMBER 714 L1
    ALOAD 0
    ILOAD 1
    INVOKESTATIC java/util/regex/Pattern.compile (Ljava/lang/String;I)Ljava/util/regex/Pattern;
    DUP
    LDC "compile(this, flags)"
    INVOKESTATIC kotlin/jvm/internal/Intrinsics.checkNotNullExpressionValue (Ljava/lang/Object;Ljava/lang/String;)V
    ARETURN
   L2
    LOCALVARIABLE $this$toPattern Ljava/lang/String; L0 L2 0
    LOCALVARIABLE flags I L0 L2 1
    MAXSTACK = 3
    MAXLOCALS = 2

  // access flags 0x1A
  private final static uppercase(Ljava/lang/String;)Ljava/lang/String;
   L0
    ALOAD 0
    LDC "<this>"
    INVOKESTATIC kotlin/jvm/internal/Intrinsics.checkNotNullParameter (Ljava/lang/Object;Ljava/lang/String;)V
   L1
    LINENUMBER 147 L1
    ALOAD 0
    GETSTATIC java/util/Locale.ROOT : Ljava/util/Locale;
    INVOKEVIRTUAL java/lang/String.toUpperCase (Ljava/util/Locale;)Ljava/lang/String;
    DUP
    LDC "this as java.lang.String).toUpperCase(Locale.ROOT)"
    INVOKESTATIC kotlin/jvm/internal/Intrinsics.checkNotNullExpressionValue (Ljava/lang/Object;Ljava/lang/String;)V
    ARETURN
   L2
    LOCALVARIABLE $this$uppercase Ljava/lang/String; L0 L2 0
    MAXSTACK = 3
    MAXLOCALS = 1

  // access flags 0x1A
  private final static uppercase(Ljava/lang/String;Ljava/util/Locale;)Ljava/lang/String;
   L0
    ALOAD 0
    LDC "<this>"
    INVOKESTATIC kotlin/jvm/internal/Intrinsics.checkNotNullParameter (Ljava/lang/Object;Ljava/lang/String;)V
    ALOAD 1
    LDC "locale"
    INVOKESTATIC kotlin/jvm/internal/Intrinsics.checkNotNullParameter (Ljava/lang/Object;Ljava/lang/String;)V
   L1
    LINENUMBER 698 L1
    ALOAD 0
    ALOAD 1
    INVOKEVIRTUAL java/lang/String.toUpperCase (Ljava/util/Locale;)Ljava/lang/String;
    DUP
    LDC "this as java.lang.String).toUpperCase(locale)"
    INVOKESTATIC kotlin/jvm/internal/Intrinsics.checkNotNullExpressionValue (Ljava/lang/Object;Ljava/lang/String;)V
    ARETURN
   L2
    LOCALVARIABLE $this$uppercase Ljava/lang/String; L0 L2 0
    LOCALVARIABLE locale Ljava/util/Locale; L0 L2 1
    MAXSTACK = 3
    MAXLOCALS = 2

  // access flags 0x1009
  public static synthetic split$default(Ljava/lang/CharSequence;Ljava/util/regex/Pattern;IILjava/lang/Object;)Ljava/util/List;
   L0
    LINENUMBER 392 L0
    ILOAD 3
    ICONST_2
    IAND
    IFEQ L1
    ICONST_0
    ISTORE 2
   L1
   FRAME FULL [java/lang/CharSequence java/util/regex/Pattern I I java/lang/Object] []
    ALOAD 0
    ALOAD 1
    ILOAD 2
    INVOKESTATIC kotlin/text/StringsKt.split (Ljava/lang/CharSequence;Ljava/util/regex/Pattern;I)Ljava/util/List;
    ARETURN
    MAXSTACK = 3
    MAXLOCALS = 5

  // access flags 0x1009
  public static synthetic startsWith$default(Ljava/lang/String;Ljava/lang/String;ZILjava/lang/Object;)Z
   L0
    LINENUMBER 416 L0
    ILOAD 3
    ICONST_2
    IAND
    IFEQ L1
    ICONST_0
    ISTORE 2
   L1
   FRAME FULL [java/lang/String java/lang/String I I java/lang/Object] []
    ALOAD 0
    ALOAD 1
    ILOAD 2
    INVOKESTATIC kotlin/text/StringsKt.startsWith (Ljava/lang/String;Ljava/lang/String;Z)Z
    IRETURN
    MAXSTACK = 3
    MAXLOCALS = 5

  // access flags 0x1009
  public static synthetic startsWith$default(Ljava/lang/String;Ljava/lang/String;IZILjava/lang/Object;)Z
   L0
    LINENUMBER 427 L0
    ILOAD 4
    ICONST_4
    IAND
    IFEQ L1
    ICONST_0
    ISTORE 3
   L1
   FRAME FULL [java/lang/String java/lang/String I I I java/lang/Object] []
    ALOAD 0
    ALOAD 1
    ILOAD 2
    ILOAD 3
    INVOKESTATIC kotlin/text/StringsKt.startsWith (Ljava/lang/String;Ljava/lang/String;IZ)Z
    IRETURN
    MAXSTACK = 4
    MAXLOCALS = 6

  // access flags 0x1009
  public static synthetic endsWith$default(Ljava/lang/String;Ljava/lang/String;ZILjava/lang/Object;)Z
   L0
    LINENUMBER 438 L0
    ILOAD 3
    ICONST_2
    IAND
    IFEQ L1
    ICONST_0
    ISTORE 2
   L1
   FRAME FULL [java/lang/String java/lang/String I I java/lang/Object] []
    ALOAD 0
    ALOAD 1
    ILOAD 2
    INVOKESTATIC kotlin/text/StringsKt.endsWith (Ljava/lang/String;Ljava/lang/String;Z)Z
    IRETURN
    MAXSTACK = 3
    MAXLOCALS = 5

  // access flags 0x1009
  public static synthetic replaceFirst$default(Ljava/lang/String;Ljava/lang/String;Ljava/lang/String;ZILjava/lang/Object;)Ljava/lang/String;
   L0
    LINENUMBER 123 L0
    ILOAD 4
    ICONST_4
    IAND
    IFEQ L1
    ICONST_0
    ISTORE 3
   L1
   FRAME FULL [java/lang/String java/lang/String java/lang/String I I java/lang/Object] []
    ALOAD 0
    ALOAD 1
    ALOAD 2
    ILOAD 3
    INVOKESTATIC kotlin/text/StringsKt.replaceFirst (Ljava/lang/String;Ljava/lang/String;Ljava/lang/String;Z)Ljava/lang/String;
    ARETURN
    MAXSTACK = 4
    MAXLOCALS = 6

  // access flags 0x1009
  public static synthetic replaceFirst$default(Ljava/lang/String;CCZILjava/lang/Object;)Ljava/lang/String;
   L0
    LINENUMBER 113 L0
    ILOAD 4
    ICONST_4
    IAND
    IFEQ L1
    ICONST_0
    ISTORE 3
   L1
   FRAME FULL [java/lang/String I I I I java/lang/Object] []
    ALOAD 0
    ILOAD 1
    ILOAD 2
    ILOAD 3
    INVOKESTATIC kotlin/text/StringsKt.replaceFirst (Ljava/lang/String;CCZ)Ljava/lang/String;
    ARETURN
    MAXSTACK = 4
    MAXLOCALS = 6

  // access flags 0x1009
  public static synthetic replace$default(Ljava/lang/String;CCZILjava/lang/Object;)Ljava/lang/String;
   L0
    LINENUMBER 68 L0
    ILOAD 4
    ICONST_4
    IAND
    IFEQ L1
    ICONST_0
    ISTORE 3
   L1
   FRAME FULL [java/lang/String I I I I java/lang/Object] []
    ALOAD 0
    ILOAD 1
    ILOAD 2
    ILOAD 3
    INVOKESTATIC kotlin/text/StringsKt.replace (Ljava/lang/String;CCZ)Ljava/lang/String;
    ARETURN
    MAXSTACK = 4
    MAXLOCALS = 6

  // access flags 0x1009
  public static synthetic replace$default(Ljava/lang/String;Ljava/lang/String;Ljava/lang/String;ZILjava/lang/Object;)Ljava/lang/String;
   L0
    LINENUMBER 86 L0
    ILOAD 4
    ICONST_4
    IAND
    IFEQ L1
    ICONST_0
    ISTORE 3
   L1
   FRAME FULL [java/lang/String java/lang/String java/lang/String I I java/lang/Object] []
    ALOAD 0
    ALOAD 1
    ALOAD 2
    ILOAD 3
    INVOKESTATIC kotlin/text/StringsKt.replace (Ljava/lang/String;Ljava/lang/String;Ljava/lang/String;Z)Ljava/lang/String;
    ARETURN
    MAXSTACK = 4
    MAXLOCALS = 6

  // access flags 0x1009
  public static synthetic equals$default(Ljava/lang/String;Ljava/lang/String;ZILjava/lang/Object;)Z
   L0
    LINENUMBER 53 L0
    ILOAD 3
    ICONST_2
    IAND
    IFEQ L1
    ICONST_0
    ISTORE 2
   L1
   FRAME FULL [java/lang/String java/lang/String I I java/lang/Object] []
    ALOAD 0
    ALOAD 1
    ILOAD 2
    INVOKESTATIC kotlin/text/StringsKt.equals (Ljava/lang/String;Ljava/lang/String;Z)Z
    IRETURN
    MAXSTACK = 3
    MAXLOCALS = 5

  // access flags 0x1A
  private final static nativeLastIndexOf(Ljava/lang/String;Ljava/lang/String;I)I
   L0
    ALOAD 0
    LDC "<this>"
    INVOKESTATIC kotlin/jvm/internal/Intrinsics.checkNotNullParameter (Ljava/lang/Object;Ljava/lang/String;)V
    ALOAD 1
    LDC "str"
    INVOKESTATIC kotlin/jvm/internal/Intrinsics.checkNotNullParameter (Ljava/lang/Object;Ljava/lang/String;)V
   L1
    LINENUMBER 42 L1
    ALOAD 0
    ALOAD 1
    ILOAD 2
    INVOKEVIRTUAL java/lang/String.lastIndexOf (Ljava/lang/String;I)I
    IRETURN
   L2
    LOCALVARIABLE $this$nativeLastIndexOf Ljava/lang/String; L0 L2 0
    LOCALVARIABLE str Ljava/lang/String; L0 L2 1
    LOCALVARIABLE fromIndex I L0 L2 2
    MAXSTACK = 3
    MAXLOCALS = 3

  // access flags 0x1A
  private final static nativeLastIndexOf(Ljava/lang/String;CI)I
   L0
    ALOAD 0
    LDC "<this>"
    INVOKESTATIC kotlin/jvm/internal/Intrinsics.checkNotNullParameter (Ljava/lang/Object;Ljava/lang/String;)V
   L1
    LINENUMBER 36 L1
    ALOAD 0
    ILOAD 1
   L2
    LINENUMBER 36 L2
    ILOAD 2
    INVOKEVIRTUAL java/lang/String.lastIndexOf (II)I
    IRETURN
   L3
    LOCALVARIABLE $this$nativeLastIndexOf Ljava/lang/String; L0 L3 0
    LOCALVARIABLE ch C L0 L3 1
    LOCALVARIABLE fromIndex I L0 L3 2
    MAXSTACK = 3
    MAXLOCALS = 3

  // access flags 0x19
  public final static decapitalize(Ljava/lang/String;)Ljava/lang/String;
  @Lkotlin/Deprecated;(message="Use replaceFirstChar instead.", replaceWith=@Lkotlin/ReplaceWith;(expression="replaceFirstChar { it.lowercase(Locale.getDefault()) }", imports={"java.util.Locale"}))
  @Lkotlin/DeprecatedSinceKotlin;(warningSince="1.5")
   L0
    ALOAD 0
    LDC "<this>"
    INVOKESTATIC kotlin/jvm/internal/Intrinsics.checkNotNullParameter (Ljava/lang/Object;Ljava/lang/String;)V
   L1
    LINENUMBER 773 L1
    ALOAD 0
    CHECKCAST java/lang/CharSequence
    INVOKEINTERFACE java/lang/CharSequence.length ()I (itf)
    IFLE L2
    ICONST_1
    GOTO L3
   L2
   FRAME FULL [java/lang/String] []
    ICONST_0
   L3
    LINENUMBER 773 L3
   FRAME FULL [java/lang/String] [I]
    IFEQ L4
    ALOAD 0
    ICONST_0
    INVOKEVIRTUAL java/lang/String.charAt (I)C
    INVOKESTATIC java/lang/Character.isLowerCase (C)Z
   L5
    LINENUMBER 773 L5
    IFNE L4
    NEW java/lang/StringBuilder
    DUP
    INVOKESPECIAL java/lang/StringBuilder.<init> ()V
    ALOAD 0
    ASTORE 1
    ICONST_0
    ISTORE 2
    ICONST_1
    ISTORE 3
    ALOAD 1
    ILOAD 2
    ILOAD 3
    INVOKEVIRTUAL java/lang/String.substring (II)Ljava/lang/String;
    DUP
    LDC "this as java.lang.String\u2026ing(startIndex, endIndex)"
    INVOKESTATIC kotlin/jvm/internal/Intrinsics.checkNotNullExpressionValue (Ljava/lang/Object;Ljava/lang/String;)V
    ASTORE 1
   L6
    LINENUMBER 773 L6
    ALOAD 1
    LDC "null cannot be cast to non-null type java.lang.String"
    INVOKESTATIC kotlin/jvm/internal/Intrinsics.checkNotNull (Ljava/lang/Object;Ljava/lang/String;)V
    ALOAD 1
    INVOKEVIRTUAL java/lang/String.toLowerCase ()Ljava/lang/String;
    DUP
    LDC "this as java.lang.String).toLowerCase()"
    INVOKESTATIC kotlin/jvm/internal/Intrinsics.checkNotNullExpressionValue (Ljava/lang/Object;Ljava/lang/String;)V
   L7
    LINENUMBER 773 L7
    INVOKEVIRTUAL java/lang/StringBuilder.append (Ljava/lang/String;)Ljava/lang/StringBuilder;
    ALOAD 0
    ASTORE 1
    ICONST_1
    ISTORE 2
    ALOAD 1
    ILOAD 2
    INVOKEVIRTUAL java/lang/String.substring (I)Ljava/lang/String;
    DUP
    LDC "this as java.lang.String).substring(startIndex)"
    INVOKESTATIC kotlin/jvm/internal/Intrinsics.checkNotNullExpressionValue (Ljava/lang/Object;Ljava/lang/String;)V
   L8
    LINENUMBER 773 L8
    INVOKEVIRTUAL java/lang/StringBuilder.append (Ljava/lang/String;)Ljava/lang/StringBuilder;
    INVOKEVIRTUAL java/lang/StringBuilder.toString ()Ljava/lang/String;
    GOTO L9
   L4
   FRAME FULL [java/lang/String] []
    ALOAD 0
   L9
   FRAME FULL [java/lang/String] [java/lang/String]
    ARETURN
   L10
    LOCALVARIABLE $this$decapitalize Ljava/lang/String; L0 L10 0
    MAXSTACK = 4
    MAXLOCALS = 4

  // access flags 0x19
  public final static decapitalize(Ljava/lang/String;Ljava/util/Locale;)Ljava/lang/String;
  @Lkotlin/Deprecated;(message="Use replaceFirstChar instead.", replaceWith=@Lkotlin/ReplaceWith;(expression="replaceFirstChar { it.lowercase(locale) }", imports={}))
  @Lkotlin/DeprecatedSinceKotlin;(warningSince="1.5")
   L0
    ALOAD 0
    LDC "<this>"
    INVOKESTATIC kotlin/jvm/internal/Intrinsics.checkNotNullParameter (Ljava/lang/Object;Ljava/lang/String;)V
    ALOAD 1
    LDC "locale"
    INVOKESTATIC kotlin/jvm/internal/Intrinsics.checkNotNullParameter (Ljava/lang/Object;Ljava/lang/String;)V
   L1
    LINENUMBER 786 L1
    ALOAD 0
    CHECKCAST java/lang/CharSequence
    INVOKEINTERFACE java/lang/CharSequence.length ()I (itf)
    IFLE L2
    ICONST_1
    GOTO L3
   L2
   FRAME FULL [java/lang/String java/util/Locale] []
    ICONST_0
   L3
    LINENUMBER 786 L3
   FRAME FULL [java/lang/String java/util/Locale] [I]
    IFEQ L4
    ALOAD 0
    ICONST_0
    INVOKEVIRTUAL java/lang/String.charAt (I)C
    INVOKESTATIC java/lang/Character.isLowerCase (C)Z
   L5
    LINENUMBER 786 L5
    IFNE L4
    NEW java/lang/StringBuilder
    DUP
    INVOKESPECIAL java/lang/StringBuilder.<init> ()V
    ALOAD 0
    ASTORE 2
    ICONST_0
    ISTORE 3
    ICONST_1
    ISTORE 4
    ALOAD 2
    ILOAD 3
    ILOAD 4
    INVOKEVIRTUAL java/lang/String.substring (II)Ljava/lang/String;
    DUP
    LDC "this as java.lang.String\u2026ing(startIndex, endIndex)"
    INVOKESTATIC kotlin/jvm/internal/Intrinsics.checkNotNullExpressionValue (Ljava/lang/Object;Ljava/lang/String;)V
    ASTORE 2
   L6
    LINENUMBER 786 L6
    ALOAD 2
    LDC "null cannot be cast to non-null type java.lang.String"
    INVOKESTATIC kotlin/jvm/internal/Intrinsics.checkNotNull (Ljava/lang/Object;Ljava/lang/String;)V
    ALOAD 2
    ALOAD 1
    INVOKEVIRTUAL java/lang/String.toLowerCase (Ljava/util/Locale;)Ljava/lang/String;
    DUP
    LDC "this as java.lang.String).toLowerCase(locale)"
    INVOKESTATIC kotlin/jvm/internal/Intrinsics.checkNotNullExpressionValue (Ljava/lang/Object;Ljava/lang/String;)V
   L7
    LINENUMBER 786 L7
    INVOKEVIRTUAL java/lang/StringBuilder.append (Ljava/lang/String;)Ljava/lang/StringBuilder;
    ALOAD 0
    ASTORE 2
    ICONST_1
    ISTORE 3
    ALOAD 2
    ILOAD 3
    INVOKEVIRTUAL java/lang/String.substring (I)Ljava/lang/String;
    DUP
    LDC "this as java.lang.String).substring(startIndex)"
    INVOKESTATIC kotlin/jvm/internal/Intrinsics.checkNotNullExpressionValue (Ljava/lang/Object;Ljava/lang/String;)V
   L8
    LINENUMBER 786 L8
    INVOKEVIRTUAL java/lang/StringBuilder.append (Ljava/lang/String;)Ljava/lang/StringBuilder;
    INVOKEVIRTUAL java/lang/StringBuilder.toString ()Ljava/lang/String;
    GOTO L9
   L4
   FRAME FULL [java/lang/String java/util/Locale] []
    ALOAD 0
   L9
   FRAME FULL [java/lang/String java/util/Locale] [java/lang/String]
    ARETURN
   L10
    LOCALVARIABLE $this$decapitalize Ljava/lang/String; L0 L10 0
    LOCALVARIABLE locale Ljava/util/Locale; L0 L10 1
    MAXSTACK = 4
    MAXLOCALS = 5

  // access flags 0x9A
  private final static varargs formatNullable(Lkotlin/jvm/internal/StringCompanionObject;Ljava/util/Locale;Ljava/lang/String;[Ljava/lang/Object;)Ljava/lang/String;
   L0
    ALOAD 0
    LDC "<this>"
    INVOKESTATIC kotlin/jvm/internal/Intrinsics.checkNotNullParameter (Ljava/lang/Object;Ljava/lang/String;)V
    ALOAD 2
    LDC "format"
    INVOKESTATIC kotlin/jvm/internal/Intrinsics.checkNotNullParameter (Ljava/lang/Object;Ljava/lang/String;)V
    ALOAD 3
    LDC "args"
    INVOKESTATIC kotlin/jvm/internal/Intrinsics.checkNotNullParameter (Ljava/lang/Object;Ljava/lang/String;)V
   L1
    LINENUMBER 379 L1
    ALOAD 1
    ALOAD 2
    ALOAD 3
    ALOAD 3
    ARRAYLENGTH
    INVOKESTATIC java/util/Arrays.copyOf ([Ljava/lang/Object;I)[Ljava/lang/Object;
    INVOKESTATIC java/lang/String.format (Ljava/util/Locale;Ljava/lang/String;[Ljava/lang/Object;)Ljava/lang/String;
    DUP
    LDC "format(locale, format, *args)"
    INVOKESTATIC kotlin/jvm/internal/Intrinsics.checkNotNullExpressionValue (Ljava/lang/Object;Ljava/lang/String;)V
    ARETURN
   L2
    LOCALVARIABLE $this$format Lkotlin/jvm/internal/StringCompanionObject; L0 L2 0
    LOCALVARIABLE locale Ljava/util/Locale; L0 L2 1
    LOCALVARIABLE format Ljava/lang/String; L0 L2 2
    LOCALVARIABLE args [Ljava/lang/Object; L0 L2 3
    MAXSTACK = 4
    MAXLOCALS = 4

  // access flags 0x9A
  private final static varargs formatNullable(Ljava/lang/String;Ljava/util/Locale;[Ljava/lang/Object;)Ljava/lang/String;
   L0
    ALOAD 0
    LDC "<this>"
    INVOKESTATIC kotlin/jvm/internal/Intrinsics.checkNotNullParameter (Ljava/lang/Object;Ljava/lang/String;)V
    ALOAD 2
    LDC "args"
    INVOKESTATIC kotlin/jvm/internal/Intrinsics.checkNotNullParameter (Ljava/lang/Object;Ljava/lang/String;)V
   L1
    LINENUMBER 359 L1
    ALOAD 1
    ALOAD 0
    ALOAD 2
    ALOAD 2
    ARRAYLENGTH
    INVOKESTATIC java/util/Arrays.copyOf ([Ljava/lang/Object;I)[Ljava/lang/Object;
    INVOKESTATIC java/lang/String.format (Ljava/util/Locale;Ljava/lang/String;[Ljava/lang/Object;)Ljava/lang/String;
    DUP
    LDC "format(locale, this, *args)"
    INVOKESTATIC kotlin/jvm/internal/Intrinsics.checkNotNullExpressionValue (Ljava/lang/Object;Ljava/lang/String;)V
    ARETURN
   L2
    LOCALVARIABLE $this$format Ljava/lang/String; L0 L2 0
    LOCALVARIABLE locale Ljava/util/Locale; L0 L2 1
    LOCALVARIABLE args [Ljava/lang/Object; L0 L2 2
    MAXSTACK = 4
    MAXLOCALS = 3

  // access flags 0x19
  public final static decodeToString([BIIZ)Ljava/lang/String;
   L0
    ALOAD 0
    LDC "<this>"
    INVOKESTATIC kotlin/jvm/internal/Intrinsics.checkNotNullParameter (Ljava/lang/Object;Ljava/lang/String;)V
   L1
    LINENUMBER 243 L1
    GETSTATIC kotlin/collections/AbstractList.Companion : Lkotlin/collections/AbstractList$Companion;
    ILOAD 1
    ILOAD 2
    ALOAD 0
    ARRAYLENGTH
    INVOKEVIRTUAL kotlin/collections/AbstractList$Companion.checkBoundsIndexes$kotlin_stdlib (III)V
   L2
    LINENUMBER 245 L2
    ILOAD 3
    IFNE L3
    NEW java/lang/String
    DUP
    ALOAD 0
    ILOAD 1
   L4
    LINENUMBER 246 L4
    ILOAD 2
    ILOAD 1
    ISUB
    GETSTATIC kotlin/text/Charsets.UTF_8 : Ljava/nio/charset/Charset;
    INVOKESPECIAL java/lang/String.<init> ([BIILjava/nio/charset/Charset;)V
   L5
    LINENUMBER 246 L5
    ARETURN
   L3
    LINENUMBER 249 L3
   FRAME FULL [[B I I I] []
    GETSTATIC kotlin/text/Charsets.UTF_8 : Ljava/nio/charset/Charset;
    INVOKEVIRTUAL java/nio/charset/Charset.newDecoder ()Ljava/nio/charset/CharsetDecoder;
   L6
    LINENUMBER 250 L6
    GETSTATIC java/nio/charset/CodingErrorAction.REPORT : Ljava/nio/charset/CodingErrorAction;
    INVOKEVIRTUAL java/nio/charset/CharsetDecoder.onMalformedInput (Ljava/nio/charset/CodingErrorAction;)Ljava/nio/charset/CharsetDecoder;
   L7
    LINENUMBER 251 L7
    GETSTATIC java/nio/charset/CodingErrorAction.REPORT : Ljava/nio/charset/CodingErrorAction;
    INVOKEVIRTUAL java/nio/charset/CharsetDecoder.onUnmappableCharacter (Ljava/nio/charset/CodingErrorAction;)Ljava/nio/charset/CharsetDecoder;
   L8
    LINENUMBER 249 L8
    ASTORE 4
   L9
    LINENUMBER 253 L9
    ALOAD 4
    ALOAD 0
    ILOAD 1
    ILOAD 2
    ILOAD 1
    ISUB
    INVOKESTATIC java/nio/ByteBuffer.wrap ([BII)Ljava/nio/ByteBuffer;
    INVOKEVIRTUAL java/nio/charset/CharsetDecoder.decode (Ljava/nio/ByteBuffer;)Ljava/nio/CharBuffer;
    INVOKEVIRTUAL java/nio/CharBuffer.toString ()Ljava/lang/String;
    DUP
    LDC "decoder.decode(ByteBuffe\u2026- startIndex)).toString()"
    INVOKESTATIC kotlin/jvm/internal/Intrinsics.checkNotNullExpressionValue (Ljava/lang/Object;Ljava/lang/String;)V
    ARETURN
   L10
    LOCALVARIABLE decoder Ljava/nio/charset/CharsetDecoder; L9 L10 4
    LOCALVARIABLE $this$decodeToString [B L0 L10 0
    LOCALVARIABLE startIndex I L0 L10 1
    LOCALVARIABLE endIndex I L0 L10 2
    LOCALVARIABLE throwOnInvalidSequence Z L0 L10 3
    MAXSTACK = 6
    MAXLOCALS = 5

  // access flags 0x19
  public final static decodeToString([B)Ljava/lang/String;
   L0
    ALOAD 0
    LDC "<this>"
    INVOKESTATIC kotlin/jvm/internal/Intrinsics.checkNotNullParameter (Ljava/lang/Object;Ljava/lang/String;)V
   L1
    LINENUMBER 221 L1
    NEW java/lang/String
    DUP
    ALOAD 0
    GETSTATIC kotlin/text/Charsets.UTF_8 : Ljava/nio/charset/Charset;
    INVOKESPECIAL java/lang/String.<init> ([BLjava/nio/charset/Charset;)V
   L2
    LINENUMBER 221 L2
    ARETURN
   L3
    LOCALVARIABLE $this$decodeToString [B L0 L3 0
    MAXSTACK = 4
    MAXLOCALS = 1

  // access flags 0x19
  // signature (Lkotlin/jvm/internal/StringCompanionObject;)Ljava/util/Comparator<Ljava/lang/String;>;
  // declaration: java.util.Comparator<java.lang.String> getCASE_INSENSITIVE_ORDER(kotlin.jvm.internal.StringCompanionObject)
  public final static getCASE_INSENSITIVE_ORDER(Lkotlin/jvm/internal/StringCompanionObject;)Ljava/util/Comparator;
   L0
    ALOAD 0
    LDC "<this>"
    INVOKESTATIC kotlin/jvm/internal/Intrinsics.checkNotNullParameter (Ljava/lang/Object;Ljava/lang/String;)V
   L1
    LINENUMBER 824 L1
    GETSTATIC java/lang/String.CASE_INSENSITIVE_ORDER : Ljava/util/Comparator;
    DUP
    LDC "CASE_INSENSITIVE_ORDER"
    INVOKESTATIC kotlin/jvm/internal/Intrinsics.checkNotNullExpressionValue (Ljava/lang/Object;Ljava/lang/String;)V
    ARETURN
   L2
    LOCALVARIABLE $this$CASE_INSENSITIVE_ORDER Lkotlin/jvm/internal/StringCompanionObject; L0 L2 0
    MAXSTACK = 3
    MAXLOCALS = 1

  // access flags 0x19
  public final static concatToString([CII)Ljava/lang/String;
   L0
    ALOAD 0
    LDC "<this>"
    INVOKESTATIC kotlin/jvm/internal/Intrinsics.checkNotNullParameter (Ljava/lang/Object;Ljava/lang/String;)V
   L1
    LINENUMBER 192 L1
    GETSTATIC kotlin/collections/AbstractList.Companion : Lkotlin/collections/AbstractList$Companion;
    ILOAD 1
    ILOAD 2
    ALOAD 0
    ARRAYLENGTH
    INVOKEVIRTUAL kotlin/collections/AbstractList$Companion.checkBoundsIndexes$kotlin_stdlib (III)V
    NEW java/lang/String
    DUP
    ALOAD 0
    ILOAD 1
   L2
    LINENUMBER 193 L2
    ILOAD 2
    ILOAD 1
    ISUB
    INVOKESPECIAL java/lang/String.<init> ([CII)V
   L3
    LINENUMBER 193 L3
    ARETURN
   L4
    LOCALVARIABLE $this$concatToString [C L0 L4 0
    LOCALVARIABLE startIndex I L0 L4 1
    LOCALVARIABLE endIndex I L0 L4 2
    MAXSTACK = 6
    MAXLOCALS = 3

  // access flags 0x19
  public final static concatToString([C)Ljava/lang/String;
   L0
    ALOAD 0
    LDC "<this>"
    INVOKESTATIC kotlin/jvm/internal/Intrinsics.checkNotNullParameter (Ljava/lang/Object;Ljava/lang/String;)V
   L1
    LINENUMBER 176 L1
    NEW java/lang/String
    DUP
    ALOAD 0
    INVOKESPECIAL java/lang/String.<init> ([C)V
   L2
    LINENUMBER 176 L2
    ARETURN
   L3
    LOCALVARIABLE $this$concatToString [C L0 L3 0
    MAXSTACK = 3
    MAXLOCALS = 1

  // access flags 0x1A
  private final static nativeIndexOf(Ljava/lang/String;CI)I
   L0
    ALOAD 0
    LDC "<this>"
    INVOKESTATIC kotlin/jvm/internal/Intrinsics.checkNotNullParameter (Ljava/lang/Object;Ljava/lang/String;)V
   L1
    LINENUMBER 24 L1
    ALOAD 0
    ILOAD 1
   L2
    LINENUMBER 24 L2
    ILOAD 2
    INVOKEVIRTUAL java/lang/String.indexOf (II)I
    IRETURN
   L3
    LOCALVARIABLE $this$nativeIndexOf Ljava/lang/String; L0 L3 0
    LOCALVARIABLE ch C L0 L3 1
    LOCALVARIABLE fromIndex I L0 L3 2
    MAXSTACK = 3
    MAXLOCALS = 3

  // access flags 0x1A
  private final static nativeIndexOf(Ljava/lang/String;Ljava/lang/String;I)I
   L0
    ALOAD 0
    LDC "<this>"
    INVOKESTATIC kotlin/jvm/internal/Intrinsics.checkNotNullParameter (Ljava/lang/Object;Ljava/lang/String;)V
    ALOAD 1
    LDC "str"
    INVOKESTATIC kotlin/jvm/internal/Intrinsics.checkNotNullParameter (Ljava/lang/Object;Ljava/lang/String;)V
   L1
    LINENUMBER 30 L1
    ALOAD 0
    ALOAD 1
    ILOAD 2
    INVOKEVIRTUAL java/lang/String.indexOf (Ljava/lang/String;I)I
    IRETURN
   L2
    LOCALVARIABLE $this$nativeIndexOf Ljava/lang/String; L0 L2 0
    LOCALVARIABLE str Ljava/lang/String; L0 L2 1
    LOCALVARIABLE fromIndex I L0 L2 2
    MAXSTACK = 3
    MAXLOCALS = 3

  // access flags 0x19
  public final static encodeToByteArray(Ljava/lang/String;)[B
   L0
    ALOAD 0
    LDC "<this>"
    INVOKESTATIC kotlin/jvm/internal/Intrinsics.checkNotNullParameter (Ljava/lang/Object;Ljava/lang/String;)V
   L1
    LINENUMBER 264 L1
    ALOAD 0
    ASTORE 1
    GETSTATIC kotlin/text/Charsets.UTF_8 : Ljava/nio/charset/Charset;
    ALOAD 1
    SWAP
    INVOKEVIRTUAL java/lang/String.getBytes (Ljava/nio/charset/Charset;)[B
    DUP
    LDC "this as java.lang.String).getBytes(charset)"
    INVOKESTATIC kotlin/jvm/internal/Intrinsics.checkNotNullExpressionValue (Ljava/lang/Object;Ljava/lang/String;)V
   L2
    LINENUMBER 264 L2
    ARETURN
   L3
    LOCALVARIABLE $this$encodeToByteArray Ljava/lang/String; L0 L3 0
    MAXSTACK = 3
    MAXLOCALS = 2

  // access flags 0x19
  public final static encodeToByteArray(Ljava/lang/String;IIZ)[B
   L0
    ALOAD 0
    LDC "<this>"
    INVOKESTATIC kotlin/jvm/internal/Intrinsics.checkNotNullParameter (Ljava/lang/Object;Ljava/lang/String;)V
   L1
    LINENUMBER 286 L1
    GETSTATIC kotlin/collections/AbstractList.Companion : Lkotlin/collections/AbstractList$Companion;
    ILOAD 1
    ILOAD 2
    ALOAD 0
    INVOKEVIRTUAL java/lang/String.length ()I
    INVOKEVIRTUAL kotlin/collections/AbstractList$Companion.checkBoundsIndexes$kotlin_stdlib (III)V
   L2
    LINENUMBER 288 L2
    ILOAD 3
    IFNE L3
   L4
    LINENUMBER 289 L4
    ALOAD 0
    ILOAD 1
    ILOAD 2
    INVOKEVIRTUAL java/lang/String.substring (II)Ljava/lang/String;
    DUP
    LDC "this as java.lang.String\u2026ing(startIndex, endIndex)"
    INVOKESTATIC kotlin/jvm/internal/Intrinsics.checkNotNullExpressionValue (Ljava/lang/Object;Ljava/lang/String;)V
    ASTORE 4
   L5
    LINENUMBER 289 L5
    GETSTATIC kotlin/text/Charsets.UTF_8 : Ljava/nio/charset/Charset;
    ASTORE 5
    ALOAD 4
    LDC "null cannot be cast to non-null type java.lang.String"
    INVOKESTATIC kotlin/jvm/internal/Intrinsics.checkNotNull (Ljava/lang/Object;Ljava/lang/String;)V
    ALOAD 4
    ALOAD 5
    INVOKEVIRTUAL java/lang/String.getBytes (Ljava/nio/charset/Charset;)[B
    DUP
    LDC "this as java.lang.String).getBytes(charset)"
    INVOKESTATIC kotlin/jvm/internal/Intrinsics.checkNotNullExpressionValue (Ljava/lang/Object;Ljava/lang/String;)V
   L6
    LINENUMBER 289 L6
    ARETURN
   L3
    LINENUMBER 292 L3
   FRAME FULL [java/lang/String I I I] []
    GETSTATIC kotlin/text/Charsets.UTF_8 : Ljava/nio/charset/Charset;
    INVOKEVIRTUAL java/nio/charset/Charset.newEncoder ()Ljava/nio/charset/CharsetEncoder;
   L7
    LINENUMBER 293 L7
    GETSTATIC java/nio/charset/CodingErrorAction.REPORT : Ljava/nio/charset/CodingErrorAction;
    INVOKEVIRTUAL java/nio/charset/CharsetEncoder.onMalformedInput (Ljava/nio/charset/CodingErrorAction;)Ljava/nio/charset/CharsetEncoder;
   L8
    LINENUMBER 294 L8
    GETSTATIC java/nio/charset/CodingErrorAction.REPORT : Ljava/nio/charset/CodingErrorAction;
    INVOKEVIRTUAL java/nio/charset/CharsetEncoder.onUnmappableCharacter (Ljava/nio/charset/CodingErrorAction;)Ljava/nio/charset/CharsetEncoder;
   L9
    LINENUMBER 292 L9
    ASTORE 4
   L10
    LINENUMBER 296 L10
    ALOAD 4
    ALOAD 0
    CHECKCAST java/lang/CharSequence
    ILOAD 1
    ILOAD 2
    INVOKESTATIC java/nio/CharBuffer.wrap (Ljava/lang/CharSequence;II)Ljava/nio/CharBuffer;
    INVOKEVIRTUAL java/nio/charset/CharsetEncoder.encode (Ljava/nio/CharBuffer;)Ljava/nio/ByteBuffer;
    ASTORE 5
   L11
    LINENUMBER 297 L11
    ALOAD 5
    INVOKEVIRTUAL java/nio/ByteBuffer.hasArray ()Z
    IFEQ L12
    ALOAD 5
    INVOKEVIRTUAL java/nio/ByteBuffer.arrayOffset ()I
    IFNE L12
    ALOAD 5
    INVOKEVIRTUAL java/nio/ByteBuffer.remaining ()I
    ALOAD 5
    INVOKEVIRTUAL java/nio/ByteBuffer.array ()[B
    DUP
    INVOKESTATIC kotlin/jvm/internal/Intrinsics.checkNotNull (Ljava/lang/Object;)V
    ARRAYLENGTH
    IF_ICMPNE L12
   L13
    LINENUMBER 298 L13
    ALOAD 5
    INVOKEVIRTUAL java/nio/ByteBuffer.array ()[B
   L14
    LINENUMBER 297 L14
    DUP
    LDC "{\n        byteBuffer.array()\n    }"
    INVOKESTATIC kotlin/jvm/internal/Intrinsics.checkNotNullExpressionValue (Ljava/lang/Object;Ljava/lang/String;)V
    GOTO L15
   L12
    LINENUMBER 300 L12
   FRAME FULL [java/lang/String I I I java/nio/charset/CharsetEncoder java/nio/ByteBuffer] []
    ALOAD 5
    INVOKEVIRTUAL java/nio/ByteBuffer.remaining ()I
    NEWARRAY T_BYTE
    ASTORE 6
    ALOAD 6
    ASTORE 7
   L16
    LINENUMBER 828 L16
    ICONST_0
    ISTORE 8
   L17
    LINENUMBER 300 L17
    ALOAD 5
    ALOAD 7
    INVOKEVIRTUAL java/nio/ByteBuffer.get ([B)Ljava/nio/ByteBuffer;
    POP
   L18
    LINENUMBER 300 L18
    ALOAD 6
   L15
    LINENUMBER 297 L15
   FRAME FULL [java/lang/String I I I java/nio/charset/CharsetEncoder java/nio/ByteBuffer] [[B]
    ARETURN
   L19
    LOCALVARIABLE $i$a$-also-StringsKt__StringsJVMKt$encodeToByteArray$1 I L17 L18 8
    LOCALVARIABLE it [B L16 L18 7
    LOCALVARIABLE encoder Ljava/nio/charset/CharsetEncoder; L10 L19 4
    LOCALVARIABLE byteBuffer Ljava/nio/ByteBuffer; L11 L19 5
    LOCALVARIABLE $this$encodeToByteArray Ljava/lang/String; L0 L19 0
    LOCALVARIABLE startIndex I L0 L19 1
    LOCALVARIABLE endIndex I L0 L19 2
    LOCALVARIABLE throwOnInvalidSequence Z L0 L19 3
    MAXSTACK = 4
    MAXLOCALS = 9

  // access flags 0x1009
  public static synthetic concatToString$default([CIIILjava/lang/Object;)Ljava/lang/String;
   L0
    LINENUMBER 191 L0
    ILOAD 3
    ICONST_1
    IAND
    IFEQ L1
    ICONST_0
    ISTORE 1
   L1
   FRAME FULL [[C I I I java/lang/Object] []
    ILOAD 3
    ICONST_2
    IAND
    IFEQ L2
    ALOAD 0
    ARRAYLENGTH
    ISTORE 2
   L2
   FRAME FULL [[C I I I java/lang/Object] []
    ALOAD 0
    ILOAD 1
    ILOAD 2
    INVOKESTATIC kotlin/text/StringsKt.concatToString ([CII)Ljava/lang/String;
    ARETURN
    MAXSTACK = 3
    MAXLOCALS = 5

  // access flags 0x1009
  public static synthetic toCharArray$default(Ljava/lang/String;IIILjava/lang/Object;)[C
   L0
    LINENUMBER 208 L0
    ILOAD 3
    ICONST_1
    IAND
    IFEQ L1
    ICONST_0
    ISTORE 1
   L1
   FRAME FULL [java/lang/String I I I java/lang/Object] []
    ILOAD 3
    ICONST_2
    IAND
    IFEQ L2
    ALOAD 0
    INVOKEVIRTUAL java/lang/String.length ()I
    ISTORE 2
   L2
   FRAME FULL [java/lang/String I I I java/lang/Object] []
    ALOAD 0
    ILOAD 1
    ILOAD 2
    INVOKESTATIC kotlin/text/StringsKt.toCharArray (Ljava/lang/String;II)[C
    ARETURN
    MAXSTACK = 3
    MAXLOCALS = 5

  // access flags 0x1008
  static synthetic toCharArray$default(Ljava/lang/String;[CIIIILjava/lang/Object;)[C
   L0
    LINENUMBER 319 L0
    ILOAD 5
    ICONST_2
    IAND
    IFEQ L1
   L2
    LINENUMBER 321 L2
    ICONST_0
    ISTORE 2
   L1
    LINENUMBER 319 L1
   FRAME FULL [java/lang/String [C I I I I java/lang/Object] []
    ILOAD 5
    ICONST_4
    IAND
    IFEQ L3
   L4
    LINENUMBER 322 L4
    ICONST_0
    ISTORE 3
   L3
    LINENUMBER 319 L3
   FRAME FULL [java/lang/String [C I I I I java/lang/Object] []
    ILOAD 5
    BIPUSH 8
    IAND
    IFEQ L5
   L6
    LINENUMBER 323 L6
    ALOAD 0
    INVOKEVIRTUAL java/lang/String.length ()I
    ISTORE 4
   L5
    LINENUMBER 319 L5
   FRAME FULL [java/lang/String [C I I I I java/lang/Object] []
    ALOAD 0
    LDC "<this>"
    INVOKESTATIC kotlin/jvm/internal/Intrinsics.checkNotNullParameter (Ljava/lang/Object;Ljava/lang/String;)V
    ALOAD 1
    LDC "destination"
    INVOKESTATIC kotlin/jvm/internal/Intrinsics.checkNotNullParameter (Ljava/lang/Object;Ljava/lang/String;)V
   L7
    LINENUMBER 325 L7
    ALOAD 0
    ILOAD 3
    ILOAD 4
    ALOAD 1
    ILOAD 2
    INVOKEVIRTUAL java/lang/String.getChars (II[CI)V
   L8
    LINENUMBER 326 L8
    ALOAD 1
    ARETURN
   L9
    LOCALVARIABLE $this$toCharArray_u24default Ljava/lang/String; L0 L9 0
    LOCALVARIABLE destination [C L0 L9 1
    LOCALVARIABLE destinationOffset I L0 L9 2
    LOCALVARIABLE startIndex I L0 L9 3
    LOCALVARIABLE endIndex I L0 L9 4
    MAXSTACK = 5
    MAXLOCALS = 7

  // access flags 0x1009
  public static synthetic decodeToString$default([BIIZILjava/lang/Object;)Ljava/lang/String;
   L0
    LINENUMBER 238 L0
    ILOAD 4
    ICONST_1
    IAND
    IFEQ L1
   L2
    LINENUMBER 239 L2
    ICONST_0
    ISTORE 1
   L1
    LINENUMBER 238 L1
   FRAME FULL [[B I I I I java/lang/Object] []
    ILOAD 4
    ICONST_2
    IAND
    IFEQ L3
   L4
    LINENUMBER 240 L4
    ALOAD 0
    ARRAYLENGTH
    ISTORE 2
   L3
    LINENUMBER 238 L3
   FRAME FULL [[B I I I I java/lang/Object] []
    ILOAD 4
    ICONST_4
    IAND
    IFEQ L5
   L6
    LINENUMBER 241 L6
    ICONST_0
    ISTORE 3
   L5
    LINENUMBER 238 L5
   FRAME FULL [[B I I I I java/lang/Object] []
    ALOAD 0
    ILOAD 1
    ILOAD 2
    ILOAD 3
    INVOKESTATIC kotlin/text/StringsKt.decodeToString ([BIIZ)Ljava/lang/String;
    ARETURN
    MAXSTACK = 4
    MAXLOCALS = 6

  // access flags 0x1009
  public static synthetic encodeToByteArray$default(Ljava/lang/String;IIZILjava/lang/Object;)[B
   L0
    LINENUMBER 281 L0
    ILOAD 4
    ICONST_1
    IAND
    IFEQ L1
   L2
    LINENUMBER 282 L2
    ICONST_0
    ISTORE 1
   L1
    LINENUMBER 281 L1
   FRAME FULL [java/lang/String I I I I java/lang/Object] []
    ILOAD 4
    ICONST_2
    IAND
    IFEQ L3
   L4
    LINENUMBER 283 L4
    ALOAD 0
    INVOKEVIRTUAL java/lang/String.length ()I
    ISTORE 2
   L3
    LINENUMBER 281 L3
   FRAME FULL [java/lang/String I I I I java/lang/Object] []
    ILOAD 4
    ICONST_4
    IAND
    IFEQ L5
   L6
    LINENUMBER 284 L6
    ICONST_0
    ISTORE 3
   L5
    LINENUMBER 281 L5
   FRAME FULL [java/lang/String I I I I java/lang/Object] []
    ALOAD 0
    ILOAD 1
    ILOAD 2
    ILOAD 3
    INVOKESTATIC kotlin/text/StringsKt.encodeToByteArray (Ljava/lang/String;IIZ)[B
    ARETURN
    MAXSTACK = 4
    MAXLOCALS = 6

  // access flags 0x1009
  public static synthetic compareTo$default(Ljava/lang/String;Ljava/lang/String;ZILjava/lang/Object;)I
   L0
    LINENUMBER 550 L0
    ILOAD 3
    ICONST_2
    IAND
    IFEQ L1
    ICONST_0
    ISTORE 2
   L1
   FRAME FULL [java/lang/String java/lang/String I I java/lang/Object] []
    ALOAD 0
    ALOAD 1
    ILOAD 2
    INVOKESTATIC kotlin/text/StringsKt.compareTo (Ljava/lang/String;Ljava/lang/String;Z)I
    IRETURN
    MAXSTACK = 3
    MAXLOCALS = 5

  // access flags 0x1009
  public static synthetic regionMatches$default(Ljava/lang/CharSequence;ILjava/lang/CharSequence;IIZILjava/lang/Object;)Z
   L0
    LINENUMBER 638 L0
    ILOAD 6
    BIPUSH 16
    IAND
    IFEQ L1
    ICONST_0
    ISTORE 5
   L1
   FRAME FULL [java/lang/CharSequence I java/lang/CharSequence I I I I java/lang/Object] []
    ALOAD 0
    ILOAD 1
    ALOAD 2
    ILOAD 3
    ILOAD 4
    ILOAD 5
    INVOKESTATIC kotlin/text/StringsKt.regionMatches (Ljava/lang/CharSequence;ILjava/lang/CharSequence;IIZ)Z
    IRETURN
    MAXSTACK = 6
    MAXLOCALS = 8

  // access flags 0x1009
  public static synthetic regionMatches$default(Ljava/lang/String;ILjava/lang/String;IIZILjava/lang/Object;)Z
   L0
    LINENUMBER 652 L0
    ILOAD 6
    BIPUSH 16
    IAND
    IFEQ L1
    ICONST_0
    ISTORE 5
   L1
   FRAME FULL [java/lang/String I java/lang/String I I I I java/lang/Object] []
    ALOAD 0
    ILOAD 1
    ALOAD 2
    ILOAD 3
    ILOAD 4
    ILOAD 5
    INVOKESTATIC kotlin/text/StringsKt.regionMatches (Ljava/lang/String;ILjava/lang/String;IIZ)Z
    IRETURN
    MAXSTACK = 6
    MAXLOCALS = 8

  // access flags 0x1008
  static synthetic toByteArray$default(Ljava/lang/String;Ljava/nio/charset/Charset;ILjava/lang/Object;)[B
   L0
    LINENUMBER 705 L0
    ILOAD 2
    ICONST_1
    IAND
    IFEQ L1
    GETSTATIC kotlin/text/Charsets.UTF_8 : Ljava/nio/charset/Charset;
    ASTORE 1
   L1
   FRAME FULL [java/lang/String java/nio/charset/Charset I java/lang/Object] []
    ALOAD 0
    LDC "<this>"
    INVOKESTATIC kotlin/jvm/internal/Intrinsics.checkNotNullParameter (Ljava/lang/Object;Ljava/lang/String;)V
    ALOAD 1
    LDC "charset"
    INVOKESTATIC kotlin/jvm/internal/Intrinsics.checkNotNullParameter (Ljava/lang/Object;Ljava/lang/String;)V
   L2
    LINENUMBER 705 L2
    ALOAD 0
    ALOAD 1
    INVOKEVIRTUAL java/lang/String.getBytes (Ljava/nio/charset/Charset;)[B
    DUP
    LDC "this as java.lang.String).getBytes(charset)"
    INVOKESTATIC kotlin/jvm/internal/Intrinsics.checkNotNullExpressionValue (Ljava/lang/Object;Ljava/lang/String;)V
    ARETURN
   L3
    LOCALVARIABLE $this$toByteArray_u24default Ljava/lang/String; L0 L3 0
    LOCALVARIABLE charset Ljava/nio/charset/Charset; L0 L3 1
    MAXSTACK = 3
    MAXLOCALS = 4

  // access flags 0x1008
  static synthetic toPattern$default(Ljava/lang/String;IILjava/lang/Object;)Ljava/util/regex/Pattern;
   L0
    LINENUMBER 713 L0
    ILOAD 2
    ICONST_1
    IAND
    IFEQ L1
    ICONST_0
    ISTORE 1
   L1
   FRAME FULL [java/lang/String I I java/lang/Object] []
    ALOAD 0
    LDC "<this>"
    INVOKESTATIC kotlin/jvm/internal/Intrinsics.checkNotNullParameter (Ljava/lang/Object;Ljava/lang/String;)V
   L2
    LINENUMBER 714 L2
    ALOAD 0
    ILOAD 1
    INVOKESTATIC java/util/regex/Pattern.compile (Ljava/lang/String;I)Ljava/util/regex/Pattern;
    DUP
    LDC "compile(this, flags)"
    INVOKESTATIC kotlin/jvm/internal/Intrinsics.checkNotNullExpressionValue (Ljava/lang/Object;Ljava/lang/String;)V
    ARETURN
   L3
    LOCALVARIABLE $this$toPattern_u24default Ljava/lang/String; L0 L3 0
    LOCALVARIABLE flags I L0 L3 1
    MAXSTACK = 3
    MAXLOCALS = 4

  // access flags 0x19
  public final static capitalize(Ljava/lang/String;)Ljava/lang/String;
  @Lkotlin/Deprecated;(message="Use replaceFirstChar instead.", replaceWith=@Lkotlin/ReplaceWith;(expression="replaceFirstChar { if (it.isLowerCase()) it.titlecase(Locale.getDefault()) else it.toString() }", imports={"java.util.Locale"}))
  @Lkotlin/DeprecatedSinceKotlin;(warningSince="1.5")
   L0
    ALOAD 0
    LDC "<this>"
    INVOKESTATIC kotlin/jvm/internal/Intrinsics.checkNotNullParameter (Ljava/lang/Object;Ljava/lang/String;)V
   L1
    LINENUMBER 730 L1
    ALOAD 0
    INVOKESTATIC java/util/Locale.getDefault ()Ljava/util/Locale;
    DUP
    LDC "getDefault()"
    INVOKESTATIC kotlin/jvm/internal/Intrinsics.checkNotNullExpressionValue (Ljava/lang/Object;Ljava/lang/String;)V
    INVOKESTATIC kotlin/text/StringsKt.capitalize (Ljava/lang/String;Ljava/util/Locale;)Ljava/lang/String;
    ARETURN
   L2
    LOCALVARIABLE $this$capitalize Ljava/lang/String; L0 L2 0
    MAXSTACK = 4
    MAXLOCALS = 1

  // access flags 0x19
  public final static capitalize(Ljava/lang/String;Ljava/util/Locale;)Ljava/lang/String;
  @Lkotlin/Deprecated;(message="Use replaceFirstChar instead.", replaceWith=@Lkotlin/ReplaceWith;(expression="replaceFirstChar { if (it.isLowerCase()) it.titlecase(locale) else it.toString() }", imports={}))
  @Lkotlin/DeprecatedSinceKotlin;(warningSince="1.5")
   L0
    ALOAD 0
    LDC "<this>"
    INVOKESTATIC kotlin/jvm/internal/Intrinsics.checkNotNullParameter (Ljava/lang/Object;Ljava/lang/String;)V
    ALOAD 1
    LDC "locale"
    INVOKESTATIC kotlin/jvm/internal/Intrinsics.checkNotNullParameter (Ljava/lang/Object;Ljava/lang/String;)V
   L1
    LINENUMBER 746 L1
    ALOAD 0
    CHECKCAST java/lang/CharSequence
    INVOKEINTERFACE java/lang/CharSequence.length ()I (itf)
    IFLE L2
    ICONST_1
    GOTO L3
   L2
   FRAME FULL [java/lang/String java/util/Locale] []
    ICONST_0
   L3
    LINENUMBER 746 L3
   FRAME FULL [java/lang/String java/util/Locale] [I]
    IFEQ L4
   L5
    LINENUMBER 747 L5
    ALOAD 0
    ICONST_0
    INVOKEVIRTUAL java/lang/String.charAt (I)C
    ISTORE 2
   L6
    LINENUMBER 748 L6
    ILOAD 2
    INVOKESTATIC java/lang/Character.isLowerCase (C)Z
   L7
    LINENUMBER 748 L7
    IFEQ L4
   L8
    LINENUMBER 749 L8
    NEW java/lang/StringBuilder
    DUP
    INVOKESPECIAL java/lang/StringBuilder.<init> ()V
    ASTORE 3
    ALOAD 3
    ASTORE 4
   L9
    ICONST_0
    ISTORE 5
   L10
    LINENUMBER 750 L10
    ILOAD 2
    INVOKESTATIC java/lang/Character.toTitleCase (C)C
   L11
    LINENUMBER 750 L11
    ISTORE 6
   L12
    LINENUMBER 751 L12
    ILOAD 6
    ILOAD 2
    INVOKESTATIC java/lang/Character.toUpperCase (C)C
   L13
    LINENUMBER 751 L13
    IF_ICMPEQ L14
   L15
    LINENUMBER 752 L15
    ALOAD 4
    ILOAD 6
    INVOKEVIRTUAL java/lang/StringBuilder.append (C)Ljava/lang/StringBuilder;
    POP
    GOTO L16
   L14
    LINENUMBER 754 L14
   FRAME FULL [java/lang/String java/util/Locale I java/lang/StringBuilder java/lang/StringBuilder I I] []
    ALOAD 4
    ALOAD 0
    ASTORE 7
    ICONST_0
    ISTORE 8
    ICONST_1
    ISTORE 9
    ALOAD 7
    ILOAD 8
    ILOAD 9
    INVOKEVIRTUAL java/lang/String.substring (II)Ljava/lang/String;
    DUP
    LDC "this as java.lang.String\u2026ing(startIndex, endIndex)"
    INVOKESTATIC kotlin/jvm/internal/Intrinsics.checkNotNullExpressionValue (Ljava/lang/Object;Ljava/lang/String;)V
    ASTORE 7
   L17
    LINENUMBER 754 L17
    ALOAD 7
    LDC "null cannot be cast to non-null type java.lang.String"
    INVOKESTATIC kotlin/jvm/internal/Intrinsics.checkNotNull (Ljava/lang/Object;Ljava/lang/String;)V
    ALOAD 7
    ALOAD 1
    INVOKEVIRTUAL java/lang/String.toUpperCase (Ljava/util/Locale;)Ljava/lang/String;
    DUP
    LDC "this as java.lang.String).toUpperCase(locale)"
    INVOKESTATIC kotlin/jvm/internal/Intrinsics.checkNotNullExpressionValue (Ljava/lang/Object;Ljava/lang/String;)V
   L18
    LINENUMBER 754 L18
    INVOKEVIRTUAL java/lang/StringBuilder.append (Ljava/lang/String;)Ljava/lang/StringBuilder;
    POP
   L16
    LINENUMBER 756 L16
   FRAME FULL [java/lang/String java/util/Locale I java/lang/StringBuilder java/lang/StringBuilder I I] []
    ALOAD 4
    ALOAD 0
    ASTORE 7
    ICONST_1
    ISTORE 8
    ALOAD 7
    ILOAD 8
    INVOKEVIRTUAL java/lang/String.substring (I)Ljava/lang/String;
    DUP
    LDC "this as java.lang.String).substring(startIndex)"
    INVOKESTATIC kotlin/jvm/internal/Intrinsics.checkNotNullExpressionValue (Ljava/lang/Object;Ljava/lang/String;)V
   L19
    LINENUMBER 756 L19
    INVOKEVIRTUAL java/lang/StringBuilder.append (Ljava/lang/String;)Ljava/lang/StringBuilder;
    POP
   L20
    LINENUMBER 757 L20
    NOP
   L21
    LINENUMBER 749 L21
    ALOAD 3
    INVOKEVIRTUAL java/lang/StringBuilder.toString ()Ljava/lang/String;
    DUP
    LDC "StringBuilder().apply(builderAction).toString()"
    INVOKESTATIC kotlin/jvm/internal/Intrinsics.checkNotNullExpressionValue (Ljava/lang/Object;Ljava/lang/String;)V
   L22
    LINENUMBER 749 L22
    ARETURN
   L4
    LINENUMBER 760 L4
   FRAME FULL [java/lang/String java/util/Locale] []
    ALOAD 0
    ARETURN
   L23
    LOCALVARIABLE $i$a$-buildString-StringsKt__StringsJVMKt$capitalize$1 I L10 L21 5
    LOCALVARIABLE titleChar C L12 L21 6
    LOCALVARIABLE $this$capitalize_u24lambda_u2d5 Ljava/lang/StringBuilder; L9 L21 4
    LOCALVARIABLE firstChar C L6 L4 2
    LOCALVARIABLE $this$capitalize Ljava/lang/String; L0 L23 0
    LOCALVARIABLE locale Ljava/util/Locale; L0 L23 1
    MAXSTACK = 4
    MAXLOCALS = 10

  // access flags 0x1
  public <init>()V
   L0
    ALOAD 0
    INVOKESPECIAL kotlin/text/StringsKt__StringNumberConversionsKt.<init> ()V
    RETURN
   L1
    LOCALVARIABLE this Lkotlin/text/StringsKt__StringsJVMKt; L0 L1 0
    MAXSTACK = 1
    MAXLOCALS = 1

  // access flags 0x19
  public final static equals(Ljava/lang/String;Ljava/lang/String;Z)Z
   L0
    LINENUMBER 54 L0
    ALOAD 0
    IFNONNULL L1
   L2
    LINENUMBER 55 L2
    ALOAD 1
    IFNONNULL L3
    ICONST_1
    GOTO L4
   L3
   FRAME FULL [java/lang/String java/lang/String I] []
    ICONST_0
   L4
   FRAME FULL [java/lang/String java/lang/String I] [I]
    IRETURN
   L1
    LINENUMBER 56 L1
   FRAME FULL [java/lang/String java/lang/String I] []
    ILOAD 2
    IFNE L5
   L6
    LINENUMBER 57 L6
    ALOAD 0
    ALOAD 1
    INVOKEVIRTUAL java/lang/String.equals (Ljava/lang/Object;)Z
    GOTO L7
   L5
    LINENUMBER 59 L5
   FRAME FULL [java/lang/String java/lang/String I] []
    ALOAD 0
    ALOAD 1
    INVOKEVIRTUAL java/lang/String.equalsIgnoreCase (Ljava/lang/String;)Z
   L7
    LINENUMBER 56 L7
   FRAME FULL [java/lang/String java/lang/String I] [I]
    IRETURN
   L8
    LOCALVARIABLE $this$equals Ljava/lang/String; L0 L8 0
    LOCALVARIABLE other Ljava/lang/String; L0 L8 1
    LOCALVARIABLE ignoreCase Z L0 L8 2
    MAXSTACK = 2
    MAXLOCALS = 3

  // access flags 0x19
  public final static compareTo(Ljava/lang/String;Ljava/lang/String;Z)I
   L0
    ALOAD 0
    LDC "<this>"
    INVOKESTATIC kotlin/jvm/internal/Intrinsics.checkNotNullParameter (Ljava/lang/Object;Ljava/lang/String;)V
    ALOAD 1
    LDC "other"
    INVOKESTATIC kotlin/jvm/internal/Intrinsics.checkNotNullParameter (Ljava/lang/Object;Ljava/lang/String;)V
   L1
    LINENUMBER 551 L1
    ILOAD 2
    IFEQ L2
   L3
    LINENUMBER 552 L3
    ALOAD 0
    ALOAD 1
    INVOKEVIRTUAL java/lang/String.compareToIgnoreCase (Ljava/lang/String;)I
    IRETURN
   L2
    LINENUMBER 554 L2
   FRAME FULL [java/lang/String java/lang/String I] []
    ALOAD 0
    ALOAD 1
    INVOKEVIRTUAL java/lang/String.compareTo (Ljava/lang/String;)I
    IRETURN
   L4
    LOCALVARIABLE $this$compareTo Ljava/lang/String; L0 L4 0
    LOCALVARIABLE other Ljava/lang/String; L0 L4 1
    LOCALVARIABLE ignoreCase Z L0 L4 2
    MAXSTACK = 2
    MAXLOCALS = 3

  // access flags 0x1A
  private final static codePointAt(Ljava/lang/String;I)I
   L0
    ALOAD 0
    LDC "<this>"
    INVOKESTATIC kotlin/jvm/internal/Intrinsics.checkNotNullParameter (Ljava/lang/Object;Ljava/lang/String;)V
   L1
    LINENUMBER 529 L1
    ALOAD 0
    ILOAD 1
    INVOKEVIRTUAL java/lang/String.codePointAt (I)I
    IRETURN
   L2
    LOCALVARIABLE $this$codePointAt Ljava/lang/String; L0 L2 0
    LOCALVARIABLE index I L0 L2 1
    MAXSTACK = 2
    MAXLOCALS = 2

  // access flags 0x1A
  private final static codePointBefore(Ljava/lang/String;I)I
   L0
    ALOAD 0
    LDC "<this>"
    INVOKESTATIC kotlin/jvm/internal/Intrinsics.checkNotNullParameter (Ljava/lang/Object;Ljava/lang/String;)V
   L1
    LINENUMBER 535 L1
    ALOAD 0
    ILOAD 1
    INVOKEVIRTUAL java/lang/String.codePointBefore (I)I
    IRETURN
   L2
    LOCALVARIABLE $this$codePointBefore Ljava/lang/String; L0 L2 0
    LOCALVARIABLE index I L0 L2 1
    MAXSTACK = 2
    MAXLOCALS = 2

  // access flags 0x1A
  private final static codePointCount(Ljava/lang/String;II)I
   L0
    ALOAD 0
    LDC "<this>"
    INVOKESTATIC kotlin/jvm/internal/Intrinsics.checkNotNullParameter (Ljava/lang/Object;Ljava/lang/String;)V
   L1
    LINENUMBER 542 L1
    ALOAD 0
    ILOAD 1
    ILOAD 2
    INVOKEVIRTUAL java/lang/String.codePointCount (II)I
    IRETURN
   L2
    LOCALVARIABLE $this$codePointCount Ljava/lang/String; L0 L2 0
    LOCALVARIABLE beginIndex I L0 L2 1
    LOCALVARIABLE endIndex I L0 L2 2
    MAXSTACK = 3
    MAXLOCALS = 3

  // access flags 0x1A
  private final static offsetByCodePoints(Ljava/lang/String;II)I
   L0
    ALOAD 0
    LDC "<this>"
    INVOKESTATIC kotlin/jvm/internal/Intrinsics.checkNotNullParameter (Ljava/lang/Object;Ljava/lang/String;)V
   L1
    LINENUMBER 628 L1
    ALOAD 0
    ILOAD 1
    ILOAD 2
    INVOKEVIRTUAL java/lang/String.offsetByCodePoints (II)I
    IRETURN
   L2
    LOCALVARIABLE $this$offsetByCodePoints Ljava/lang/String; L0 L2 0
    LOCALVARIABLE index I L0 L2 1
    LOCALVARIABLE codePointOffset I L0 L2 2
    MAXSTACK = 3
    MAXLOCALS = 3

  // access flags 0x1A
  private final static contentEquals(Ljava/lang/String;Ljava/lang/CharSequence;)Z
   L0
    ALOAD 0
    LDC "<this>"
    INVOKESTATIC kotlin/jvm/internal/Intrinsics.checkNotNullParameter (Ljava/lang/Object;Ljava/lang/String;)V
    ALOAD 1
    LDC "charSequence"
    INVOKESTATIC kotlin/jvm/internal/Intrinsics.checkNotNullParameter (Ljava/lang/Object;Ljava/lang/String;)V
   L1
    LINENUMBER 564 L1
    ALOAD 0
    ALOAD 1
    INVOKEVIRTUAL java/lang/String.contentEquals (Ljava/lang/CharSequence;)Z
    IRETURN
   L2
    LOCALVARIABLE $this$contentEquals Ljava/lang/String; L0 L2 0
    LOCALVARIABLE charSequence Ljava/lang/CharSequence; L0 L2 1
    MAXSTACK = 2
    MAXLOCALS = 2

  // access flags 0x19
  public final static contentEquals(Ljava/lang/CharSequence;Ljava/lang/CharSequence;)Z
   L0
    LINENUMBER 586 L0
    ALOAD 0
    INSTANCEOF java/lang/String
    IFEQ L1
    ALOAD 1
    IFNULL L1
   L2
    LINENUMBER 587 L2
    ALOAD 0
    CHECKCAST java/lang/String
    ALOAD 1
    INVOKEVIRTUAL java/lang/String.contentEquals (Ljava/lang/CharSequence;)Z
    GOTO L3
   L1
    LINENUMBER 589 L1
   FRAME FULL [java/lang/CharSequence java/lang/CharSequence] []
    ALOAD 0
    ALOAD 1
    INVOKESTATIC kotlin/text/StringsKt.contentEqualsImpl (Ljava/lang/CharSequence;Ljava/lang/CharSequence;)Z
   L3
    LINENUMBER 586 L3
   FRAME FULL [java/lang/CharSequence java/lang/CharSequence] [I]
    IRETURN
   L4
    LOCALVARIABLE $this$contentEquals Ljava/lang/CharSequence; L0 L4 0
    LOCALVARIABLE other Ljava/lang/CharSequence; L0 L4 1
    MAXSTACK = 2
    MAXLOCALS = 2

  // access flags 0x1A
  private final static contentEquals(Ljava/lang/String;Ljava/lang/StringBuffer;)Z
   L0
    ALOAD 0
    LDC "<this>"
    INVOKESTATIC kotlin/jvm/internal/Intrinsics.checkNotNullParameter (Ljava/lang/Object;Ljava/lang/String;)V
    ALOAD 1
    LDC "stringBuilder"
    INVOKESTATIC kotlin/jvm/internal/Intrinsics.checkNotNullParameter (Ljava/lang/Object;Ljava/lang/String;)V
   L1
    LINENUMBER 573 L1
    ALOAD 0
    ALOAD 1
    INVOKEVIRTUAL java/lang/String.contentEquals (Ljava/lang/StringBuffer;)Z
    IRETURN
   L2
    LOCALVARIABLE $this$contentEquals Ljava/lang/String; L0 L2 0
    LOCALVARIABLE stringBuilder Ljava/lang/StringBuffer; L0 L2 1
    MAXSTACK = 2
    MAXLOCALS = 2

  // access flags 0x19
  public final static contentEquals(Ljava/lang/CharSequence;Ljava/lang/CharSequence;Z)Z
   L0
    LINENUMBER 604 L0
    ILOAD 2
    IFEQ L1
   L2
    LINENUMBER 605 L2
    ALOAD 0
    ALOAD 1
    INVOKESTATIC kotlin/text/StringsKt.contentEqualsIgnoreCaseImpl (Ljava/lang/CharSequence;Ljava/lang/CharSequence;)Z
    GOTO L3
   L1
    LINENUMBER 607 L1
   FRAME FULL [java/lang/CharSequence java/lang/CharSequence I] []
    ALOAD 0
    ALOAD 1
    INVOKESTATIC kotlin/text/StringsKt.contentEquals (Ljava/lang/CharSequence;Ljava/lang/CharSequence;)Z
   L3
    LINENUMBER 604 L3
   FRAME FULL [java/lang/CharSequence java/lang/CharSequence I] [I]
    IRETURN
   L4
    LOCALVARIABLE $this$contentEquals Ljava/lang/CharSequence; L0 L4 0
    LOCALVARIABLE other Ljava/lang/CharSequence; L0 L4 1
    LOCALVARIABLE ignoreCase Z L0 L4 2
    MAXSTACK = 2
    MAXLOCALS = 3

  // access flags 0x19
  public final static regionMatches(Ljava/lang/String;ILjava/lang/String;IIZ)Z
   L0
    ALOAD 0
    LDC "<this>"
    INVOKESTATIC kotlin/jvm/internal/Intrinsics.checkNotNullParameter (Ljava/lang/Object;Ljava/lang/String;)V
    ALOAD 2
    LDC "other"
    INVOKESTATIC kotlin/jvm/internal/Intrinsics.checkNotNullParameter (Ljava/lang/Object;Ljava/lang/String;)V
   L1
    LINENUMBER 653 L1
    ILOAD 5
    IFNE L2
   L3
    LINENUMBER 654 L3
    ALOAD 0
    ILOAD 1
    ALOAD 2
    ILOAD 3
    ILOAD 4
    INVOKEVIRTUAL java/lang/String.regionMatches (ILjava/lang/String;II)Z
    GOTO L4
   L2
    LINENUMBER 656 L2
   FRAME FULL [java/lang/String I java/lang/String I I I] []
    ALOAD 0
    ILOAD 5
    ILOAD 1
    ALOAD 2
    ILOAD 3
    ILOAD 4
    INVOKEVIRTUAL java/lang/String.regionMatches (ZILjava/lang/String;II)Z
   L4
   FRAME FULL [java/lang/String I java/lang/String I I I] [I]
    IRETURN
   L5
    LOCALVARIABLE $this$regionMatches Ljava/lang/String; L0 L5 0
    LOCALVARIABLE thisOffset I L0 L5 1
    LOCALVARIABLE other Ljava/lang/String; L0 L5 2
    LOCALVARIABLE otherOffset I L0 L5 3
    LOCALVARIABLE length I L0 L5 4
    LOCALVARIABLE ignoreCase Z L0 L5 5
    MAXSTACK = 6
    MAXLOCALS = 6

  // access flags 0x19
  public final static regionMatches(Ljava/lang/CharSequence;ILjava/lang/CharSequence;IIZ)Z
   L0
    ALOAD 0
    LDC "<this>"
    INVOKESTATIC kotlin/jvm/internal/Intrinsics.checkNotNullParameter (Ljava/lang/Object;Ljava/lang/String;)V
    ALOAD 2
    LDC "other"
    INVOKESTATIC kotlin/jvm/internal/Intrinsics.checkNotNullParameter (Ljava/lang/Object;Ljava/lang/String;)V
   L1
    LINENUMBER 639 L1
    ALOAD 0
    INSTANCEOF java/lang/String
    IFEQ L2
    ALOAD 2
    INSTANCEOF java/lang/String
    IFEQ L2
   L3
    LINENUMBER 640 L3
    ALOAD 0
    CHECKCAST java/lang/String
    ILOAD 1
    ALOAD 2
    CHECKCAST java/lang/String
    ILOAD 3
    ILOAD 4
    ILOAD 5
    INVOKESTATIC kotlin/text/StringsKt.regionMatches (Ljava/lang/String;ILjava/lang/String;IIZ)Z
    IRETURN
   L2
    LINENUMBER 642 L2
   FRAME FULL [java/lang/CharSequence I java/lang/CharSequence I I I] []
    ALOAD 0
    ILOAD 1
    ALOAD 2
    ILOAD 3
    ILOAD 4
    ILOAD 5
    INVOKESTATIC kotlin/text/StringsKt.regionMatchesImpl (Ljava/lang/CharSequence;ILjava/lang/CharSequence;IIZ)Z
    IRETURN
   L4
    LOCALVARIABLE $this$regionMatches Ljava/lang/CharSequence; L0 L4 0
    LOCALVARIABLE thisOffset I L0 L4 1
    LOCALVARIABLE other Ljava/lang/CharSequence; L0 L4 2
    LOCALVARIABLE otherOffset I L0 L4 3
    LOCALVARIABLE length I L0 L4 4
    LOCALVARIABLE ignoreCase Z L0 L4 5
    MAXSTACK = 6
    MAXLOCALS = 6

  // access flags 0x19
  public final static startsWith(Ljava/lang/String;Ljava/lang/String;IZ)Z
   L0
    ALOAD 0
    LDC "<this>"
    INVOKESTATIC kotlin/jvm/internal/Intrinsics.checkNotNullParameter (Ljava/lang/Object;Ljava/lang/String;)V
    ALOAD 1
    LDC "prefix"
    INVOKESTATIC kotlin/jvm/internal/Intrinsics.checkNotNullParameter (Ljava/lang/Object;Ljava/lang/String;)V
   L1
    LINENUMBER 428 L1
    ILOAD 3
    IFNE L2
   L3
    LINENUMBER 429 L3
    ALOAD 0
    ALOAD 1
    ILOAD 2
    INVOKEVIRTUAL java/lang/String.startsWith (Ljava/lang/String;I)Z
    IRETURN
   L2
    LINENUMBER 431 L2
   FRAME FULL [java/lang/String java/lang/String I I] []
    ALOAD 0
    ILOAD 2
    ALOAD 1
    ICONST_0
    ALOAD 1
    INVOKEVIRTUAL java/lang/String.length ()I
    ILOAD 3
    INVOKESTATIC kotlin/text/StringsKt.regionMatches (Ljava/lang/String;ILjava/lang/String;IIZ)Z
    IRETURN
   L4
    LOCALVARIABLE $this$startsWith Ljava/lang/String; L0 L4 0
    LOCALVARIABLE prefix Ljava/lang/String; L0 L4 1
    LOCALVARIABLE startIndex I L0 L4 2
    LOCALVARIABLE ignoreCase Z L0 L4 3
    MAXSTACK = 6
    MAXLOCALS = 4

  // access flags 0x19
  public final static startsWith(Ljava/lang/String;Ljava/lang/String;Z)Z
   L0
    ALOAD 0
    LDC "<this>"
    INVOKESTATIC kotlin/jvm/internal/Intrinsics.checkNotNullParameter (Ljava/lang/Object;Ljava/lang/String;)V
    ALOAD 1
    LDC "prefix"
    INVOKESTATIC kotlin/jvm/internal/Intrinsics.checkNotNullParameter (Ljava/lang/Object;Ljava/lang/String;)V
   L1
    LINENUMBER 417 L1
    ILOAD 2
    IFNE L2
   L3
    LINENUMBER 418 L3
    ALOAD 0
    ALOAD 1
    INVOKEVIRTUAL java/lang/String.startsWith (Ljava/lang/String;)Z
    IRETURN
   L2
    LINENUMBER 420 L2
   FRAME FULL [java/lang/String java/lang/String I] []
    ALOAD 0
    ICONST_0
    ALOAD 1
    ICONST_0
    ALOAD 1
    INVOKEVIRTUAL java/lang/String.length ()I
    ILOAD 2
    INVOKESTATIC kotlin/text/StringsKt.regionMatches (Ljava/lang/String;ILjava/lang/String;IIZ)Z
    IRETURN
   L4
    LOCALVARIABLE $this$startsWith Ljava/lang/String; L0 L4 0
    LOCALVARIABLE prefix Ljava/lang/String; L0 L4 1
    LOCALVARIABLE ignoreCase Z L0 L4 2
    MAXSTACK = 6
    MAXLOCALS = 3

  // access flags 0x19
  public final static endsWith(Ljava/lang/String;Ljava/lang/String;Z)Z
   L0
    ALOAD 0
    LDC "<this>"
    INVOKESTATIC kotlin/jvm/internal/Intrinsics.checkNotNullParameter (Ljava/lang/Object;Ljava/lang/String;)V
    ALOAD 1
    LDC "suffix"
    INVOKESTATIC kotlin/jvm/internal/Intrinsics.checkNotNullParameter (Ljava/lang/Object;Ljava/lang/String;)V
   L1
    LINENUMBER 439 L1
    ILOAD 2
    IFNE L2
   L3
    LINENUMBER 440 L3
    ALOAD 0
    ALOAD 1
    INVOKEVIRTUAL java/lang/String.endsWith (Ljava/lang/String;)Z
    IRETURN
   L2
    LINENUMBER 442 L2
   FRAME FULL [java/lang/String java/lang/String I] []
    ALOAD 0
    ALOAD 0
    INVOKEVIRTUAL java/lang/String.length ()I
    ALOAD 1
    INVOKEVIRTUAL java/lang/String.length ()I
    ISUB
    ALOAD 1
    ICONST_0
    ALOAD 1
    INVOKEVIRTUAL java/lang/String.length ()I
    ICONST_1
    INVOKESTATIC kotlin/text/StringsKt.regionMatches (Ljava/lang/String;ILjava/lang/String;IIZ)Z
    IRETURN
   L4
    LOCALVARIABLE $this$endsWith Ljava/lang/String; L0 L4 0
    LOCALVARIABLE suffix Ljava/lang/String; L0 L4 1
    LOCALVARIABLE ignoreCase Z L0 L4 2
    MAXSTACK = 6
    MAXLOCALS = 3

  // access flags 0x1A
  private final static substring(Ljava/lang/String;I)Ljava/lang/String;
   L0
    ALOAD 0
    LDC "<this>"
    INVOKESTATIC kotlin/jvm/internal/Intrinsics.checkNotNullParameter (Ljava/lang/Object;Ljava/lang/String;)V
   L1
    LINENUMBER 401 L1
    ALOAD 0
    ILOAD 1
    INVOKEVIRTUAL java/lang/String.substring (I)Ljava/lang/String;
    DUP
    LDC "this as java.lang.String).substring(startIndex)"
    INVOKESTATIC kotlin/jvm/internal/Intrinsics.checkNotNullExpressionValue (Ljava/lang/Object;Ljava/lang/String;)V
    ARETURN
   L2
    LOCALVARIABLE $this$substring Ljava/lang/String; L0 L2 0
    LOCALVARIABLE startIndex I L0 L2 1
    MAXSTACK = 3
    MAXLOCALS = 2

  // access flags 0x1A
  private final static substring(Ljava/lang/String;II)Ljava/lang/String;
   L0
    ALOAD 0
    LDC "<this>"
    INVOKESTATIC kotlin/jvm/internal/Intrinsics.checkNotNullParameter (Ljava/lang/Object;Ljava/lang/String;)V
   L1
    LINENUMBER 410 L1
    ALOAD 0
    ILOAD 1
    ILOAD 2
    INVOKEVIRTUAL java/lang/String.substring (II)Ljava/lang/String;
    DUP
    LDC "this as java.lang.String\u2026ing(startIndex, endIndex)"
    INVOKESTATIC kotlin/jvm/internal/Intrinsics.checkNotNullExpressionValue (Ljava/lang/Object;Ljava/lang/String;)V
    ARETURN
   L2
    LOCALVARIABLE $this$substring Ljava/lang/String; L0 L2 0
    LOCALVARIABLE startIndex I L0 L2 1
    LOCALVARIABLE endIndex I L0 L2 2
    MAXSTACK = 3
    MAXLOCALS = 3

  // access flags 0x19
  public final static replace(Ljava/lang/String;Ljava/lang/String;Ljava/lang/String;Z)Ljava/lang/String;
   L0
    ALOAD 0
    LDC "<this>"
    INVOKESTATIC kotlin/jvm/internal/Intrinsics.checkNotNullParameter (Ljava/lang/Object;Ljava/lang/String;)V
    ALOAD 1
    LDC "oldValue"
    INVOKESTATIC kotlin/jvm/internal/Intrinsics.checkNotNullParameter (Ljava/lang/Object;Ljava/lang/String;)V
    ALOAD 2
    LDC "newValue"
    INVOKESTATIC kotlin/jvm/internal/Intrinsics.checkNotNullParameter (Ljava/lang/Object;Ljava/lang/String;)V
   L1
    LINENUMBER 87 L1
    ALOAD 0
    ASTORE 4
    ALOAD 4
    ASTORE 5
   L2
    ICONST_0
    ISTORE 6
   L3
    LINENUMBER 88 L3
    ALOAD 5
    CHECKCAST java/lang/CharSequence
    ALOAD 1
    ICONST_0
    ILOAD 3
    INVOKESTATIC kotlin/text/StringsKt.indexOf (Ljava/lang/CharSequence;Ljava/lang/String;IZ)I
    ISTORE 7
   L4
    LINENUMBER 90 L4
    ILOAD 7
    IFGE L5
    ALOAD 5
    ARETURN
   L5
    LINENUMBER 92 L5
   FRAME FULL [java/lang/String java/lang/String java/lang/String I java/lang/String java/lang/String I I] []
    ALOAD 1
    INVOKEVIRTUAL java/lang/String.length ()I
    ISTORE 8
   L6
    LINENUMBER 93 L6
    ILOAD 8
    ICONST_1
    INVOKESTATIC kotlin/ranges/RangesKt.coerceAtLeast (II)I
    ISTORE 9
   L7
    LINENUMBER 94 L7
    ALOAD 5
    INVOKEVIRTUAL java/lang/String.length ()I
    ILOAD 8
    ISUB
    ALOAD 2
    INVOKEVIRTUAL java/lang/String.length ()I
    IADD
    ISTORE 10
   L8
    LINENUMBER 95 L8
    ILOAD 10
    IFGE L9
    NEW java/lang/OutOfMemoryError
    DUP
    INVOKESPECIAL java/lang/OutOfMemoryError.<init> ()V
    ATHROW
   L9
    LINENUMBER 96 L9
   FRAME FULL [java/lang/String java/lang/String java/lang/String I java/lang/String java/lang/String I I I I I] []
    NEW java/lang/StringBuilder
    DUP
    ILOAD 10
    INVOKESPECIAL java/lang/StringBuilder.<init> (I)V
    ASTORE 11
   L10
    LINENUMBER 98 L10
    ICONST_0
    ISTORE 12
   L11
    LINENUMBER 100 L11
   FRAME FULL [java/lang/String java/lang/String java/lang/String I java/lang/String java/lang/String I I I I I java/lang/StringBuilder I] []
    ALOAD 11
    ALOAD 5
    CHECKCAST java/lang/CharSequence
    ILOAD 12
    ILOAD 7
    INVOKEVIRTUAL java/lang/StringBuilder.append (Ljava/lang/CharSequence;II)Ljava/lang/StringBuilder;
    ALOAD 2
    INVOKEVIRTUAL java/lang/StringBuilder.append (Ljava/lang/String;)Ljava/lang/StringBuilder;
    POP
   L12
    LINENUMBER 101 L12
    ILOAD 7
    ILOAD 8
    IADD
    ISTORE 12
   L13
    LINENUMBER 102 L13
    ILOAD 7
    ALOAD 5
    INVOKEVIRTUAL java/lang/String.length ()I
    IF_ICMPGE L14
   L15
    LINENUMBER 103 L15
    ALOAD 5
    CHECKCAST java/lang/CharSequence
    ALOAD 1
    ILOAD 7
    ILOAD 9
    IADD
    ILOAD 3
    INVOKESTATIC kotlin/text/StringsKt.indexOf (Ljava/lang/CharSequence;Ljava/lang/String;IZ)I
    ISTORE 7
   L16
    LINENUMBER 104 L16
    ILOAD 7
    IFGT L11
   L14
    LINENUMBER 105 L14
   FRAME FULL [java/lang/String java/lang/String java/lang/String I java/lang/String java/lang/String I I I I I java/lang/StringBuilder I] []
    ALOAD 11
    ALOAD 5
    CHECKCAST java/lang/CharSequence
    ILOAD 12
    ALOAD 5
    INVOKEVIRTUAL java/lang/String.length ()I
    INVOKEVIRTUAL java/lang/StringBuilder.append (Ljava/lang/CharSequence;II)Ljava/lang/StringBuilder;
    INVOKEVIRTUAL java/lang/StringBuilder.toString ()Ljava/lang/String;
    DUP
    LDC "stringBuilder.append(this, i, length).toString()"
    INVOKESTATIC kotlin/jvm/internal/Intrinsics.checkNotNullExpressionValue (Ljava/lang/Object;Ljava/lang/String;)V
    ARETURN
   L17
    LOCALVARIABLE $i$a$-run-StringsKt__StringsJVMKt$replace$2 I L3 L17 6
    LOCALVARIABLE occurrenceIndex I L4 L17 7
    LOCALVARIABLE oldValueLength I L6 L17 8
    LOCALVARIABLE searchStep I L7 L17 9
    LOCALVARIABLE newLengthHint I L8 L17 10
    LOCALVARIABLE stringBuilder Ljava/lang/StringBuilder; L10 L17 11
    LOCALVARIABLE i I L11 L17 12
    LOCALVARIABLE $this$replace_u24lambda_u2d2 Ljava/lang/String; L2 L17 5
    LOCALVARIABLE $this$replace Ljava/lang/String; L0 L17 0
    LOCALVARIABLE oldValue Ljava/lang/String; L0 L17 1
    LOCALVARIABLE newValue Ljava/lang/String; L0 L17 2
    LOCALVARIABLE ignoreCase Z L0 L17 3
    MAXSTACK = 4
    MAXLOCALS = 13

  // access flags 0x19
  public final static replace(Ljava/lang/String;CCZ)Ljava/lang/String;
   L0
    ALOAD 0
    LDC "<this>"
    INVOKESTATIC kotlin/jvm/internal/Intrinsics.checkNotNullParameter (Ljava/lang/Object;Ljava/lang/String;)V
   L1
    LINENUMBER 70 L1
    ILOAD 3
    IFNE L2
    ALOAD 0
    ILOAD 1
    ILOAD 2
    INVOKEVIRTUAL java/lang/String.replace (CC)Ljava/lang/String;
    DUP
    LDC "this as java.lang.String\u2026replace(oldChar, newChar)"
    INVOKESTATIC kotlin/jvm/internal/Intrinsics.checkNotNullExpressionValue (Ljava/lang/Object;Ljava/lang/String;)V
    ARETURN
   L2
    LINENUMBER 72 L2
   FRAME FULL [java/lang/String I I I] []
    ALOAD 0
    INVOKEVIRTUAL java/lang/String.length ()I
    ISTORE 4
    NEW java/lang/StringBuilder
    DUP
    ILOAD 4
    INVOKESPECIAL java/lang/StringBuilder.<init> (I)V
    ASTORE 5
    ALOAD 5
    ASTORE 6
   L3
    ICONST_0
    ISTORE 7
   L4
    LINENUMBER 73 L4
    ALOAD 0
    CHECKCAST java/lang/CharSequence
    ASTORE 8
   L5
    ICONST_0
    ISTORE 9
   L6
    LINENUMBER 826 L6
    ICONST_0
    ISTORE 10
   L7
   FRAME FULL [java/lang/String I I I I java/lang/StringBuilder java/lang/StringBuilder I java/lang/CharSequence I I] []
    ILOAD 10
    ALOAD 8
    INVOKEINTERFACE java/lang/CharSequence.length ()I (itf)
    IF_ICMPGE L8
    ALOAD 8
    ILOAD 10
    INVOKEINTERFACE java/lang/CharSequence.charAt (I)C (itf)
    ISTORE 11
   L9
    ILOAD 11
    ISTORE 12
   L10
    ICONST_0
    ISTORE 13
   L11
    LINENUMBER 74 L11
    ALOAD 6
    ILOAD 12
    ILOAD 1
    ILOAD 3
    INVOKESTATIC kotlin/text/CharsKt.equals (CCZ)Z
    IFEQ L12
    ILOAD 2
    GOTO L13
   L12
   FRAME FULL [java/lang/String I I I I java/lang/StringBuilder java/lang/StringBuilder I java/lang/CharSequence I I I I I] [java/lang/StringBuilder]
    ILOAD 12
   L13
   FRAME FULL [java/lang/String I I I I java/lang/StringBuilder java/lang/StringBuilder I java/lang/CharSequence I I I I I] [java/lang/StringBuilder I]
    INVOKEVIRTUAL java/lang/StringBuilder.append (C)Ljava/lang/StringBuilder;
    POP
   L14
    LINENUMBER 75 L14
    NOP
   L15
    IINC 10 1
    GOTO L7
   L8
    LINENUMBER 827 L8
   FRAME FULL [java/lang/String I I I I java/lang/StringBuilder java/lang/StringBuilder I java/lang/CharSequence I I] []
    NOP
   L16
    LINENUMBER 76 L16
    NOP
   L17
    LINENUMBER 72 L17
    ALOAD 5
    INVOKEVIRTUAL java/lang/StringBuilder.toString ()Ljava/lang/String;
    DUP
    LDC "StringBuilder(capacity).\u2026builderAction).toString()"
    INVOKESTATIC kotlin/jvm/internal/Intrinsics.checkNotNullExpressionValue (Ljava/lang/Object;Ljava/lang/String;)V
   L18
    LINENUMBER 72 L18
    ARETURN
   L19
    LOCALVARIABLE $i$a$-forEach-StringsKt__StringsJVMKt$replace$1$1 I L11 L15 13
    LOCALVARIABLE c C L10 L15 12
    LOCALVARIABLE element$iv C L9 L8 11
    LOCALVARIABLE $i$f$forEach I L6 L16 9
    LOCALVARIABLE $this$forEach$iv Ljava/lang/CharSequence; L5 L16 8
    LOCALVARIABLE $i$a$-buildString-StringsKt__StringsJVMKt$replace$1 I L4 L17 7
    LOCALVARIABLE $this$replace_u24lambda_u2d1 Ljava/lang/StringBuilder; L3 L17 6
    LOCALVARIABLE $this$replace Ljava/lang/String; L0 L19 0
    LOCALVARIABLE oldChar C L0 L19 1
    LOCALVARIABLE newChar C L0 L19 2
    LOCALVARIABLE ignoreCase Z L0 L19 3
    MAXSTACK = 4
    MAXLOCALS = 14

  // access flags 0x19
  public final static replaceFirst(Ljava/lang/String;CCZ)Ljava/lang/String;
   L0
    ALOAD 0
    LDC "<this>"
    INVOKESTATIC kotlin/jvm/internal/Intrinsics.checkNotNullParameter (Ljava/lang/Object;Ljava/lang/String;)V
   L1
    LINENUMBER 114 L1
    ALOAD 0
    CHECKCAST java/lang/CharSequence
    ILOAD 1
    ICONST_0
    ILOAD 3
    ICONST_2
    ACONST_NULL
    INVOKESTATIC kotlin/text/StringsKt.indexOf$default (Ljava/lang/CharSequence;CIZILjava/lang/Object;)I
    ISTORE 4
   L2
    LINENUMBER 115 L2
    ILOAD 4
    IFGE L3
    ALOAD 0
    GOTO L4
   L3
   FRAME FULL [java/lang/String I I I I] []
    ALOAD 0
    ASTORE 5
    ILOAD 4
    ICONST_1
    IADD
    ISTORE 6
    ILOAD 2
    INVOKESTATIC java/lang/String.valueOf (C)Ljava/lang/String;
    CHECKCAST java/lang/CharSequence
    ASTORE 7
    ALOAD 5
    CHECKCAST java/lang/CharSequence
    ILOAD 4
    ILOAD 6
    ALOAD 7
    INVOKESTATIC kotlin/text/StringsKt.replaceRange (Ljava/lang/CharSequence;IILjava/lang/CharSequence;)Ljava/lang/CharSequence;
    INVOKEVIRTUAL java/lang/Object.toString ()Ljava/lang/String;
   L4
    LINENUMBER 115 L4
   FRAME FULL [java/lang/String I I I I] [java/lang/String]
    ARETURN
   L5
    LOCALVARIABLE index I L2 L5 4
    LOCALVARIABLE $this$replaceFirst Ljava/lang/String; L0 L5 0
    LOCALVARIABLE oldChar C L0 L5 1
    LOCALVARIABLE newChar C L0 L5 2
    LOCALVARIABLE ignoreCase Z L0 L5 3
    MAXSTACK = 6
    MAXLOCALS = 8

  // access flags 0x19
  public final static replaceFirst(Ljava/lang/String;Ljava/lang/String;Ljava/lang/String;Z)Ljava/lang/String;
   L0
    ALOAD 0
    LDC "<this>"
    INVOKESTATIC kotlin/jvm/internal/Intrinsics.checkNotNullParameter (Ljava/lang/Object;Ljava/lang/String;)V
    ALOAD 1
    LDC "oldValue"
    INVOKESTATIC kotlin/jvm/internal/Intrinsics.checkNotNullParameter (Ljava/lang/Object;Ljava/lang/String;)V
    ALOAD 2
    LDC "newValue"
    INVOKESTATIC kotlin/jvm/internal/Intrinsics.checkNotNullParameter (Ljava/lang/Object;Ljava/lang/String;)V
   L1
    LINENUMBER 124 L1
    ALOAD 0
    CHECKCAST java/lang/CharSequence
    ALOAD 1
    ICONST_0
    ILOAD 3
    ICONST_2
    ACONST_NULL
    INVOKESTATIC kotlin/text/StringsKt.indexOf$default (Ljava/lang/CharSequence;Ljava/lang/String;IZILjava/lang/Object;)I
    ISTORE 4
   L2
    LINENUMBER 125 L2
    ILOAD 4
    IFGE L3
    ALOAD 0
    GOTO L4
   L3
   FRAME FULL [java/lang/String java/lang/String java/lang/String I I] []
    ALOAD 0
    ASTORE 5
    ILOAD 4
    ALOAD 1
    INVOKEVIRTUAL java/lang/String.length ()I
    IADD
    ISTORE 6
    ALOAD 5
    CHECKCAST java/lang/CharSequence
    ILOAD 4
    ILOAD 6
    ALOAD 2
    CHECKCAST java/lang/CharSequence
    INVOKESTATIC kotlin/text/StringsKt.replaceRange (Ljava/lang/CharSequence;IILjava/lang/CharSequence;)Ljava/lang/CharSequence;
    INVOKEVIRTUAL java/lang/Object.toString ()Ljava/lang/String;
   L4
    LINENUMBER 125 L4
   FRAME FULL [java/lang/String java/lang/String java/lang/String I I] [java/lang/String]
    ARETURN
   L5
    LOCALVARIABLE index I L2 L5 4
    LOCALVARIABLE $this$replaceFirst Ljava/lang/String; L0 L5 0
    LOCALVARIABLE oldValue Ljava/lang/String; L0 L5 1
    LOCALVARIABLE newValue Ljava/lang/String; L0 L5 2
    LOCALVARIABLE ignoreCase Z L0 L5 3
    MAXSTACK = 6
    MAXLOCALS = 7

  // access flags 0x19
  // signature (Ljava/lang/CharSequence;Ljava/util/regex/Pattern;I)Ljava/util/List<Ljava/lang/String;>;
  // declaration: java.util.List<java.lang.String> split(java.lang.CharSequence, java.util.regex.Pattern, int)
  public final static split(Ljava/lang/CharSequence;Ljava/util/regex/Pattern;I)Ljava/util/List;
   L0
    ALOAD 0
    LDC "<this>"
    INVOKESTATIC kotlin/jvm/internal/Intrinsics.checkNotNullParameter (Ljava/lang/Object;Ljava/lang/String;)V
    ALOAD 1
    LDC "regex"
    INVOKESTATIC kotlin/jvm/internal/Intrinsics.checkNotNullParameter (Ljava/lang/Object;Ljava/lang/String;)V
   L1
    LINENUMBER 393 L1
    ILOAD 2
    INVOKESTATIC kotlin/text/StringsKt.requireNonNegativeLimit (I)V
   L2
    LINENUMBER 394 L2
    ALOAD 1
    ALOAD 0
    ILOAD 2
    IFNE L3
    ICONST_M1
    GOTO L4
   L3
   FRAME FULL [java/lang/CharSequence java/util/regex/Pattern I] [java/util/regex/Pattern java/lang/CharSequence]
    ILOAD 2
   L4
   FRAME FULL [java/lang/CharSequence java/util/regex/Pattern I] [java/util/regex/Pattern java/lang/CharSequence I]
    INVOKEVIRTUAL java/util/regex/Pattern.split (Ljava/lang/CharSequence;I)[Ljava/lang/String;
    DUP
    LDC "regex.split(this, if (limit == 0) -1 else limit)"
    INVOKESTATIC kotlin/jvm/internal/Intrinsics.checkNotNullExpressionValue (Ljava/lang/Object;Ljava/lang/String;)V
    CHECKCAST [Ljava/lang/Object;
    INVOKESTATIC kotlin/collections/ArraysKt.asList ([Ljava/lang/Object;)Ljava/util/List;
    ARETURN
   L5
    LOCALVARIABLE $this$split Ljava/lang/CharSequence; L0 L5 0
    LOCALVARIABLE regex Ljava/util/regex/Pattern; L0 L5 1
    LOCALVARIABLE limit I L0 L5 2
    MAXSTACK = 3
    MAXLOCALS = 3

  // access flags 0x1A
  private final static toLowerCase(Ljava/lang/String;)Ljava/lang/String;
  @Lkotlin/Deprecated;(message="Use lowercase() instead.", replaceWith=@Lkotlin/ReplaceWith;(expression="lowercase(Locale.getDefault())", imports={"java.util.Locale"}))
  @Lkotlin/DeprecatedSinceKotlin;(warningSince="1.5")
   L0
    ALOAD 0
    LDC "<this>"
    INVOKESTATIC kotlin/jvm/internal/Intrinsics.checkNotNullParameter (Ljava/lang/Object;Ljava/lang/String;)V
   L1
    LINENUMBER 155 L1
    ALOAD 0
    INVOKEVIRTUAL java/lang/String.toLowerCase ()Ljava/lang/String;
    DUP
    LDC "this as java.lang.String).toLowerCase()"
    INVOKESTATIC kotlin/jvm/internal/Intrinsics.checkNotNullExpressionValue (Ljava/lang/Object;Ljava/lang/String;)V
    ARETURN
   L2
    LOCALVARIABLE $this$toLowerCase Ljava/lang/String; L0 L2 0
    MAXSTACK = 3
    MAXLOCALS = 1

  // access flags 0x1A
  private final static toLowerCase(Ljava/lang/String;Ljava/util/Locale;)Ljava/lang/String;
  @Lkotlin/Deprecated;(message="Use lowercase() instead.", replaceWith=@Lkotlin/ReplaceWith;(expression="lowercase(locale)", imports={}))
  @Lkotlin/DeprecatedSinceKotlin;(warningSince="1.5")
   L0
    ALOAD 0
    LDC "<this>"
    INVOKESTATIC kotlin/jvm/internal/Intrinsics.checkNotNullParameter (Ljava/lang/Object;Ljava/lang/String;)V
    ALOAD 1
    LDC "locale"
    INVOKESTATIC kotlin/jvm/internal/Intrinsics.checkNotNullParameter (Ljava/lang/Object;Ljava/lang/String;)V
   L1
    LINENUMBER 664 L1
    ALOAD 0
    ALOAD 1
    INVOKEVIRTUAL java/lang/String.toLowerCase (Ljava/util/Locale;)Ljava/lang/String;
    DUP
    LDC "this as java.lang.String).toLowerCase(locale)"
    INVOKESTATIC kotlin/jvm/internal/Intrinsics.checkNotNullExpressionValue (Ljava/lang/Object;Ljava/lang/String;)V
   L2
    LINENUMBER 664 L2
    ARETURN
   L3
    LOCALVARIABLE $this$toLowerCase Ljava/lang/String; L0 L3 0
    LOCALVARIABLE locale Ljava/util/Locale; L0 L3 1
    MAXSTACK = 3
    MAXLOCALS = 2

  // access flags 0x1A
  private final static toUpperCase(Ljava/lang/String;Ljava/util/Locale;)Ljava/lang/String;
  @Lkotlin/Deprecated;(message="Use uppercase() instead.", replaceWith=@Lkotlin/ReplaceWith;(expression="uppercase(locale)", imports={}))
  @Lkotlin/DeprecatedSinceKotlin;(warningSince="1.5")
   L0
    ALOAD 0
    LDC "<this>"
    INVOKESTATIC kotlin/jvm/internal/Intrinsics.checkNotNullParameter (Ljava/lang/Object;Ljava/lang/String;)V
    ALOAD 1
    LDC "locale"
    INVOKESTATIC kotlin/jvm/internal/Intrinsics.checkNotNullParameter (Ljava/lang/Object;Ljava/lang/String;)V
   L1
    LINENUMBER 685 L1
    ALOAD 0
    ALOAD 1
    INVOKEVIRTUAL java/lang/String.toUpperCase (Ljava/util/Locale;)Ljava/lang/String;
    DUP
    LDC "this as java.lang.String).toUpperCase(locale)"
    INVOKESTATIC kotlin/jvm/internal/Intrinsics.checkNotNullExpressionValue (Ljava/lang/Object;Ljava/lang/String;)V
   L2
    LINENUMBER 685 L2
    ARETURN
   L3
    LOCALVARIABLE $this$toUpperCase Ljava/lang/String; L0 L3 0
    LOCALVARIABLE locale Ljava/util/Locale; L0 L3 1
    MAXSTACK = 3
    MAXLOCALS = 2

  // access flags 0x1A
  private final static toUpperCase(Ljava/lang/String;)Ljava/lang/String;
  @Lkotlin/Deprecated;(message="Use uppercase() instead.", replaceWith=@Lkotlin/ReplaceWith;(expression="uppercase(Locale.getDefault())", imports={"java.util.Locale"}))
  @Lkotlin/DeprecatedSinceKotlin;(warningSince="1.5")
   L0
    ALOAD 0
    LDC "<this>"
    INVOKESTATIC kotlin/jvm/internal/Intrinsics.checkNotNullParameter (Ljava/lang/Object;Ljava/lang/String;)V
   L1
    LINENUMBER 134 L1
    ALOAD 0
    INVOKEVIRTUAL java/lang/String.toUpperCase ()Ljava/lang/String;
    DUP
    LDC "this as java.lang.String).toUpperCase()"
    INVOKESTATIC kotlin/jvm/internal/Intrinsics.checkNotNullExpressionValue (Ljava/lang/Object;Ljava/lang/String;)V
    ARETURN
   L2
    LOCALVARIABLE $this$toUpperCase Ljava/lang/String; L0 L2 0
    MAXSTACK = 3
    MAXLOCALS = 1

  // access flags 0x19
  public final static isBlank(Ljava/lang/CharSequence;)Z
   L0
    ALOAD 0
    LDC "<this>"
    INVOKESTATIC kotlin/jvm/internal/Intrinsics.checkNotNullParameter (Ljava/lang/Object;Ljava/lang/String;)V
   L1
    LINENUMBER 621 L1
    ALOAD 0
    INVOKEINTERFACE java/lang/CharSequence.length ()I (itf)
    IFEQ L2
    ALOAD 0
    INVOKESTATIC kotlin/text/StringsKt.getIndices (Ljava/lang/CharSequence;)Lkotlin/ranges/IntRange;
    CHECKCAST java/lang/Iterable
    ASTORE 1
   L3
    ICONST_0
    ISTORE 2
   L4
    LINENUMBER 829 L4
    ALOAD 1
    INSTANCEOF java/util/Collection
    IFEQ L5
    ALOAD 1
    CHECKCAST java/util/Collection
    INVOKEINTERFACE java/util/Collection.isEmpty ()Z (itf)
    IFEQ L5
    ICONST_1
    GOTO L6
   L5
    LINENUMBER 830 L5
   FRAME FULL [java/lang/CharSequence java/lang/Iterable I] []
    ALOAD 1
    INVOKEINTERFACE java/lang/Iterable.iterator ()Ljava/util/Iterator; (itf)
    ASTORE 3
   L7
   FRAME FULL [java/lang/CharSequence java/lang/Iterable I java/util/Iterator] []
    ALOAD 3
    INVOKEINTERFACE java/util/Iterator.hasNext ()Z (itf)
    IFEQ L8
    ALOAD 3
    CHECKCAST kotlin/collections/IntIterator
    INVOKEVIRTUAL kotlin/collections/IntIterator.nextInt ()I
    ISTORE 4
   L9
    ILOAD 4
    ISTORE 5
   L10
    ICONST_0
    ISTORE 6
   L11
    LINENUMBER 621 L11
    ALOAD 0
    ILOAD 5
    INVOKEINTERFACE java/lang/CharSequence.charAt (I)C (itf)
    INVOKESTATIC kotlin/text/CharsKt.isWhitespace (C)Z
   L12
    IFNE L7
    ICONST_0
    GOTO L6
   L8
    LINENUMBER 831 L8
   FRAME FULL [java/lang/CharSequence java/lang/Iterable I java/util/Iterator] []
    ICONST_1
   L6
   FRAME FULL [java/lang/CharSequence java/lang/Iterable I] [I]
    IFEQ L13
   L2
   FRAME FULL [java/lang/CharSequence] []
    ICONST_1
    GOTO L14
   L13
   FRAME FULL [java/lang/CharSequence java/lang/Iterable I] []
    ICONST_0
   L14
    LINENUMBER 621 L14
   FRAME FULL [java/lang/CharSequence] [I]
    IRETURN
   L15
    LOCALVARIABLE $i$a$-all-StringsKt__StringsJVMKt$isBlank$1 I L11 L12 6
    LOCALVARIABLE it I L10 L12 5
    LOCALVARIABLE element$iv I L9 L8 4
    LOCALVARIABLE $i$f$all I L4 L6 2
    LOCALVARIABLE $this$all$iv Ljava/lang/Iterable; L3 L6 1
    LOCALVARIABLE $this$isBlank Ljava/lang/CharSequence; L0 L15 0
    MAXSTACK = 2
    MAXLOCALS = 7

  // access flags 0x19
  public final static repeat(Ljava/lang/CharSequence;I)Ljava/lang/String;
   L0
    ALOAD 0
    LDC "<this>"
    INVOKESTATIC kotlin/jvm/internal/Intrinsics.checkNotNullParameter (Ljava/lang/Object;Ljava/lang/String;)V
   L1
    LINENUMBER 795 L1
    ILOAD 1
    IFLT L2
    ICONST_1
    GOTO L3
   L2
   FRAME FULL [java/lang/CharSequence I] []
    ICONST_0
   L3
   FRAME FULL [java/lang/CharSequence I] [I]
    ISTORE 2
    ILOAD 2
    IFNE L4
   L5
    LINENUMBER 828 L5
    ICONST_0
    ISTORE 3
   L6
    LINENUMBER 795 L6
    NEW java/lang/StringBuilder
    DUP
    INVOKESPECIAL java/lang/StringBuilder.<init> ()V
    LDC "Count 'n' must be non-negative, but was "
    INVOKEVIRTUAL java/lang/StringBuilder.append (Ljava/lang/String;)Ljava/lang/StringBuilder;
    ILOAD 1
    INVOKEVIRTUAL java/lang/StringBuilder.append (I)Ljava/lang/StringBuilder;
    BIPUSH 46
    INVOKEVIRTUAL java/lang/StringBuilder.append (C)Ljava/lang/StringBuilder;
    INVOKEVIRTUAL java/lang/StringBuilder.toString ()Ljava/lang/String;
   L7
    LINENUMBER 795 L7
    ASTORE 3
    NEW java/lang/IllegalArgumentException
    DUP
    ALOAD 3
    INVOKEVIRTUAL java/lang/Object.toString ()Ljava/lang/String;
    INVOKESPECIAL java/lang/IllegalArgumentException.<init> (Ljava/lang/String;)V
    ATHROW
   L4
    LINENUMBER 797 L4
   FRAME FULL [java/lang/CharSequence I I] []
    ILOAD 1
    TABLESWITCH
      0: L8
      1: L9
      default: L10
   L8
    LINENUMBER 798 L8
   FRAME FULL [java/lang/CharSequence I I] []
    LDC ""
    GOTO L11
   L9
    LINENUMBER 799 L9
   FRAME FULL [java/lang/CharSequence I I] []
    ALOAD 0
    INVOKEVIRTUAL java/lang/Object.toString ()Ljava/lang/String;
    GOTO L11
   L10
    LINENUMBER 801 L10
   FRAME FULL [java/lang/CharSequence I I] []
    ALOAD 0
    INVOKEINTERFACE java/lang/CharSequence.length ()I (itf)
    TABLESWITCH
      0: L12
      1: L13
      default: L14
   L12
    LINENUMBER 802 L12
   FRAME FULL [java/lang/CharSequence I I] []
    LDC ""
    GOTO L11
   L13
    LINENUMBER 803 L13
   FRAME FULL [java/lang/CharSequence I I] []
    ALOAD 0
    ICONST_0
    INVOKEINTERFACE java/lang/CharSequence.charAt (I)C (itf)
    ISTORE 4
    ILOAD 4
    ISTORE 5
   L15
    LINENUMBER 828 L15
    ICONST_0
    ISTORE 6
   L16
    LINENUMBER 803 L16
    ICONST_0
    ISTORE 7
    ILOAD 1
    NEWARRAY T_CHAR
    ASTORE 8
   L17
   FRAME FULL [java/lang/CharSequence I I T I I I I [C] []
    ILOAD 7
    ILOAD 1
    IF_ICMPGE L18
    ILOAD 7
    ISTORE 9
    ALOAD 8
    ILOAD 9
    ILOAD 5
    CASTORE
    IINC 7 1
    GOTO L17
   L18
   FRAME FULL [java/lang/CharSequence I I T I I I I [C] []
    ALOAD 8
    ASTORE 7
    NEW java/lang/String
    DUP
    ALOAD 7
    INVOKESPECIAL java/lang/String.<init> ([C)V
   L19
    LINENUMBER 803 L19
    NOP
   L20
    LINENUMBER 803 L20
    GOTO L11
   L14
    LINENUMBER 805 L14
   FRAME FULL [java/lang/CharSequence I I] []
    NEW java/lang/StringBuilder
    DUP
    ILOAD 1
    ALOAD 0
    INVOKEINTERFACE java/lang/CharSequence.length ()I (itf)
    IMUL
    INVOKESPECIAL java/lang/StringBuilder.<init> (I)V
    ASTORE 5
   L21
    LINENUMBER 806 L21
    NEW kotlin/ranges/IntRange
    DUP
    ICONST_1
    ILOAD 1
    INVOKESPECIAL kotlin/ranges/IntRange.<init> (II)V
    INVOKEVIRTUAL kotlin/ranges/IntRange.iterator ()Lkotlin/collections/IntIterator;
    ASTORE 6
   L22
   FRAME FULL [java/lang/CharSequence I I T T java/lang/StringBuilder kotlin/collections/IntIterator] []
    ALOAD 6
    INVOKEVIRTUAL kotlin/collections/IntIterator.hasNext ()Z
    IFEQ L23
    ALOAD 6
    INVOKEVIRTUAL kotlin/collections/IntIterator.nextInt ()I
    ISTORE 7
   L24
    LINENUMBER 807 L24
    ALOAD 5
    ALOAD 0
    INVOKEVIRTUAL java/lang/StringBuilder.append (Ljava/lang/CharSequence;)Ljava/lang/StringBuilder;
    POP
   L25
    GOTO L22
   L23
    LINENUMBER 809 L23
   FRAME FULL [java/lang/CharSequence I I T T java/lang/StringBuilder kotlin/collections/IntIterator] []
    ALOAD 5
    INVOKEVIRTUAL java/lang/StringBuilder.toString ()Ljava/lang/String;
   L26
    LINENUMBER 804 L26
    ASTORE 4
   L27
    LINENUMBER 807 L27
    ALOAD 4
    LDC "{\n                    va\u2026tring()\n                }"
    INVOKESTATIC kotlin/jvm/internal/Intrinsics.checkNotNullExpressionValue (Ljava/lang/Object;Ljava/lang/String;)V
    ALOAD 4
   L11
    LINENUMBER 797 L11
   FRAME FULL [java/lang/CharSequence I I] [java/lang/String]
    ARETURN
   L28
    LOCALVARIABLE $i$a$-require-StringsKt__StringsJVMKt$repeat$1 I L6 L7 3
    LOCALVARIABLE $i$a$-let-StringsKt__StringsJVMKt$repeat$2 I L16 L20 6
    LOCALVARIABLE char C L15 L20 5
    LOCALVARIABLE i I L24 L25 7
    LOCALVARIABLE sb Ljava/lang/StringBuilder; L21 L26 5
    LOCALVARIABLE $this$repeat Ljava/lang/CharSequence; L0 L28 0
    LOCALVARIABLE n I L0 L28 1
    MAXSTACK = 4
    MAXLOCALS = 10

  // access flags 0x1A
  private final static toCharArray(Ljava/lang/String;[CIII)[C
   L0
    ALOAD 0
    LDC "<this>"
    INVOKESTATIC kotlin/jvm/internal/Intrinsics.checkNotNullParameter (Ljava/lang/Object;Ljava/lang/String;)V
    ALOAD 1
    LDC "destination"
    INVOKESTATIC kotlin/jvm/internal/Intrinsics.checkNotNullParameter (Ljava/lang/Object;Ljava/lang/String;)V
   L1
    LINENUMBER 325 L1
    ALOAD 0
    ILOAD 3
    ILOAD 4
    ALOAD 1
    ILOAD 2
    INVOKEVIRTUAL java/lang/String.getChars (II[CI)V
   L2
    LINENUMBER 326 L2
    ALOAD 1
    ARETURN
   L3
    LOCALVARIABLE $this$toCharArray Ljava/lang/String; L0 L3 0
    LOCALVARIABLE destination [C L0 L3 1
    LOCALVARIABLE destinationOffset I L0 L3 2
    LOCALVARIABLE startIndex I L0 L3 3
    LOCALVARIABLE endIndex I L0 L3 4
    MAXSTACK = 5
    MAXLOCALS = 5

  // access flags 0x1A
  private final static toCharArray(Ljava/lang/String;)[C
   L0
    ALOAD 0
    LDC "<this>"
    INVOKESTATIC kotlin/jvm/internal/Intrinsics.checkNotNullParameter (Ljava/lang/Object;Ljava/lang/String;)V
   L1
    LINENUMBER 308 L1
    ALOAD 0
    INVOKEVIRTUAL java/lang/String.toCharArray ()[C
    DUP
    LDC "this as java.lang.String).toCharArray()"
    INVOKESTATIC kotlin/jvm/internal/Intrinsics.checkNotNullExpressionValue (Ljava/lang/Object;Ljava/lang/String;)V
    ARETURN
   L2
    LOCALVARIABLE $this$toCharArray Ljava/lang/String; L0 L2 0
    MAXSTACK = 3
    MAXLOCALS = 1

  // access flags 0x19
  public final static toCharArray(Ljava/lang/String;II)[C
   L0
    ALOAD 0
    LDC "<this>"
    INVOKESTATIC kotlin/jvm/internal/Intrinsics.checkNotNullParameter (Ljava/lang/Object;Ljava/lang/String;)V
   L1
    LINENUMBER 209 L1
    GETSTATIC kotlin/collections/AbstractList.Companion : Lkotlin/collections/AbstractList$Companion;
    ILOAD 1
    ILOAD 2
    ALOAD 0
    INVOKEVIRTUAL java/lang/String.length ()I
    INVOKEVIRTUAL kotlin/collections/AbstractList$Companion.checkBoundsIndexes$kotlin_stdlib (III)V
   L2
    LINENUMBER 210 L2
    ALOAD 0
    ASTORE 3
    ILOAD 2
    ILOAD 1
    ISUB
    NEWARRAY T_CHAR
    ASTORE 4
    ICONST_0
    ISTORE 5
    ALOAD 3
    ILOAD 1
    ILOAD 2
    ALOAD 4
    ILOAD 5
    INVOKEVIRTUAL java/lang/String.getChars (II[CI)V
    ALOAD 4
   L3
    LINENUMBER 210 L3
    ARETURN
   L4
    LOCALVARIABLE $this$toCharArray Ljava/lang/String; L0 L4 0
    LOCALVARIABLE startIndex I L0 L4 1
    LOCALVARIABLE endIndex I L0 L4 2
    MAXSTACK = 5
    MAXLOCALS = 6

  // access flags 0x9A
  private final static varargs format(Lkotlin/jvm/internal/StringCompanionObject;Ljava/lang/String;[Ljava/lang/Object;)Ljava/lang/String;
   L0
    ALOAD 0
    LDC "<this>"
    INVOKESTATIC kotlin/jvm/internal/Intrinsics.checkNotNullParameter (Ljava/lang/Object;Ljava/lang/String;)V
    ALOAD 1
    LDC "format"
    INVOKESTATIC kotlin/jvm/internal/Intrinsics.checkNotNullParameter (Ljava/lang/Object;Ljava/lang/String;)V
    ALOAD 2
    LDC "args"
    INVOKESTATIC kotlin/jvm/internal/Intrinsics.checkNotNullParameter (Ljava/lang/Object;Ljava/lang/String;)V
   L1
    LINENUMBER 341 L1
    ALOAD 1
    ALOAD 2
    ALOAD 2
    ARRAYLENGTH
    INVOKESTATIC java/util/Arrays.copyOf ([Ljava/lang/Object;I)[Ljava/lang/Object;
    INVOKESTATIC java/lang/String.format (Ljava/lang/String;[Ljava/lang/Object;)Ljava/lang/String;
    DUP
    LDC "format(format, *args)"
    INVOKESTATIC kotlin/jvm/internal/Intrinsics.checkNotNullExpressionValue (Ljava/lang/Object;Ljava/lang/String;)V
    ARETURN
   L2
    LOCALVARIABLE $this$format Lkotlin/jvm/internal/StringCompanionObject; L0 L2 0
    LOCALVARIABLE format Ljava/lang/String; L0 L2 1
    LOCALVARIABLE args [Ljava/lang/Object; L0 L2 2
    MAXSTACK = 3
    MAXLOCALS = 3

  // access flags 0x109A
  private final static synthetic varargs format(Lkotlin/jvm/internal/StringCompanionObject;Ljava/util/Locale;Ljava/lang/String;[Ljava/lang/Object;)Ljava/lang/String;
  @Lkotlin/Deprecated;(message="Use Kotlin compiler 1.4 to avoid deprecation warning.")
  @Lkotlin/DeprecatedSinceKotlin;(hiddenSince="1.4")
   L0
    ALOAD 0
    LDC "<this>"
    INVOKESTATIC kotlin/jvm/internal/Intrinsics.checkNotNullParameter (Ljava/lang/Object;Ljava/lang/String;)V
    ALOAD 1
    LDC "locale"
    INVOKESTATIC kotlin/jvm/internal/Intrinsics.checkNotNullParameter (Ljava/lang/Object;Ljava/lang/String;)V
    ALOAD 2
    LDC "format"
    INVOKESTATIC kotlin/jvm/internal/Intrinsics.checkNotNullParameter (Ljava/lang/Object;Ljava/lang/String;)V
    ALOAD 3
    LDC "args"
    INVOKESTATIC kotlin/jvm/internal/Intrinsics.checkNotNullParameter (Ljava/lang/Object;Ljava/lang/String;)V
   L1
    LINENUMBER 369 L1
    ALOAD 1
    ALOAD 2
    ALOAD 3
    ALOAD 3
    ARRAYLENGTH
    INVOKESTATIC java/util/Arrays.copyOf ([Ljava/lang/Object;I)[Ljava/lang/Object;
    INVOKESTATIC java/lang/String.format (Ljava/util/Locale;Ljava/lang/String;[Ljava/lang/Object;)Ljava/lang/String;
    DUP
    LDC "format(locale, format, *args)"
    INVOKESTATIC kotlin/jvm/internal/Intrinsics.checkNotNullExpressionValue (Ljava/lang/Object;Ljava/lang/String;)V
    ARETURN
   L2
    LOCALVARIABLE $this$format Lkotlin/jvm/internal/StringCompanionObject; L0 L2 0
    LOCALVARIABLE locale Ljava/util/Locale; L0 L2 1
    LOCALVARIABLE format Ljava/lang/String; L0 L2 2
    LOCALVARIABLE args [Ljava/lang/Object; L0 L2 3
    MAXSTACK = 4
    MAXLOCALS = 4

  // access flags 0x109A
  private final static synthetic varargs format(Ljava/lang/String;Ljava/util/Locale;[Ljava/lang/Object;)Ljava/lang/String;
  @Lkotlin/Deprecated;(message="Use Kotlin compiler 1.4 to avoid deprecation warning.")
  @Lkotlin/DeprecatedSinceKotlin;(hiddenSince="1.4")
   L0
    ALOAD 0
    LDC "<this>"
    INVOKESTATIC kotlin/jvm/internal/Intrinsics.checkNotNullParameter (Ljava/lang/Object;Ljava/lang/String;)V
    ALOAD 1
    LDC "locale"
    INVOKESTATIC kotlin/jvm/internal/Intrinsics.checkNotNullParameter (Ljava/lang/Object;Ljava/lang/String;)V
    ALOAD 2
    LDC "args"
    INVOKESTATIC kotlin/jvm/internal/Intrinsics.checkNotNullParameter (Ljava/lang/Object;Ljava/lang/String;)V
   L1
    LINENUMBER 350 L1
    ALOAD 1
    ALOAD 0
    ALOAD 2
    ALOAD 2
    ARRAYLENGTH
    INVOKESTATIC java/util/Arrays.copyOf ([Ljava/lang/Object;I)[Ljava/lang/Object;
    INVOKESTATIC java/lang/String.format (Ljava/util/Locale;Ljava/lang/String;[Ljava/lang/Object;)Ljava/lang/String;
    DUP
    LDC "format(locale, this, *args)"
    INVOKESTATIC kotlin/jvm/internal/Intrinsics.checkNotNullExpressionValue (Ljava/lang/Object;Ljava/lang/String;)V
    ARETURN
   L2
    LOCALVARIABLE $this$format Ljava/lang/String; L0 L2 0
    LOCALVARIABLE locale Ljava/util/Locale; L0 L2 1
    LOCALVARIABLE args [Ljava/lang/Object; L0 L2 2
    MAXSTACK = 4
    MAXLOCALS = 3

  // access flags 0x9A
  private final static varargs format(Ljava/lang/String;[Ljava/lang/Object;)Ljava/lang/String;
   L0
    ALOAD 0
    LDC "<this>"
    INVOKESTATIC kotlin/jvm/internal/Intrinsics.checkNotNullParameter (Ljava/lang/Object;Ljava/lang/String;)V
    ALOAD 1
    LDC "args"
    INVOKESTATIC kotlin/jvm/internal/Intrinsics.checkNotNullParameter (Ljava/lang/Object;Ljava/lang/String;)V
   L1
    LINENUMBER 334 L1
    ALOAD 0
    ALOAD 1
    ALOAD 1
    ARRAYLENGTH
    INVOKESTATIC java/util/Arrays.copyOf ([Ljava/lang/Object;I)[Ljava/lang/Object;
    INVOKESTATIC java/lang/String.format (Ljava/lang/String;[Ljava/lang/Object;)Ljava/lang/String;
    DUP
    LDC "format(this, *args)"
    INVOKESTATIC kotlin/jvm/internal/Intrinsics.checkNotNullExpressionValue (Ljava/lang/Object;Ljava/lang/String;)V
    ARETURN
   L2
    LOCALVARIABLE $this$format Ljava/lang/String; L0 L2 0
    LOCALVARIABLE args [Ljava/lang/Object; L0 L2 1
    MAXSTACK = 3
    MAXLOCALS = 2

  // access flags 0x1A
  private final static intern(Ljava/lang/String;)Ljava/lang/String;
   L0
    ALOAD 0
    LDC "<this>"
    INVOKESTATIC kotlin/jvm/internal/Intrinsics.checkNotNullParameter (Ljava/lang/Object;Ljava/lang/String;)V
   L1
    LINENUMBER 614 L1
    ALOAD 0
    INVOKEVIRTUAL java/lang/String.intern ()Ljava/lang/String;
    DUP
    LDC "this as java.lang.String).intern()"
    INVOKESTATIC kotlin/jvm/internal/Intrinsics.checkNotNullExpressionValue (Ljava/lang/Object;Ljava/lang/String;)V
    ARETURN
   L2
    LOCALVARIABLE $this$intern Ljava/lang/String; L0 L2 0
    MAXSTACK = 3
    MAXLOCALS = 1

  // access flags 0x1A
  private final static toByteArray(Ljava/lang/String;Ljava/nio/charset/Charset;)[B
   L0
    ALOAD 0
    LDC "<this>"
    INVOKESTATIC kotlin/jvm/internal/Intrinsics.checkNotNullParameter (Ljava/lang/Object;Ljava/lang/String;)V
    ALOAD 1
    LDC "charset"
    INVOKESTATIC kotlin/jvm/internal/Intrinsics.checkNotNullParameter (Ljava/lang/Object;Ljava/lang/String;)V
   L1
    LINENUMBER 705 L1
    ALOAD 0
    ALOAD 1
    INVOKEVIRTUAL java/lang/String.getBytes (Ljava/nio/charset/Charset;)[B
    DUP
    LDC "this as java.lang.String).getBytes(charset)"
    INVOKESTATIC kotlin/jvm/internal/Intrinsics.checkNotNullExpressionValue (Ljava/lang/Object;Ljava/lang/String;)V
    ARETURN
   L2
    LOCALVARIABLE $this$toByteArray Ljava/lang/String; L0 L2 0
    LOCALVARIABLE charset Ljava/nio/charset/Charset; L0 L2 1
    MAXSTACK = 3
    MAXLOCALS = 2
}
